Workbook
Name SchemeList: 'Scheme Master'!$B$4:$B$44

Sheet Scheme Master
A1: SCHEME MASTER - PER CANDIDATE RATE
A3: Sr No. | B3: Scheme Name | C3: Per Candidate Rate (₹) | D3: Description | E3: Status
A4: 1 | B4: PMKVY 4.0 | C4: 480 | D4: Pradhan Mantri Kaushal Vikas Yojana | E4: Active
A5: 2 | B5: DDUGKY | C5: 720 | D5: Deen Dayal Upadhyaya Grameen Kaushalya Yojana | E5: Active
A6: 3 | B6: ODOP-RPL | C6: 540 | D6: SSC- Affiliated Scheme
A7: 4 | B7: BSDMA-RPL | C7: 540
A8: 5 | B8: PMAY-G-STT | C8: 720
A9: 6 | B9: VSSY-RPL | C9: 540
A10: 7 | B10: Suryamitra Skill Development Programme | C10: 400
A11: 8 | B11: PMAY-G-RPL | C11: 540
A12: 9 | B12: NON-PMKVY -CSR | C12: 600
A13: 10 | B13: MESC Fee Based | C13: 400
A14: 11 | B14: CSDCI Fee Based | C14: 720
A15: 12 | B15: ITDA-Meity | C15: 400
A16: 13 | B16: Mahajyoti | C16: 600
A17: 14 | B17: (Industry)EPCH-RPL | C17: 360
A18: 15 | B18: CSR | C18: 600
... A47: 47 | B47: PMKUVA | C47: 420
A48: =A47+1 -> 48 | B48: PMKVY-SP-GIF-Mass Employment Jobrole | C48: 480
A49: =A48+1 -> 49 | B49: TOT - PMVK-Advance | C49: 70 | D49: Gems and Jewellery
A50: =A49+1 -> 50 | B50: SANKALP | C50: 400
A51: =A50+1 -> 51 | B51: SDIS-DDU-GKY | C51: 400
A52: =A51+1 -> 52 | B52: SDIS-ORISSA STATE SKILLING SCHEME | C52: 400
A53: =A52+1 -> 53 | B53: SKILL HUB INITIATIVE | C53: 480
A54: =A53+1 -> 54 | B54: Short Term Training | C54: 480
A55: =A54+1 -> 55 | B55: Special Projects | C55: 480
A56: =A55+1 -> 56 | B56: SSC Affiliated: Skill Council for Green Jobs | C56: 400
A57: =A56+1 -> 57 | B57: TOA | C57: 400
A58: =A57+1 -> 58 | B58: TOMA | C58: 600
A59: =A58+1 -> 59 | B59: TOMT | C59: 400
A60: =A59+1 -> 60 | B60: TOMT | C60: 600
A61: =A60+1 -> 61 | B61: TOT | C61: 400
... A70: =A69+1 -> 70 | B70: offline- Oct-2025- 003 | C70: 600
A71: 71 | B71: 3rd Party | C71: 480

Sheet Assessor Master
A1: ASSESSOR MASTER - ON-ROLL ASSESSORS
A3: Sr No. | B3: Assessor Name | C3: Assessor ID | D3: Sector | E3: Phone | F3: Email | G3: Status
A4: 1 | B4: Mohd Haseen | C4: AR10066 | D4: IT-ITeS | E4: 9876543210 | F4: haseen@example.com | G4: Active
A5: 2 | B5: John Assessor | C5: AR10045 | D5: Healthcare | E5: 9876543211 | F5: john@example.com | G5: Active
A6: 3 | B6: Priya Sharma | C6: AR10078 | D6: Electronics | E6: 9876543212 | F6: priya@example.com | G6: Active
A7: 4 | B7: Amit Kumar | C7: AR10092 | D7: Retail | E7: 9876543213 | F7: amit@example.com | G7: Active
A8: 5 | B8: Neha Singh | C8: AR10101 | D8: Beauty & Wellness | E8: 9876543214 | F8: neha@example.com | G8: Active
A10: Note: | B10: Add on-roll assessors here. When an assessor name is entered in the Assessment Tracker, the system auto-detects if they are on-roll. If not found, user must select Freelancer or Special Circumstances.

Sheet Assessment Tracker
A1: Sr No. | B1: Scheme | C1: Batch ID | D1: Day | E1: Sector | F1: Group Status | G1: Job Role | H1: TP Name | I1: District | J1: State | K1: Assessment Start Date | L1: Assessment End Date | M1: Total Candidates | N1: Present | O1: Absent | P1: Male Count | Q1: Female Count | R1: Passed | S1: Failed | T1: Result Date | U1: Result | V1: Pass % | W1: Fail % | X1: Assessor Name | Y1: User ID | Z1: Trainer Name | AA1: Trainer ID | AB1: Rate/Candidate (₹) | AC1: Total Income (₹) | AD1: Assessor Fee (₹) | AE1: TA/DA (₹) | AF1: Total Exp. (₹) | AG1: Profit/Loss (₹) | AH1: Expense % | AI1: Status | AJ1: Remarks | AK1: Assessor Aligned By | AL1: Approved By | AM1: Approval Date | AN1: Decision | AO1: Final Status | AP1: Assessor Invoice | AQ1: Assessor Expenses Tickets | AR1: Payment Status | AS1: Payment Amount | AT1: Payment Reference ID | AU1: Payment Mode | AV1: Payment Slip Uploaded in drive | AW1: Theory Link | AX1: Practical | AY1: Viva
A2: 1 | B2: PM Vishwakarma | C2: 3732880 | D2: Day 6 | E2: Gems and Jewellery | G2: Goldsmith (Sunar)( G&J/N0612 ) | H2: LEARNET SKILLS LIMITED | I2: SARAN | J2: BIHAR | K2: 46113 | L2: 46113 | M2: 34 | N2: 32 | O2: =IF(AND(M2<>"",N2<>""),M2-N2,"") -> 2 | P2: 28 | Q2: =IF(AND(N2<>"",P2<>""),N2-P2,"") -> 4 | R2: 32 | S2: =IF(AND(N2<>"",R2<>""),N2-R2,"") -> 0 | T2: 46113 | U2: Uploaded | V2: =IFERROR(R2/N2,"") -> 1 | W2: =IFERROR(S2/N2,"") -> 0 | X2: Priyanshu Kumar Tiwari | Y2: AR164546 | Z2: Prem Kumar Harishankar Prasad Singh | AA2: TR21465 | AB2: =IFERROR(VLOOKUP(B2,'Scheme Master'!$B$4:$C$79,2,FALSE),"") -> 360 | AC2: =IF(AND(AB2<>"",N2<>""),AB2*N2,"") -> 11520 | AD2: 2000 | AE2: 1000 | AF2: =IF(OR(AD2<>"",AE2<>""),AD2+AE2,"") -> 3000 | AG2: =IF(AND(AC2<>"",AF2<>""),AC2-AF2,"") -> 8520 | AH2: =IF(AND(AC2<>"",AC2>0,AF2<>""),AF2/AC2,"") -> 0.26041667 | AI2: =IF(AH2="","",IF(AF2>AC2,"🔴 Critical - Over Budget",IF(AH2>0.4,"⚠️ Approval Required","✅ Auto-Approved"))) -> ✅ Auto-Approved | AJ2: =IF(AI2="","",IF(AF2>AC2,"URGENT: Expenses exceed total income. Immediate review needed.",IF(AH2>0.4,"Expenses exceed 40% of income. Management approval required.","Within budget. No approval needed."))) -> Within budget. No approval needed. | AK2: Nisha Saifi | AL2: Richa Mehta | AM2: 46108 | AN2: Approved | AO2: =IF(AI2="","",IF(AI2="✅ Auto-Approved","✅ Approved (Auto - Within Budget)",IF(AN2="","⏳ Awaiting Approval",IF(AN2="Approved","✅ Approved by "&AL2&" on "&TEXT(AM2,"mm/dd/yyyy"),IF(AN2="Rejected","❌ Rejected by "&AL2&" - Review Expenses",IF(AN2="Pending Review","🔍 Under Review by "&AL2,IF(AN2="Escalated","⬆️ Escalated - Senior Management Review",""))))))) -> ✅ Approved (Auto - Within Budget) | AP2: Yes | AR2: Not Paid | AX2: https://drive.google.com/drive/folders/11RgGHdXvEN7luxqe-Tvxifm1UIN4WQZl?usp=sharing
A3: 2 | B3: Suryamitra Skill Development Programme | C3: 3732880 | D3: Normal | E3: Green Jobs | G3: Solar PV Installer (Suryamitra)(SGJ/Q0101) | H3: SAIFI HEALING TOUCH RESEARCH BUREAU FOR SOCIAL WELFARE OF INDIA | I3: SRINAGAR | J3: JAMMU AND KASHMIR | K3: 46114 | L3: 46114 | M3: 30 | N3: 30 | O3: =IF(AND(M3<>"",N3<>""),M3-N3,"") -> 0 | P3: 0 | Q3: =IF(AND(N3<>"",P3<>""),N3-P3,"") -> 30 | R3: 30 | S3: =IF(AND(N3<>"",R3<>""),N3-R3,"") -> 0 | T3: 46115 | U3: Uploaded | V3: =IFERROR(R3/N3,"") -> 1 | W3: =IFERROR(S3/N3,"") -> 0 | X3: Wajid bashir | Y3: AR84804 | Z3: Khalda Yousaf | AA3: TR251247 | AB3: =IFERROR(VLOOKUP(B3,'Scheme Master'!$B$4:$C$79,2,FALSE),"") -> 400 | AC3: =IF(AND(AB3<>"",N3<>""),AB3*N3,"") -> 12000 | AF3: =IF(OR(AD3<>"",AE3<>""),AD3+AE3,"") | AG3: =IF(AND(AC3<>"",AF3<>""),AC3-AF3,"") | AH3: =IF(AND(AC3<>"",AC3>0,AF3<>""),AF3/AC3,"") | AI3: =IF(AH3="","",IF(AF3>AC3,"🔴 Critical - Over Budget",IF(AH3>0.4,"⚠️ Approval Required","✅ Auto-Approved"))) | AK3: Nisha Saifi | AL3: Richa Mehta | AO3: =IF(AI3="","",IF(AI3="✅ Auto-Approved","✅ Approved (Auto - Within Budget)",IF(AN3="","⏳ Awaiting Approval",IF(AN3="Approved","✅ Approved by "&AL3&" on "&TEXT(AM3,"mm/dd/yyyy"),IF(AN3="Rejected","❌ Rejected by "&AL3&" - Review Expenses",IF(AN3="Pending Review","🔍 Under Review by "&AL3,IF(AN3="Escalated","⬆️ Escalated - Senior Management Review",""))))))) | AR3: Not Paid
A4: 3 | B4: PMKVY 4.0 | C4: 3735303 | D4: Day 6 | E4: Gems and Jewellery | G4: Goldsmith (Sunar)( G&J/N0612 ) | H4: NG MANI COLLEGE | I4: IMPHAL EAST | J4: MANIPUR | K4: 46114 | L4: 46114 | M4: 23 | N4: 19 | O4: =IF(AND(M4<>"",N4<>""),M4-N4,"") -> 4 | P4: 14 | Q4: =IF(AND(N4<>"",P4<>""),N4-P4,"") -> 5 | R4: 19 | S4: =IF(AND(N4<>"",R4<>""),N4-R4,"") -> 0 | T4: 46114 | U4: Uploaded | V4: =IFERROR(R4/N4,"") -> 1 | W4: =IFERROR(S4/N4,"") -> 0 | X4: Surjit Sapam | Y4: AR78791 | Z4: Nirmala Yumnam | AA4: TR386536 | AB4: =IFERROR(VLOOKUP(B4,'Scheme Master'!$B$4:$C$79,2,FALSE),"") -> 480 | AC4: =IF(AND(AB4<>"",N4<>""),AB4*N4,"") -> 9120 | AD4: 2000 | AF4: =IF(OR(AD4<>"",AE4<>""),AD4+AE4,"") -> 2000 | AG4: =IF(AND(AC4<>"",AF4<>""),AC4-AF4,"") -> 7120 | AH4: =IF(AND(AC4<>"",AC4>0,AF4<>""),AF4/AC4,"") -> 0.21929825 | AI4: =IF(AH4="","",IF(AF4>AC4,"🔴 Critical - Over Budget",IF(AH4>0.4,"⚠️ Approval Required","✅ Auto-Approved"))) -> ✅ Auto-Approved | AJ4: =IF(AI4="","",IF(AF4>AC4,"URGENT: Expenses exceed total income. Immediate review needed.",IF(AH4>0.4,"Expenses exceed 40% of income. Management approval required.","Within budget. No approval needed."))) -> Within budget. No approval needed. | AK4: Nisha Saifi | AL4: Richa Mehta | AO4: =IF(AI4="","",IF(AI4="✅ Auto-Approved","✅ Approved (Auto - Within Budget)",IF(AN4="","⏳ Awaiting Approval",IF(AN4="Approved","✅ Approved by "&AL4&" on "&TEXT(AM4,"mm/dd/yyyy"),IF(AN4="Rejected","❌ Rejected by "&AL4&" - Review Expenses",IF(AN4="Pending Review","🔍 Under Review by "&AL4,IF(AN4="Escalated","⬆️ Escalated - Senior Management Review",""))))))) -> ✅ Approved (Auto - Within Budget) | AP4: Yes | AR4: Not Paid
A5: 4 | B5: PM Vishwakarma | C5: 3733981 | D5: Day 6 | E5: Construction | G5: Brick Mason -Basic( CON/N0160 ) | H5: TOOL ROOM & TRAINING CENTRE | I5: KAMRUP | J5: ASSAM | K5: 46114 | L5: 46114 | M5: 24 | N5: 20 | O5: =IF(AND(M5<>"",N5<>""),M5-N5,"") -> 4 | P5: 20 | Q5: =IF(AND(N5<>"",P5<>""),N5-P5,"") -> 0 | R5: 20 | S5: =IF(AND(N5<>"",R5<>""),N5-R5,"") -> 0 | T5: 46114 | U5: Uploaded | V5: =IFERROR(R5/N5,"") -> 1 | W5: =IFERROR(S5/N5,"") -> 0 | X5: Satyajit Dash | Y5: AR113593 | Z5: Partha Jyoti Sarmah | AA5: TR633887 | AB5: =IFERROR(VLOOKUP(B5,'Scheme Master'!$B$4:$C$79,2,FALSE),"") -> 360 | AC5: =IF(AND(AB5<>"",N5<>""),AB5*N5,"") -> 7200 | AD5: 2000 | AF5: =IF(OR(AD5<>"",AE5<>""),AD5+AE5,"") -> 2000 | AG5: =IF(AND(AC5<>"",AF5<>""),AC5-AF5,"") -> 5200 | AH5: =IF(AND(AC5<>"",AC5>0,AF5<>""),AF5/AC5,"") -> 0.27777778 | AI5: =IF(AH5="","",IF(AF5>AC5,"🔴 Critical - Over Budget",IF(AH5>0.4,"⚠️ Approval Required","✅ Auto-Approved"))) -> ✅ Auto-Approved | AK5: Harpreet Kaur | AL5: Richa Mehta | AO5: =IF(AI5="","",IF(AI5="✅ Auto-Approved","✅ Approved (Auto - Within Budget)",IF(AN5="","⏳ Awaiting Approval",IF(AN5="Approved","✅ Approved by "&AL5&" on "&TEXT(AM5,"mm/dd/yyyy"),IF(AN5="Rejected","❌ Rejected by "&AL5&" - Review Expenses",IF(AN5="Pending Review","🔍 Under Review by "&AL5,IF(AN5="Escalated","⬆️ Escalated - Senior Management Review",""))))))) -> ✅ Approved (Auto - Within Budget) | AP5: Yes | AR5: Not Paid
A6: 5 | B6: PM Vishwakarma | C6: 3739308 | D6: Day 0 | E6: Handicraft | G6: Traditional Basket Maker( HCS/N9206 ) | H6: Government ITI, Farrukhabad | I6: FARRUKHABAD | J6: UTTAR PRADESH | K6: 46114 | L6: 46114 | M6: 23 | N6: 15 | O6: =IF(AND(M6<>"",N6<>""),M6-N6,"") -> 8 | P6: 9 | Q6: =IF(AND(N6<>"",P6<>""),N6-P6,"") -> 6 | R6: 15 | S6: =IF(AND(N6<>"",R6<>""),N6-R6,"") -> 0 | T6: 46114 | U6: Uploaded | V6: =IFERROR(R6/N6,"") -> 1 | W6: =IFERROR(S6/N6,"") -> 0 | X6: Laxmi Tiwari | Y6: AR135976 | Z6: Laxmi Tiwari | AA6: TR558148 | AB6: =IFERROR(VLOOKUP(B6,'Scheme Master'!$B$4:$C$79,2,FALSE),"") -> 360 | AC6: =IF(AND(AB6<>"",N6<>""),AB6*N6,"") -> 5400 | AD6: 2000 | AF6: =IF(OR(AD6<>"",AE6<>""),AD6+AE6,"") -> 2000 | AG6: =IF(AND(AC6<>"",AF6<>""),AC6-AF6,"") -> 3400 | AH6: =IF(AND(AC6<>"",AC6>0,AF6<>""),AF6/AC6,"") -> 0.37037037 | AI6: =IF(AH6="","",IF(AF6>AC6,"🔴 Critical - Over Budget",IF(AH6>0.4,"⚠️ Approval Required","✅ Auto-Approved"))) -> ✅ Auto-Approved | AJ6: =IF(AI6="","",IF(AF6>AC6,"URGENT: Expenses exceed total income. Immediate review needed.",IF(AH6>0.4,"Expenses exceed 40% of income. Management approval required.","Within budget. No approval needed."))) -> Within budget. No approval needed. | AO6: =IF(AI6="","",IF(AI6="✅ Auto-Approved","✅ Approved (Auto - Within Budget)",IF(AN6="","⏳ Awaiting Approval",IF(AN6="Approved","✅ Approved by "&AL6&" on "&TEXT(AM6,"mm/dd/yyyy"),IF(AN6="Rejected","❌ Rejected by "&AL6&" - Review Expenses",IF(AN6="Pending Review","🔍 Under Review by "&AL6,IF(AN6="Escalated","⬆️ Escalated - Senior Management Review",""))))))) -> ✅ Approved (Auto - Within Budget) | AP6: Yes | AR6: Not Paid
A7: 6 | B7: PM Vishwakarma | C7: 3756354 | D7: Day 0 | E7: Handicraft | G7: Traditional Soft Toy Maker( HCS/N7355 ) | H7: VISION INDIA SERVICES PRIVATE LIMITED | I7: BEGUSARAI | J7: BIHAR | K7: 46114 | L7: 46114 | M7: 8 | N7: 8 | O7: =IF(AND(M7<>"",N7<>""),M7-N7,"") -> 0 | P7: 0 | Q7: =IF(AND(N7<>"",P7<>""),N7-P7,"") -> 8 | R7: 8 | S7: =IF(AND(N7<>"",R7<>""),N7-R7,"") -> 0 | T7: 46114 | U7: Uploaded | V7: =IFERROR(R7/N7,"") -> 1 | W7: =IFERROR(S7/N7,"") -> 0 | X7: Kajal Kumari | Y7: AR154274 | Z7: Kajal Kumari | AA7: TR598635 | AB7: =IFERROR(VLOOKUP(B7,'Scheme Master'!$B$4:$C$79,2,FALSE),"") -> 360 | AC7: =IF(AND(AB7<>"",N7<>""),AB7*N7,"") -> 2880 | AD7: 800 | AF7: =IF(OR(AD7<>"",AE7<>""),AD7+AE7,"") -> 800 | AG7: =IF(AND(AC7<>"",AF7<>""),AC7-AF7,"") -> 2080 | AH7: =IF(AND(AC7<>"",AC7>0,AF7<>""),AF7/AC7,"") -> 0.27777778 | AI7: =IF(AH7="","",IF(AF7>AC7,"🔴 Critical - Over Budget",IF(AH7>0.4,"⚠️ Approval Required","✅ Auto-Approved"))) -> ✅ Auto-Approved | AJ7: =IF(AI7="","",IF(AF7>AC7,"URGENT: Expenses exceed total income. Immediate review needed.",IF(AH7>0.4,"Expenses exceed 40% of income. Management approval required.","Within budget. No approval needed."))) -> Within budget. No approval needed. | AO7: =IF(AI7="","",IF(AI7="✅ Auto-Approved","✅ Approved (Auto - Within Budget)",IF(AN7="","⏳ Awaiting Approval",IF(AN7="Approved","✅ Approved by "&AL7&" on "&TEXT(AM7,"mm/dd/yyyy"),IF(AN7="Rejected","❌ Rejected by "&AL7&" - Review Expenses",IF(AN7="Pending Review","🔍 Under Review by "&AL7,IF(AN7="Escalated","⬆️ Escalated - Senior Management Review",""))))))) -> ✅ Approved (Auto - Within Budget) | AP7: Yes | AR7: Not Paid
A8: 7 | B8: PM Vishwakarma | C8: 3739384 | D8: Day 0 | E8: Construction | G8: Brick Mason -Basic( CON/N0160 ) | H8: ORION EDUTECH PRIVATE LIMITED | I8: DARRANG | J8: ASSAM | K8: postpone | L8: Postpone | M8: 41 | O8: =IF(AND(M8<>"",N8<>""),M8-N8,"") | Q8: =IF(AND(N8<>"",P8<>""),N8-P8,"") | S8: =IF(AND(N8<>"",R8<>""),N8-R8,"") | V8: =IFERROR(R8/N8,"") | W8: =IFERROR(S8/N8,"") | AB8: =IFERROR(VLOOKUP(B8,'Scheme Master'!$B$4:$C$79,2,FALSE),"") -> 360 | AC8: =IF(AND(AB8<>"",N8<>""),AB8*N8,"") | AF8: =IF(OR(AD8<>"",AE8<>""),AD8+AE8,"") | AG8: =IF(AND(AC8<>"",AF8<>""),AC8-AF8,"") | AH8: =IF(AND(AC8<>"",AC8>0,AF8<>""),AF8/AC8,"") | AI8: =IF(AH8="","",IF(AF8>AC8,"🔴 Critical - Over Budget",IF(AH8>0.4,"⚠️ Approval Required","✅ Auto-Approved"))) | AO8: =IF(AI8="","",IF(AI8="✅ Auto-Approved","✅ Approved (Auto - Within Budget)",IF(AN8="","⏳ Awaiting Approval",IF(AN8="Approved","✅ Approved by "&AL8&" on "&TEXT(AM8,"mm/dd/yyyy"),IF(AN8="Rejected","❌ Rejected by "&AL8&" - Review Expenses",IF(AN8="Pending Review","🔍 Under Review by "&AL8,IF(AN8="Escalated","⬆️ Escalated - Senior Management Review","")))))))
A9: 8 | B9: DDUGKY | C9: 3466403 | D9: Day 1 | E9: Construction | G9: Assistant Electrician V3(CON/Q0602) | H9: Lala Kundan Lal Memorial Training Centre | I9: Fatehabad | J9: Haryana | K9: 46115 | L9: 46116 | M9: 35 | N9: 27 | O9: =IF(AND(M9<>"",N9<>""),M9-N9,"") -> 8 | P9: 13 | Q9: =IF(AND(N9<>"",P9<>""),N9-P9,"") -> 14 | R9: 26 | S9: =IF(AND(N9<>"",R9<>""),N9-R9,"") -> 1 | T9: 46118 | U9: Uploaded | V9: =IFERROR(R9/N9,"") -> 0.96296296 | W9: =IFERROR(S9/N9,"") -> 0.037037037 | X9: Mohd Navi | Y9: AR2351 | Z9: Not Available | AA9: Not Available | AB9: =IFERROR(VLOOKUP(B9,'Scheme Master'!$B$4:$C$79,2,FALSE),"") -> 720 | AC9: =IF(AND(AB9<>"",N9<>""),AB9*N9,"") -> 19440 | AF9: =IF(OR(AD9<>"",AE9<>""),AD9+AE9,"") | AG9: =IF(AND(AC9<>"",AF9<>""),AC9-AF9,"") | AH9: =IF(AND(AC9<>"",AC9>0,AF9<>""),AF9/AC9,"") | AI9: =IF(AH9="","",IF(AF9>AC9,"🔴 Critical - Over Budget",IF(AH9>0.4,"⚠️ Approval Required","✅ Auto-Approved"))) | AJ9: =IF(AI9="","",IF(AF9>AC9,"URGENT: Expenses exceed total income. Immediate review needed.",IF(AH9>0.4,"Expenses exceed 40% of income. Management approval required.","Within budget. No approval needed."))) | AO9: =IF(AI9="","",IF(AI9="✅ Auto-Approved","✅ Approved (Auto - Within Budget)",IF(AN9="","⏳ Awaiting Approval",IF(AN9="Approved","✅ Approved by "&AL9&" on "&TEXT(AM9,"mm/dd/yyyy"),IF(AN9="Rejected","❌ Rejected by "&AL9&" - Review Expenses",IF(AN9="Pending Review","🔍 Under Review by "&AL9,IF(AN9="Escalated","⬆️ Escalated - Senior Management Review",""))))))) | AR9: Not Paid
A10: 9 | B10: PM Vishwakarma | C10: 3734797 | D10: Day 6 | E10: Construction | G10: Brick Mason -Basic( CON/N0160 ) | H10: Government Polytechnic college Bandipora | I10: BANDIPORA | J10: JAMMU AND KASHMIR | K10: 46115 | L10: 46115 | M10: 6 | N10: 5 | O10: =IF(AND(M10<>"",N10<>""),M10-N10,"") -> 1 | P10: 5 | Q10: =IF(AND(N10<>"",P10<>""),N10-P10,"") -> 0 | R10: 5 | S10: =IF(AND(N10<>"",R10<>""),N10-R10,"") -> 0 | T10: 46115 | U10: Uploaded | V10: =IFERROR(R10/N10,"") -> 1 | W10: =IFERROR(S10/N10,"") -> 0 | X10: Mudasir Nisar | Y10: AR53637 | Z10: Arifa Bashir | AA10: TR472161 | AB10: =IFERROR(VLOOKUP(B10,'Scheme Master'!$B$4:$C$79,2,FALSE),"") -> 360 | AC10: =IF(AND(AB10<>"",N10<>""),AB10*N10,"") -> 1800 | AF10: =IF(OR(AD10<>"",AE10<>""),AD10+AE10,"") | AG10: =IF(AND(AC10<>"",AF10<>""),AC10-AF10,"") | AH10: =IF(AND(AC10<>"",AC10>0,AF10<>""),AF10/AC10,"") | AI10: =IF(AH10="","",IF(AF10>AC10,"🔴 Critical - Over Budget",IF(AH10>0.4,"⚠️ Approval Required","✅ Auto-Approved"))) | AO10: =IF(AI10="","",IF(AI10="✅ Auto-Approved","✅ Approved (Auto - Within Budget)",IF(AN10="","⏳ Awaiting Approval",IF(AN10="Approved","✅ Approved by "&AL10&" on "&TEXT(AM10,"mm/dd/yyyy"),IF(AN10="Rejected","❌ Rejected by "&AL10&" - Review Expenses",IF(AN10="Pending Review","🔍 Under Review by "&AL10,IF(AN10="Escalated","⬆️ Escalated - Senior Management Review",""))))))) | AR10: Not Paid
A11: 10 | B11: PMKVY 4.0 | C11: 3736126 | D11: Normal | E11: Construction | G11: Fabricator v5.0(CON/Q1206) | H11: Larsen & Toubro Limited | I11: MAYURBHANJ | J11: Odisha | K11: 46115 | L11: 46115 | M11: 28 | N11: 27 | O11: =IF(AND(M11<>"",N11<>""),M11-N11,"") -> 1 | P11: 27 | Q11: =IF(AND(N11<>"",P11<>""),N11-P11,"") -> 0 | R11: 27 | S11: =IF(AND(N11<>"",R11<>""),N11-R11,"") -> 0 | T11: 46116 | U11: Uploaded | V11: =IFERROR(R11/N11,"") -> 1 | W11: =IFERROR(S11/N11,"") -> 0 | X11: Vishal Verma | Y11: A-00E1F0 | Z11: Surya prakash Updhyay | AA11: TR672540 | AB11: =IFERROR(VLOOKUP(B11,'Scheme Master'!$B$4:$C$79,2,FALSE),"") -> 480 | AC11: =IF(AND(AB11<>"",N11<>""),AB11*N11,"") -> 12960 | AF11: =IF(OR(AD11<>"",AE11<>""),AD11+AE11,"") | AG11: =IF(AND(AC11<>"",AF11<>""),AC11-AF11,"") | AH11: =IF(AND(AC11<>"",AC11>0,AF11<>""),AF11/AC11,"") | AI11: =IF(AH11="","",IF(AF11>AC11,"🔴 Critical - Over Budget",IF(AH11>0.4,"⚠️ Approval Required","✅ Auto-Approved"))) | AJ11: =IF(AI11="","",IF(AF11>AC11,"URGENT: Expenses exceed total income. Immediate review needed.",IF(AH11>0.4,"Expenses exceed 40% of income. Management approval required.","Within budget. No approval needed."))) | AO11: =IF(AI11="","",IF(AI11="✅ Auto-Approved","✅ Approved (Auto - Within Budget)",IF(AN11="","⏳ Awaiting Approval",IF(AN11="Approved","✅ Approved by "&AL11&" on "&TEXT(AM11,"mm/dd/yyyy"),IF(AN11="Rejected","❌ Rejected by "&AL11&" - Review Expenses",IF(AN11="Pending Review","🔍 Under Review by "&AL11,IF(AN11="Escalated","⬆️ Escalated - Senior Management Review",""))))))) | AR11: Not Paid
A12: 11 | B12: PM Vishwakarma | C12: 3756600 | D12: Day 0 | E12: Gems and Jewellery | G12: goldsmith (Sunar)( G&J/N0612 ) | H12: NG MANI COLLEGE | I12: IMPHAL EAST | J12: MANIPUR | K12: 46115 | L12: 46115 | M12: 22 | N12: 15 | O12: =IF(AND(M12<>"",N12<>""),M12-N12,"") -> 7 | P12: 11 | Q12: =IF(AND(N12<>"",P12<>""),N12-P12,"") -> 4 | R12: 15 | S12: =IF(AND(N12<>"",R12<>""),N12-R12,"") -> 0 | T12: 46115 | U12: Uploaded | V12: =IFERROR(R12/N12,"") -> 1 | W12: =IFERROR(S12/N12,"") -> 0 | X12: Nirmala Yumnam Chanu | Y12: AR78961 | Z12: Nirmala Yumnam Chanu | AA12: TR386536 | AB12: =IFERROR(VLOOKUP(B12,'Scheme Master'!$B$4:$C$79,2,FALSE),"") -> 360 | AC12: =IF(AND(AB12<>"",N12<>""),AB12*N12,"") -> 5400 | AD12: 2000 | AF12: =IF(OR(AD12<>"",AE12<>""),AD12+AE12,"") -> 2000 | AG12: =IF(AND(AC12<>"",AF12<>""),AC12-AF12,"") -> 3400 | AH12: =IF(AND(AC12<>"",AC12>0,AF12<>""),AF12/AC12,"") -> 0.37037037 | AI12: =IF(AH12="","",IF(AF12>AC12,"🔴 Critical - Over Budget",IF(AH12>0.4,"⚠️ Approval Required","✅ Auto-Approved"))) -> ✅ Auto-Approved | AJ12: =IF(AI12="","",IF(AF12>AC12,"URGENT: Expenses exceed total income. Immediate review needed.",IF(AH12>0.4,"Expenses exceed 40% of income. Management approval required.","Within budget. No approval needed."))) -> Within budget. No approval needed. | AO12: =IF(AI12="","",IF(AI12="✅ Auto-Approved","✅ Approved (Auto - Within Budget)",IF(AN12="","⏳ Awaiting Approval",IF(AN12="Approved","✅ Approved by "&AL12&" on "&TEXT(AM12,"mm/dd/yyyy"),IF(AN12="Rejected","❌ Rejected by "&AL12&" - Review Expenses",IF(AN12="Pending Review","🔍 Under Review by "&AL12,IF(AN12="Escalated","⬆️ Escalated - Senior Management Review",""))))))) -> ✅ Approved (Auto - Within Budget) | AP12: Yes | AR12: Not Paid
A13: 12 | B13: PM Vishwakarma | C13: 3756452 | D13: Day 0 | E13: Gems and Jewellery | G13: goldsmith (Sunar)( G&J/N0612 ) | H13: Government ITI, Sirathu, Kaushambi | I13: KAUSHAMBI | J13: UTTAR PRADESH | K13: 46115 | L13: 46115 | M13: 2 | N13: 2 | O13: =IF(AND(M13<>"",N13<>""),M13-N13,"") -> 0 | P13: 2 | Q13: =IF(AND(N13<>"",P13<>""),N13-P13,"") -> 0 | R13: 2 | S13: =IF(AND(N13<>"",R13<>""),N13-R13,"") -> 0 | T13: 46115 | U13: Uploaded | V13: =IFERROR(R13/N13,"") -> 1 | W13: =IFERROR(S13/N13,"") -> 0 | X13: Anand Kumar | Y13: AR153752 | Z13: Anand Kumar | AA13: TR597173 | AB13: =IFERROR(VLOOKUP(B13,'Scheme Master'!$B$4:$C$79,2,FALSE),"") -> 360 | AC13: =IF(AND(AB13<>"",N13<>""),AB13*N13,"") -> 720 | AD13: 200 | AF13: =IF(OR(AD13<>"",AE13<>""),AD13+AE13,"") -> 200 | AG13: =IF(AND(AC13<>"",AF13<>""),AC13-AF13,"") -> 520 | AH13: =IF(AND(AC13<>"",AC13>0,AF13<>""),AF13/AC13,"") -> 0.27777778 | AI13: =IF(AH13="","",IF(AF13>AC13,"🔴 Critical - Over Budget",IF(AH13>0.4,"⚠️ Approval Required","✅ Auto-Approved"))) -> ✅ Auto-Approved | AJ13: =IF(AI13="","",IF(AF13>AC13,"URGENT: Expenses exceed total income. Immediate review needed.",IF(AH13>0.4,"Expenses exceed 40% of income. Management approval required.","Within budget. No approval needed."))) -> Within budget. No approval needed. | AO13: =IF(AI13="","",IF(AI13="✅ Auto-Approved","✅ Approved (Auto - Within Budget)",IF(AN13="","⏳ Awaiting Approval",IF(AN13="Approved","✅ Approved by "&AL13&" on "&TEXT(AM13,"mm/dd/yyyy"),IF(AN13="Rejected","❌ Rejected by "&AL13&" - Review Expenses",IF(AN13="Pending Review","🔍 Under Review by "&AL13,IF(AN13="Escalated","⬆️ Escalated - Senior Management Review",""))))))) -> ✅ Approved (Auto - Within Budget) | AP13: Yes | AR13: Not Paid
A14: 13 | B14: PMKVY 4.0 | C14: 3739936 | D14: Normal | E14: Green Jobs | G14: Junior Technician - Mechanized Sewer Cleaning(SGJ/Q4006) | H14: NATIONAL SAFAI KARAMCHARIS FINANCE AND DEVELOPMENT CORPORATION | I14: AHMEDABAD | J14: GUJARAT | K14: 46116 | L14: 46116 | M14: 24 | N14: 20 | O14: =IF(AND(M14<>"",N14<>""),M14-N14,"") -> 4 | P14: 18 | Q14: =IF(AND(N14<>"",P14<>""),N14-P14,"") -> 2 | R14: 20 | S14: =IF(AND(N14<>"",R14<>""),N14-R14,"") -> 0 | T14: 46118 | U14: Uploaded | V14: =IFERROR(R14/N14,"") -> 1 | W14: =IFERROR(S14/N14,"") -> 0 | X14: Gaurav patel | Y14: AR180975 | Z14: Ambuj Tripathi | AA14: TR654284 | AB14: =IFERROR(VLOOKUP(B14,'Scheme Master'!$B$4:$C$79,2,FALSE),"") -> 480 | AC14: =IF(AND(AB14<>"",N14<>""),AB14*N14,"") -> 9600 | AD14: 2000 | AE14: 1000 | AF14: =IF(OR(AD14<>"",AE14<>""),AD14+AE14,"") -> 3000 | AG14: =IF(AND(AC14<>"",AF14<>""),AC14-AF14,"") -> 6600 | AH14: =IF(AND(AC14<>"",AC14>0,AF14<>""),AF14/AC14,"") -> 0.3125 | AI14: =IF(AH14="","",IF(AF14>AC14,"🔴 Critical - Over Budget",IF(AH14>0.4,"⚠️ Approval Required","✅ Auto-Approved"))) -> ✅ Auto-Approved | AJ14: =IF(AI14="","",IF(AF14>AC14,"URGENT: Expenses exceed total income. Immediate review needed.",IF(AH14>0.4,"Expenses exceed 40% of income. Management approval required.","Within budget. No approval needed."))) -> Within budget. No approval needed. | AK14: Nisha Saifi | AL14: Richa Mehta | AM14: 46113 | AO14: =IF(AI14="","",IF(AI14="✅ Auto-Approved","✅ Approved (Auto - Within Budget)",IF(AN14="","⏳ Awaiting Approval",IF(AN14="Approved","✅ Approved by "&AL14&" on "&TEXT(AM14,"mm/dd/yyyy"),IF(AN14="Rejected","❌ Rejected by "&AL14&" - Review Expenses",IF(AN14="Pending Review","🔍 Under Review by "&AL14,IF(AN14="Escalated","⬆️ Escalated - Senior Management Review",""))))))) -> ✅ Approved (Auto - Within Budget) | AR14: Not Paid
A15: 8 | B15: DDUGKY | C15: 3466403 | D15: Day 2 | E15: Construction | G15: Assistant Electrician V3(CON/Q0602) | H15: Lala Kundan Lal Memorial Training Centre | I15: Fatehabad | J15: Haryana | K15: 46115 | L15: 46116 | M15: 35 | N15: 27 | O15: =IF(AND(M15<>"",N15<>""),M15-N15,"") -> 8 | P15: 13 | Q15: =IF(AND(N15<>"",P15<>""),N15-P15,"") -> 14 | R15: 26 | S15: =IF(AND(N15<>"",R15<>""),N15-R15,"") -> 1 | T15: 46118 | U15: Uploaded | V15: =IFERROR(R15/N15,"") -> 0.96296296 | W15: =IFERROR(S15/N15,"") -> 0.037037037 | X15: Mohd Navi | Y15: AR2351 | Z15: Not Available | AA15: Not Available | AB15: =IFERROR(VLOOKUP(B15,'Scheme Master'!$B$4:$C$79,2,FALSE),"") -> 720 | AC15: =IF(AND(AB15<>"",N15<>""),AB15*N15,"") -> 19440 | AF15: =IF(OR(AD15<>"",AE15<>""),AD15+AE15,"") | AG15: =IF(AND(AC15<>"",AF15<>""),AC15-AF15,"") | AH15: =IF(AND(AC15<>"",AC15>0,AF15<>""),AF15/AC15,"") | AI15: =IF(AH15="","",IF(AF15>AC15,"🔴 Critical - Over Budget",IF(AH15>0.4,"⚠️ Approval Required","✅ Auto-Approved"))) | AJ15: =IF(AI15="","",IF(AF15>AC15,"URGENT: Expenses exceed total income. Immediate review needed.",IF(AH15>0.4,"Expenses exceed 40% of income. Management approval required.","Within budget. No approval needed."))) | AO15: =IF(AI15="","",IF(AI15="✅ Auto-Approved","✅ Approved (Auto - Within Budget)",IF(AN15="","⏳ Awaiting Approval",IF(AN15="Approved","✅ Approved by "&AL15&" on "&TEXT(AM15,"mm/dd/yyyy"),IF(AN15="Rejected","❌ Rejected by "&AL15&" - Review Expenses",IF(AN15="Pending Review","🔍 Under Review by "&AL15,IF(AN15="Escalated","⬆️ Escalated - Senior Management Review",""))))))) | AR15: Not Paid
A16: 14 | B16: VSSY-RPL | C16: GJSCI_VSSY-RPL/2026-02 | D16: Normal | E16: Gems and Jewellery | G16: Jewellery Frame and Component Maker | H16: UPICON | I16: Barabanki | J16: UttarPradesh | K16: 46116 | L16: 46116 | M16: 25 | N16: 21 | O16: =IF(AND(M16<>"",N16<>""),M16-N16,"") -> 4 | P16: 19 | Q16: =IF(AND(N16<>"",P16<>""),N16-P16,"") -> 2 | R16: 21 | S16: =IF(AND(N16<>"",R16<>""),N16-R16,"") -> 0 | T16: 46118 | U16: Uploaded | V16: =IFERROR(R16/N16,"") -> 1 | W16: =IFERROR(S16/N16,"") -> 0 | X16: Mohd Nadeem | Y16: AR29759 | Z16: Mahima Pandey | AA16: TR346258 | AB16: =IFERROR(VLOOKUP(B16,'Scheme Master'!$B$4:$C$79,2,FALSE),"") -> 540 | AC16: =IF(AND(AB16<>"",N16<>""),AB16*N16,"") -> 11340 | AF16: =IF(OR(AD16<>"",AE16<>""),AD16+AE16,"") | AG16: =IF(AND(AC16<>"",AF16<>""),AC16-AF16,"") | AH16: =IF(AND(AC16<>"",AC16>0,AF16<>""),AF16/AC16,"") | AI16: =IF(AH16="","",IF(AF16>AC16,"🔴 Critical - Over Budget",IF(AH16>0.4,"⚠️ Approval Required","✅ Auto-Approved"))) | AJ16: =IF(AI16="","",IF(AF16>AC16,"URGENT: Expenses exceed total income. Immediate review needed.",IF(AH16>0.4,"Expenses exceed 40% of income. Management approval required.","Within budget. No approval needed."))) | AO16: =IF(AI16="","",IF(AI16="✅ Auto-Approved","✅ Approved (Auto - Within Budget)",IF(AN16="","⏳ Awaiting Approval",IF(AN16="Approved","✅ Approved by "&AL16&" on "&TEXT(AM16,"mm/dd/yyyy"),IF(AN16="Rejected","❌ Rejected by "&AL16&" - Review Expenses",IF(AN16="Pending Review","🔍 Under Review by "&AL16,IF(AN16="Escalated","⬆️ Escalated - Senior Management Review",""))))))) | AR16: Not Paid
A17: 15 | B17: BSDMA-RPL | C17: 3727804 | D17: Day 1 | E17: Construction | G17: Masonry of Earthquake-Resistant Building(CON/N0161) | H17: Astric Solutions | I17: Siwan | J17: Bihar | K17: 46116 | L17: 46117 | M17: 25 | N17: 24 | O17: =IF(AND(M17<>"",N17<>""),M17-N17,"") -> 1 | P17: 24 | Q17: =IF(AND(N17<>"",P17<>""),N17-P17,"") -> 0 | R17: 23 | S17: =IF(AND(N17<>"",R17<>""),N17-R17,"") -> 1 | T17: 46119 | U17: Uploaded | V17: =IFERROR(R17/N17,"") -> 0.95833333 | W17: =IFERROR(S17/N17,"") -> 0.041666667 | X17: Mohd Naseem | Y17: AR145441 | Z17: Priyanshu Ranjan Upadhyay | AA17: TR544100 | AB17: =IFERROR(VLOOKUP(B17,'Scheme Master'!$B$4:$C$79,2,FALSE),"") -> 540 | AC17: =IF(AND(AB17<>"",N17<>""),AB17*N17,"") -> 12960 | AD17: 2000 | AE17: 2000 | AF17: =IF(OR(AD17<>"",AE17<>""),AD17+AE17,"") -> 4000 | AG17: =IF(AND(AC17<>"",AF17<>""),AC17-AF17,"") -> 8960 | AH17: =IF(AND(AC17<>"",AC17>0,AF17<>""),AF17/AC17,"") -> 0.30864198 | AI17: =IF(AH17="","",IF(AF17>AC17,"🔴 Critical - Over Budget",IF(AH17>0.4,"⚠️ Approval Required","✅ Auto-Approved"))) -> ✅ Auto-Approved | AJ17: =IF(AI17="","",IF(AF17>AC17,"URGENT: Expenses exceed total income. Immediate review needed.",IF(AH17>0.4,"Expenses exceed 40% of income. Management approval required.","Within budget. No approval needed."))) -> Within budget. No approval needed. | AO17: =IF(AI17="","",IF(AI17="✅ Auto-Approved","✅ Approved (Auto - Within Budget)",IF(AN17="","⏳ Awaiting Approval",IF(AN17="Approved","✅ Approved by "&AL17&" on "&TEXT(AM17,"mm/dd/yyyy"),IF(AN17="Rejected","❌ Rejected by "&AL17&" - Review Expenses",IF(AN17="Pending Review","🔍 Under Review by "&AL17,IF(AN17="Escalated","⬆️ Escalated - Senior Management Review",""))))))) -> ✅ Approved (Auto - Within Budget) | AR17: Not Paid
A18: 16 | B18: PM Vishwakarma | C18: 3735550 | D18: Day 6 | E18: Construction | G18: Brick Mason -Basic( CON/N0160 ) | H18: ALL INDIA SOCIETY FOR ELECTRONICS AND COMPUTER TECHNOLOGY | I18: KATNI | J18: MADHYA PRADESH | K18: 46116 | L18: 46116 | M18: 23 | N18: 20 | O18: =IF(AND(M18<>"",N18<>""),M18-N18,"") -> 3 | P18: 20 | Q18: =IF(AND(N18<>"",P18<>""),N18-P18,"") -> 0 | R18: 20 | S18: =IF(AND(N18<>"",R18<>""),N18-R18,"") -> 0 | T18: 46116 | U18: Uploaded | V18: =IFERROR(R18/N18,"") -> 1 | W18: =IFERROR(S18/N18,"") -> 0 | X18: Girja Shankar Gigoliya | Y18: AR136635 | Z18: Shiv Kumar Choudhary | AA18: TR409060 | AB18: =IFERROR(VLOOKUP(B18,'Scheme Master'!$B$4:$C$79,2,FALSE),"") -> 360 | AC18: =IF(AND(AB18<>"",N18<>""),AB18*N18,"") -> 7200 | AD18: 2000 | AF18: =IF(OR(AD18<>"",AE18<>""),AD18+AE18,"") -> 2000 | AG18: =IF(AND(AC18<>"",AF18<>""),AC18-AF18,"") -> 5200 | AH18: =IF(AND(AC18<>"",AC18>0,AF18<>""),AF18/AC18,"") -> 0.27777778 | AI18: =IF(AH18="","",IF(AF18>AC18,"🔴 Critical - Over Budget",IF(AH18>0.4,"⚠️ Approval Required","✅ Auto-Approved"))) -> ✅ Auto-Approved | AJ18: =IF(AI18="","",IF(AF18>AC18,"URGENT: Expenses exceed total income. Immediate review needed.",IF(AH18>0.4,"Expenses exceed 40% of income. Management approval required.","Within budget. No approval needed."))) -> Within budget. No approval needed. | AO18: =IF(AI18="","",IF(AI18="✅ Auto-Approved","✅ Approved (Auto - Within Budget)",IF(AN18="","⏳ Awaiting Approval",IF(AN18="Approved","✅ Approved by "&AL18&" on "&TEXT(AM18,"mm/dd/yyyy"),IF(AN18="Rejected","❌ Rejected by "&AL18&" - Review Expenses",IF(AN18="Pending Review","🔍 Under Review by "&AL18,IF(AN18="Escalated","⬆️ Escalated - Senior Management Review",""))))))) -> ✅ Approved (Auto - Within Budget) | AP18: Yes | AR18: Not Paid
A19: 17 | B19: PM Vishwakarma | C19: 3756888 | D19: Day 0 | E19: Handicraft | G19: Traditional Basket Maker( HCS/N9206 ) | H19: Govt ITI (LWE) Gidhuar, Jamui | I19: JAMUI | J19: BIHAR | K19: 46116 | L19: 46116 | M19: 18 | N19: 17 | O19: =IF(AND(M19<>"",N19<>""),M19-N19,"") -> 1 | P19: 0 | Q19: =IF(AND(N19<>"",P19<>""),N19-P19,"") -> 17 | R19: 17 | S19: =IF(AND(N19<>"",R19<>""),N19-R19,"") -> 0 | T19: 46116 | U19: Uploaded | V19: =IFERROR(R19/N19,"") -> 1 | W19: =IFERROR(S19/N19,"") -> 0 | X19: Kanhaiya Kumar | Y19: AR115952 | Z19: Kanhaiya Kumar | AA19: TR507370 | AB19: =IFERROR(VLOOKUP(B19,'Scheme Master'!$B$4:$C$79,2,FALSE),"") -> 360 | AC19: =IF(AND(AB19<>"",N19<>""),AB19*N19,"") -> 6120 | AD19: 2000 | AF19: =IF(OR(AD19<>"",AE19<>""),AD19+AE19,"") -> 2000 | AG19: =IF(AND(AC19<>"",AF19<>""),AC19-AF19,"") -> 4120 | AH19: =IF(AND(AC19<>"",AC19>0,AF19<>""),AF19/AC19,"") -> 0.32679739 | AI19: =IF(AH19="","",IF(AF19>AC19,"🔴 Critical - Over Budget",IF(AH19>0.4,"⚠️ Approval Required","✅ Auto-Approved"))) -> ✅ Auto-Approved | AJ19: =IF(AI19="","",IF(AF19>AC19,"URGENT: Expenses exceed total income. Immediate review needed.",IF(AH19>0.4,"Expenses exceed 40% of income. Management approval required.","Within budget. No approval needed."))) -> Within budget. No approval needed. | AO19: =IF(AI19="","",IF(AI19="✅ Auto-Approved","✅ Approved (Auto - Within Budget)",IF(AN19="","⏳ Awaiting Approval",IF(AN19="Approved","✅ Approved by "&AL19&" on "&TEXT(AM19,"mm/dd/yyyy"),IF(AN19="Rejected","❌ Rejected by "&AL19&" - Review Expenses",IF(AN19="Pending Review","🔍 Under Review by "&AL19,IF(AN19="Escalated","⬆️ Escalated - Senior Management Review",""))))))) -> ✅ Approved (Auto - Within Budget) | AP19: Yes | AR19: Not Paid
A20: 18 | B20: PM Vishwakarma | C20: 3755823 | D20: Day 0 | E20: Gems and Jewellery | G20: Goldsmith (Sunar)( G&J/N0612 ) | H20: GOVT WITI SAHARSA | I20: SAHARSA | J20: BIHAR | K20: 46116 | L20: 46116 | M20: 19 | N20: 19 | O20: =IF(AND(M20<>"",N20<>""),M20-N20,"") -> 0 | P20: 9 | Q20: =IF(AND(N20<>"",P20<>""),N20-P20,"") -> 10 | R20: 19 | S20: =IF(AND(N20<>"",R20<>""),N20-R20,"") -> 0 | T20: 46116 | U20: Uploaded | V20: =IFERROR(R20/N20,"") -> 1 | W20: =IFERROR(S20/N20,"") -> 0 | X20: Ashwinee kumar | Y20: AR161851 | Z20: Ashwinee kumar | AA20: TR616427 | AB20: =IFERROR(VLOOKUP(B20,'Scheme Master'!$B$4:$C$79,2,FALSE),"") -> 360 | AC20: =IF(AND(AB20<>"",N20<>""),AB20*N20,"") -> 6840 | AD20: 2000 | AF20: =IF(OR(AD20<>"",AE20<>""),AD20+AE20,"") -> 2000 | AG20: =IF(AND(AC20<>"",AF20<>""),AC20-AF20,"") -> 4840 | AH20: =IF(AND(AC20<>"",AC20>0,AF20<>""),AF20/AC20,"") -> 0.29239766 | AI20: =IF(AH20="","",IF(AF20>AC20,"🔴 Critical - Over Budget",IF(AH20>0.4,"⚠️ Approval Required","✅ Auto-Approved"))) -> ✅ Auto-Approved | AJ20: =IF(AI20="","",IF(AF20>AC20,"URGENT: Expenses exceed total income. Immediate review needed.",IF(AH20>0.4,"Expenses exceed 40% of income. Management approval required.","Within budget. No approval needed."))) -> Within budget. No approval needed. | AO20: =IF(AI20="","",IF(AI20="✅ Auto-Approved","✅ Approved (Auto - Within Budget)",IF(AN20="","⏳ Awaiting Approval",IF(AN20="Approved","✅ Approved by "&AL20&" on "&TEXT(AM20,"mm/dd/yyyy"),IF(AN20="Rejected","❌ Rejected by "&AL20&" - Review Expenses",IF(AN20="Pending Review","🔍 Under Review by "&AL20,IF(AN20="Escalated","⬆️ Escalated - Senior Management Review",""))))))) -> ✅ Approved (Auto - Within Budget) | AP20: Yes | AR20: Not Paid
A21: 19 | B21: PM Vishwakarma | C21: 3739384 | D21: Day 0 | E21: Construction | G21: Brick Mason -Basic( CON/N0160 ) | H21: ORION EDUTECH PRIVATE LIMITED | I21: DARRANG | J21: ASSAM | K21: Postpone | L21: Postpone | M21: 41 | O21: =IF(AND(M21<>"",N21<>""),M21-N21,"") | Q21: =IF(AND(N21<>"",P21<>""),N21-P21,"") | S21: =IF(AND(N21<>"",R21<>""),N21-R21,"") | V21: =IFERROR(R21/N21,"") | W21: =IFERROR(S21/N21,"") | AB21: =IFERROR(VLOOKUP(B21,'Scheme Master'!$B$4:$C$79,2,FALSE),"") -> 360 | AC21: =IF(AND(AB21<>"",N21<>""),AB21*N21,"") | AF21: =IF(OR(AD21<>"",AE21<>""),AD21+AE21,"") | AG21: =IF(AND(AC21<>"",AF21<>""),AC21-AF21,"") | AH21: =IF(AND(AC21<>"",AC21>0,AF21<>""),AF21/AC21,"") | AI21: =IF(AH21="","",IF(AF21>AC21,"🔴 Critical - Over Budget",IF(AH21>0.4,"⚠️ Approval Required","✅ Auto-Approved"))) | AJ21: =IF(AI21="","",IF(AF21>AC21,"URGENT: Expenses exceed total income. Immediate review needed.",IF(AH21>0.4,"Expenses exceed 40% of income. Management approval required.","Within budget. No approval needed."))) | AO21: =IF(AI21="","",IF(AI21="✅ Auto-Approved","✅ Approved (Auto - Within Budget)",IF(AN21="","⏳ Awaiting Approval",IF(AN21="Approved","✅ Approved by "&AL21&" on "&TEXT(AM21,"mm/dd/yyyy"),IF(AN21="Rejected","❌ Rejected by "&AL21&" - Review Expenses",IF(AN21="Pending Review","🔍 Under Review by "&AL21,IF(AN21="Escalated","⬆️ Escalated - Senior Management Review","")))))))
A22: 20 | B22: PMKVY 4.0 | C22: 3727439 | D22: Normal | E22: Green Jobs | G22: Junior Technician - Mechanized Sewer Cleaning(SGJ/Q4006) | H22: Brainlite Education Solutions Pvt Ltd | I22: RAJKOT | J22: GUJARAT | K22: Postpone | L22: Postpone | M22: 38 | O22: =IF(AND(M22<>"",N22<>""),M22-N22,"") | Q22: =IF(AND(N22<>"",P22<>""),N22-P22,"") | S22: =IF(AND(N22<>"",R22<>""),N22-R22,"") | V22: =IFERROR(R22/N22,"") | W22: =IFERROR(S22/N22,"") | AB22: =IFERROR(VLOOKUP(B22,'Scheme Master'!$B$4:$C$79,2,FALSE),"") -> 480 | AC22: =IF(AND(AB22<>"",N22<>""),AB22*N22,"") | AF22: =IF(OR(AD22<>"",AE22<>""),AD22+AE22,"") | AG22: =IF(AND(AC22<>"",AF22<>""),AC22-AF22,"") | AH22: =IF(AND(AC22<>"",AC22>0,AF22<>""),AF22/AC22,"") | AI22: =IF(AH22="","",IF(AF22>AC22,"🔴 Critical - Over Budget",IF(AH22>0.4,"⚠️ Approval Required","✅ Auto-Approved"))) | AJ22: =IF(AI22="","",IF(AF22>AC22,"URGENT: Expenses exceed total income. Immediate review needed.",IF(AH22>0.4,"Expenses exceed 40% of income. Management approval required.","Within budget. No approval needed."))) | AO22: =IF(AI22="","",IF(AI22="✅ Auto-Approved","✅ Approved (Auto - Within Budget)",IF(AN22="","⏳ Awaiting Approval",IF(AN22="Approved","✅ Approved by "&AL22&" on "&TEXT(AM22,"mm/dd/yyyy"),IF(AN22="Rejected","❌ Rejected by "&AL22&" - Review Expenses",IF(AN22="Pending Review","🔍 Under Review by "&AL22,IF(AN22="Escalated","⬆️ Escalated - Senior Management Review","")))))))
A23: 21 | B23: PMKVY 4.0 | C23: 3708112 | D23: Normal | E23: Green Jobs | G23: Swacchta Saarthi( SGJ/MCr-0015) | H23: Shrawani Srivastava | I23: KHAMMAM | J23: TELANGANA | K23: Postpone | L23: Postpone | M23: 44 | O23: =IF(AND(M23<>"",N23<>""),M23-N23,"") | Q23: =IF(AND(N23<>"",P23<>""),N23-P23,"") | S23: =IF(AND(N23<>"",R23<>""),N23-R23,"") | V23: =IFERROR(R23/N23,"") | W23: =IFERROR(S23/N23,"") | AB23: =IFERROR(VLOOKUP(B23,'Scheme Master'!$B$4:$C$79,2,FALSE),"") -> 480 | AC23: =IF(AND(AB23<>"",N23<>""),AB23*N23,"") | AF23: =IF(OR(AD23<>"",AE23<>""),AD23+AE23,"") | AG23: =IF(AND(AC23<>"",AF23<>""),AC23-AF23,"") | AH23: =IF(AND(AC23<>"",AC23>0,AF23<>""),AF23/AC23,"") | AI23: =IF(AH23="","",IF(AF23>AC23,"🔴 Critical - Over Budget",IF(AH23>0.4,"⚠️ Approval Required","✅ Auto-Approved"))) | AJ23: =IF(AI23="","",IF(AF23>AC23,"URGENT: Expenses exceed total income. Immediate review needed.",IF(AH23>0.4,"Expenses exceed 40% of income. Management approval required.","Within budget. No approval needed."))) | AO23: =IF(AI23="","",IF(AI23="✅ Auto-Approved","✅ Approved (Auto - Within Budget)",IF(AN23="","⏳ Awaiting Approval",IF(AN23="Approved","✅ Approved by "&AL23&" on "&TEXT(AM23,"mm/dd/yyyy"),IF(AN23="Rejected","❌ Rejected by "&AL23&" - Review Expenses",IF(AN23="Pending Review","🔍 Under Review by "&AL23,IF(AN23="Escalated","⬆️ Escalated - Senior Management Review","")))))))
A24: 23 | B24: ODOP-RPL | C24: 01042026-27 | D24: Normal | E24: Handicraft | G24: Bamboo Work Artisan | H24: Uttar Pradesh Institute of Design and Research | I24: Amethi | J24: Uttar Pradesh | K24: 46117 | L24: 46117 | M24: 25 | N24: 25 | O24: =IF(AND(M24<>"",N24<>""),M24-N24,"") -> 0 | P24: 0 | Q24: =IF(AND(N24<>"",P24<>""),N24-P24,"") -> 25 | R24: 25 | S24: =IF(AND(N24<>"",R24<>""),N24-R24,"") -> 0 | T24: 46120 | U24: Uploaded | V24: =IFERROR(R24/N24,"") -> 1 | W24: =IFERROR(S24/N24,"") -> 0 | X24: Amit Gangwar | Y24: AR73171 | Z24: Pradeep Kumar Kulshreshtha | AA24: TR587524 | AB24: =IFERROR(VLOOKUP(B24,'Scheme Master'!$B$4:$C$79,2,FALSE),"") -> 540 | AC24: =IF(AND(AB24<>"",N24<>""),AB24*N24,"") -> 13500 | AE24: 1230 | AF24: =IF(OR(AD24<>"",AE24<>""),AD24+AE24,"") -> 1230 | AG24: =IF(AND(AC24<>"",AF24<>""),AC24-AF24,"") -> 12270 | AH24: =IF(AND(AC24<>"",AC24>0,AF24<>""),AF24/AC24,"") -> 0.091111111 | AI24: =IF(AH24="","",IF(AF24>AC24,"🔴 Critical - Over Budget",IF(AH24>0.4,"⚠️ Approval Required","✅ Auto-Approved"))) -> ✅ Auto-Approved | AJ24: =IF(AI24="","",IF(AF24>AC24,"URGENT: Expenses exceed total income. Immediate review needed.",IF(AH24>0.4,"Expenses exceed 40% of income. Management approval required.","Within budget. No approval needed."))) -> Within budget. No approval needed. | AO24: =IF(AI24="","",IF(AI24="✅ Auto-Approved","✅ Approved (Auto - Within Budget)",IF(AN24="","⏳ Awaiting Approval",IF(AN24="Approved","✅ Approved by "&AL24&" on "&TEXT(AM24,"mm/dd/yyyy"),IF(AN24="Rejected","❌ Rejected by "&AL24&" - Review Expenses",IF(AN24="Pending Review","🔍 Under Review by "&AL24,IF(AN24="Escalated","⬆️ Escalated - Senior Management Review",""))))))) -> ✅ Approved (Auto - Within Budget) | AR24: Not Paid
A25: 24 | B25: ODOP-RPL | C25: 01042026-28 | D25: Normal | E25: Handicraft | G25: Bamboo Work Artisan | H25: Uttar Pradesh Institute of Design and Research | I25: Amethi | J25: Uttar Pradesh | K25: 46117 | L25: 46117 | M25: 25 | N25: 24 | O25: =IF(AND(M25<>"",N25<>""),M25-N25,"") -> 1 | P25: 0 | Q25: =IF(AND(N25<>"",P25<>""),N25-P25,"") -> 24 | R25: 24 | S25: =IF(AND(N25<>"",R25<>""),N25-R25,"") -> 0 | T25: 46120 | U25: Uploaded | V25: =IFERROR(R25/N25,"") -> 1 | W25: =IFERROR(S25/N25,"") -> 0 | X25: Amit Gangwar | Y25: AR73171 | Z25: Pradeep Kumar Kulshreshtha | AA25: TR587524 | AB25: =IFERROR(VLOOKUP(B25,'Scheme Master'!$B$4:$C$79,2,FALSE),"") -> 540 | AC25: =IF(AND(AB25<>"",N25<>""),AB25*N25,"") -> 12960 | AF25: =IF(OR(AD25<>"",AE25<>""),AD25+AE25,"") | AG25: =IF(AND(AC25<>"",AF25<>""),AC25-AF25,"") | AH25: =IF(AND(AC25<>"",AC25>0,AF25<>""),AF25/AC25,"") | AI25: =IF(AH25="","",IF(AF25>AC25,"🔴 Critical - Over Budget",IF(AH25>0.4,"⚠️ Approval Required","✅ Auto-Approved"))) | AJ25: =IF(AI25="","",IF(AF25>AC25,"URGENT: Expenses exceed total income. Immediate review needed.",IF(AH25>0.4,"Expenses exceed 40% of income. Management approval required.","Within budget. No approval needed."))) | AO25: =IF(AI25="","",IF(AI25="✅ Auto-Approved","✅ Approved (Auto - Within Budget)",IF(AN25="","⏳ Awaiting Approval",IF(AN25="Approved","✅ Approved by "&AL25&" on "&TEXT(AM25,"mm/dd/yyyy"),IF(AN25="Rejected","❌ Rejected by "&AL25&" - Review Expenses",IF(AN25="Pending Review","🔍 Under Review by "&AL25,IF(AN25="Escalated","⬆️ Escalated - Senior Management Review",""))))))) | AR25: Not Paid
A26: 25 | B26: PMKVY 4.0 | C26: GJSCI_VSSY-RPL/2026-04 | D26: Normal | E26: Gems and Jewellery | G26: Jewellery Frame and Component Maker | H26: UPICON | I26: Kanpur Nagar | J26: Uttar Pradesh | K26: 46117 | L26: 46117 | M26: 25 | N26: 19 | O26: =IF(AND(M26<>"",N26<>""),M26-N26,"") -> 6 | P26: 18 | Q26: =IF(AND(N26<>"",P26<>""),N26-P26,"") -> 1 | R26: 19 | S26: =IF(AND(N26<>"",R26<>""),N26-R26,"") -> 0 | T26: 46118 | U26: Uploaded | V26: =IFERROR(R26/N26,"") -> 1 | W26: =IFERROR(S26/N26,"") -> 0 | X26: Mohd Nadeem | Y26: AR29759 | Z26: Anju Verma | AA26: TR341602 | AB26: =IFERROR(VLOOKUP(B26,'Scheme Master'!$B$4:$C$79,2,FALSE),"") -> 480 | AC26: =IF(AND(AB26<>"",N26<>""),AB26*N26,"") -> 9120 | AF26: =IF(OR(AD26<>"",AE26<>""),AD26+AE26,"") | AG26: =IF(AND(AC26<>"",AF26<>""),AC26-AF26,"") | AH26: =IF(AND(AC26<>"",AC26>0,AF26<>""),AF26/AC26,"") | AI26: =IF(AH26="","",IF(AF26>AC26,"🔴 Critical - Over Budget",IF(AH26>0.4,"⚠️ Approval Required","✅ Auto-Approved"))) | AJ26: =IF(AI26="","",IF(AF26>AC26,"URGENT: Expenses exceed total income. Immediate review needed.",IF(AH26>0.4,"Expenses exceed 40% of income. Management approval required.","Within budget. No approval needed."))) | AO26: =IF(AI26="","",IF(AI26="✅ Auto-Approved","✅ Approved (Auto - Within Budget)",IF(AN26="","⏳ Awaiting Approval",IF(AN26="Approved","✅ Approved by "&AL26&" on "&TEXT(AM26,"mm/dd/yyyy"),IF(AN26="Rejected","❌ Rejected by "&AL26&" - Review Expenses",IF(AN26="Pending Review","🔍 Under Review by "&AL26,IF(AN26="Escalated","⬆️ Escalated - Senior Management Review",""))))))) | AR26: Not Paid
A27: 26 | B27: PMAY-G-STT | C27: 3583922 | D27: Normal | E27: Construction | G27: Rural Mason V4.0 | H27: Merapath Education Limited | I27: Nandurbar | J27: Maharashtra | K27: 46117 | L27: 46117 | M27: 15 | N27: 15 | O27: =IF(AND(M27<>"",N27<>""),M27-N27,"") -> 0 | P27: 9 | Q27: =IF(AND(N27<>"",P27<>""),N27-P27,"") -> 6 | R27: 14 | S27: =IF(AND(N27<>"",R27<>""),N27-R27,"") -> 1 | T27: 46120 | U27: Uploaded | V27: =IFERROR(R27/N27,"") -> 0.93333333 | W27: =IFERROR(S27/N27,"") -> 0.066666667 | X27: Krishnapal | Y27: AR77228 | Z27: Vijay Meghval | AA27: TR506611 | AB27: =IFERROR(VLOOKUP(B27,'Scheme Master'!$B$4:$C$79,2,FALSE),"") -> 720 | AC27: =IF(AND(AB27<>"",N27<>""),AB27*N27,"") -> 10800 | AF27: =IF(OR(AD27<>"",AE27<>""),AD27+AE27,"") | AG27: =IF(AND(AC27<>"",AF27<>""),AC27-AF27,"") | AH27: =IF(AND(AC27<>"",AC27>0,AF27<>""),AF27/AC27,"") | AI27: =IF(AH27="","",IF(AF27>AC27,"🔴 Critical - Over Budget",IF(AH27>0.4,"⚠️ Approval Required","✅ Auto-Approved"))) | AJ27: =IF(AI27="","",IF(AF27>AC27,"URGENT: Expenses exceed total income. Immediate review needed.",IF(AH27>0.4,"Expenses exceed 40% of income. Management approval required.","Within budget. No approval needed."))) | AO27: =IF(AI27="","",IF(AI27="✅ Auto-Approved","✅ Approved (Auto - Within Budget)",IF(AN27="","⏳ Awaiting Approval",IF(AN27="Approved","✅ Approved by "&AL27&" on "&TEXT(AM27,"mm/dd/yyyy"),IF(AN27="Rejected","❌ Rejected by "&AL27&" - Review Expenses",IF(AN27="Pending Review","🔍 Under Review by "&AL27,IF(AN27="Escalated","⬆️ Escalated - Senior Management Review",""))))))) | AR27: Not Paid
A28: 27 | B28: BSDMA-RPL | C28: 3727804 | D28: Day 2 | E28: Construction | G28: Masonry of Earthquake-Resistant Building | H28: Astric Solutions | I28: Siwan | J28: Bihar | K28: 46116 | L28: 46117 | M28: 25 | N28: 24 | O28: =IF(AND(M28<>"",N28<>""),M28-N28,"") -> 1 | P28: 24 | Q28: =IF(AND(N28<>"",P28<>""),N28-P28,"") -> 0 | R28: 23 | S28: =IF(AND(N28<>"",R28<>""),N28-R28,"") -> 1 | T28: 46119 | U28: Uploaded | V28: =IFERROR(R28/N28,"") -> 0.95833333 | W28: =IFERROR(S28/N28,"") -> 0.041666667 | X28: Mohd Naseem | Y28: AR145441 | Z28: Priyanshu Ranjan Upadhyay | AA28: TR544100 | AB28: =IFERROR(VLOOKUP(B28,'Scheme Master'!$B$4:$C$79,2,FALSE),"") -> 540 | AC28: =IF(AND(AB28<>"",N28<>""),AB28*N28,"") -> 12960 | AF28: =IF(OR(AD28<>"",AE28<>""),AD28+AE28,"") | AG28: =IF(AND(AC28<>"",AF28<>""),AC28-AF28,"") | AH28: =IF(AND(AC28<>"",AC28>0,AF28<>""),AF28/AC28,"") | AI28: =IF(AH28="","",IF(AF28>AC28,"🔴 Critical - Over Budget",IF(AH28>0.4,"⚠️ Approval Required","✅ Auto-Approved"))) | AJ28: =IF(AI28="","",IF(AF28>AC28,"URGENT: Expenses exceed total income. Immediate review needed.",IF(AH28>0.4,"Expenses exceed 40% of income. Management approval required.","Within budget. No approval needed."))) | AO28: =IF(AI28="","",IF(AI28="✅ Auto-Approved","✅ Approved (Auto - Within Budget)",IF(AN28="","⏳ Awaiting Approval",IF(AN28="Approved","✅ Approved by "&AL28&" on "&TEXT(AM28,"mm/dd/yyyy"),IF(AN28="Rejected","❌ Rejected by "&AL28&" - Review Expenses",IF(AN28="Pending Review","🔍 Under Review by "&AL28,IF(AN28="Escalated","⬆️ Escalated - Senior Management Review",""))))))) | AR28: Not Paid
A29: 28 | B29: PM Vishwakarma | C29: 3739641 | D29: Day 0 | E29: Construction | G29: Brick Mason -Basic( CON/N0160 ) | H29: LEARNET SKILLS LIMITED | I29: JAMMU | J29: JAMMU AND KASHMIR | K29: Postpone | L29: Postpone | M29: 45 | O29: =IF(AND(M29<>"",N29<>""),M29-N29,"") | Q29: =IF(AND(N29<>"",P29<>""),N29-P29,"") | S29: =IF(AND(N29<>"",R29<>""),N29-R29,"") | V29: =IFERROR(R29/N29,"") | W29: =IFERROR(S29/N29,"") | AB29: =IFERROR(VLOOKUP(B29,'Scheme Master'!$B$4:$C$79,2,FALSE),"") -> 360 | AC29: =IF(AND(AB29<>"",N29<>""),AB29*N29,"") | AF29: =IF(OR(AD29<>"",AE29<>""),AD29+AE29,"") | AG29: =IF(AND(AC29<>"",AF29<>""),AC29-AF29,"") | AH29: =IF(AND(AC29<>"",AC29>0,AF29<>""),AF29/AC29,"") | AI29: =IF(AH29="","",IF(AF29>AC29,"🔴 Critical - Over Budget",IF(AH29>0.4,"⚠️ Approval Required","✅ Auto-Approved"))) | AJ29: =IF(AI29="","",IF(AF29>AC29,"URGENT: Expenses exceed total income. Immediate review needed.",IF(AH29>0.4,"Expenses exceed 40% of income. Management approval required.","Within budget. No approval needed."))) | AO29: =IF(AI29="","",IF(AI29="✅ Auto-Approved","✅ Approved (Auto - Within Budget)",IF(AN29="","⏳ Awaiting Approval",IF(AN29="Approved","✅ Approved by "&AL29&" on "&TEXT(AM29,"mm/dd/yyyy"),IF(AN29="Rejected","❌ Rejected by "&AL29&" - Review Expenses",IF(AN29="Pending Review","🔍 Under Review by "&AL29,IF(AN29="Escalated","⬆️ Escalated - Senior Management Review","")))))))
A30: 29 | B30: PM Vishwakarma | C30: 3739236 | D30: Day 6 | E30: Construction | G30: Brick Mason -Basic( CON/N0160 ) | H30: CENTRAL TOOL ROOM AND TRAINING CENTRE | I30: KALAHANDI | J30: ODISHA | K30: 46117 | L30: 46117 | M30: 12 | N30: 11 | O30: =IF(AND(M30<>"",N30<>""),M30-N30,"") -> 1 | P30: 11 | Q30: =IF(AND(N30<>"",P30<>""),N30-P30,"") -> 0 | R30: 11 | S30: =IF(AND(N30<>"",R30<>""),N30-R30,"") -> 0 | T30: 46117 | U30: Uploaded | V30: =IFERROR(R30/N30,"") -> 1 | W30: =IFERROR(S30/N30,"") -> 0 | X30: Chittaranjan panda | Y30: AR142325 | Z30: Jaga Prasad Pattnaik | AA30: TR546304 | AB30: =IFERROR(VLOOKUP(B30,'Scheme Master'!$B$4:$C$79,2,FALSE),"") -> 360 | AC30: =IF(AND(AB30<>"",N30<>""),AB30*N30,"") -> 3960 | AD30: 2000 | AE30: 1000 | AF30: =IF(OR(AD30<>"",AE30<>""),AD30+AE30,"") -> 3000 | AG30: =IF(AND(AC30<>"",AF30<>""),AC30-AF30,"") -> 960 | AH30: =IF(AND(AC30<>"",AC30>0,AF30<>""),AF30/AC30,"") -> 0.75757576 | AI30: =IF(AH30="","",IF(AF30>AC30,"🔴 Critical - Over Budget",IF(AH30>0.4,"⚠️ Approval Required","✅ Auto-Approved"))) -> ⚠️ Approval Required | AJ30: =IF(AI30="","",IF(AF30>AC30,"URGENT: Expenses exceed total income. Immediate review needed.",IF(AH30>0.4,"Expenses exceed 40% of income. Management approval required.","Within budget. No approval needed."))) -> Expenses exceed 40% of income. Management approval required. | AK30: Nisha Saifi | AL30: Richa Mehta | AM30: 46114 | AN30: Approved | AO30: =IF(AI30="","",IF(AI30="✅ Auto-Approved","✅ Approved (Auto - Within Budget)",IF(AN30="","⏳ Awaiting Approval",IF(AN30="Approved","✅ Approved by "&AL30&" on "&TEXT(AM30,"mm/dd/yyyy"),IF(AN30="Rejected","❌ Rejected by "&AL30&" - Review Expenses",IF(AN30="Pending Review","🔍 Under Review by "&AL30,IF(AN30="Escalated","⬆️ Escalated - Senior Management Review",""))))))) -> ✅ Approved by Richa Mehta on 04/02/2026 | AR30: Not Paid
A31: =A30+1 -> 30 | B31: PMKVY 4.0 | C31: 3708112 | D31: Normal | E31: Green Jobs | G31: Swacchta Saarthi( SGJ/MCr-0015) | H31: Shrawani Srivastava | I31: KHAMMAM | J31: TELANGANA | K31: 46118 | L31: 46118 | M31: 44 | N31: 43 | O31: =IF(AND(M31<>"",N31<>""),M31-N31,"") -> 1 | P31: 16 | Q31: =IF(AND(N31<>"",P31<>""),N31-P31,"") -> 27 | R31: 43 | S31: =IF(AND(N31<>"",R31<>""),N31-R31,"") -> 0 | T31: 46120 | U31: Uploaded | V31: =IFERROR(R31/N31,"") -> 1 | W31: =IFERROR(S31/N31,"") -> 0 | X31: Kanagala Ramasurekanand | Y31: AR102979 | Z31: Satish Kumar | AA31: TR29766 | AB31: =IFERROR(VLOOKUP(B31,'Scheme Master'!$B$4:$C$79,2,FALSE),"") -> 480 | AC31: =IF(AND(AB31<>"",N31<>""),AB31*N31,"") -> 20640 | AD31: 2000 | AE31: 1000 | AF31: =IF(OR(AD31<>"",AE31<>""),AD31+AE31,"") -> 3000 | AG31: =IF(AND(AC31<>"",AF31<>""),AC31-AF31,"") -> 17640 | AH31: =IF(AND(AC31<>"",AC31>0,AF31<>""),AF31/AC31,"") -> 0.14534884 | AI31: =IF(AH31="","",IF(AF31>AC31,"🔴 Critical - Over Budget",IF(AH31>0.4,"⚠️ Approval Required","✅ Auto-Approved"))) -> ✅ Auto-Approved | AJ31: =IF(AI31="","",IF(AF31>AC31,"URGENT: Expenses exceed total income. Immediate review needed.",IF(AH31>0.4,"Expenses exceed 40% of income. Management approval required.","Within budget. No approval needed."))) -> Within budget. No approval needed. | AK31: Nisha Saifi | AL31: Richa Mehta | AM31: 46117 | AN31: Approved | AO31: =IF(AI31="","",IF(AI31="✅ Auto-Approved","✅ Approved (Auto - Within Budget)",IF(AN31="","⏳ Awaiting Approval",IF(AN31="Approved","✅ Approved by "&AL31&" on "&TEXT(AM31,"mm/dd/yyyy"),IF(AN31="Rejected","❌ Rejected by "&AL31&" - Review Expenses",IF(AN31="Pending Review","🔍 Under Review by "&AL31,IF(AN31="Escalated","⬆️ Escalated - Senior Management Review",""))))))) -> ✅ Approved (Auto - Within Budget) | AR31: Not Paid
A32: =A31+1 -> 31 | B32: ODOP-RPL | C32: 01042026-29 | D32: Normal | E32: Handicraft | G32: Bamboo Work Artisan | H32: Uttar Pradesh Institute of Design and Research | I32: Amethi | J32: Uttar Pradesh | K32: 46118 | L32: 46118 | M32: 25 | N32: 23 | O32: =IF(AND(M32<>"",N32<>""),M32-N32,"") -> 2 | P32: 0 | Q32: =IF(AND(N32<>"",P32<>""),N32-P32,"") -> 23 | R32: 23 | S32: =IF(AND(N32<>"",R32<>""),N32-R32,"") -> 0 | T32: 46120 | U32: Uploaded | V32: =IFERROR(R32/N32,"") -> 1 | W32: =IFERROR(S32/N32,"") -> 0 | X32: Amit Gangwar | Y32: AR73171 | Z32: Pradeep Kumar Kulshreshtha | AA32: TR587524 | AB32: =IFERROR(VLOOKUP(B32,'Scheme Master'!$B$4:$C$79,2,FALSE),"") -> 540 | AC32: =IF(AND(AB32<>"",N32<>""),AB32*N32,"") -> 12420 | AE32: 1230 | AF32: =IF(OR(AD32<>"",AE32<>""),AD32+AE32,"") -> 1230 | AG32: =IF(AND(AC32<>"",AF32<>""),AC32-AF32,"") -> 11190 | AH32: =IF(AND(AC32<>"",AC32>0,AF32<>""),AF32/AC32,"") -> 0.099033816 | AI32: =IF(AH32="","",IF(AF32>AC32,"🔴 Critical - Over Budget",IF(AH32>0.4,"⚠️ Approval Required","✅ Auto-Approved"))) -> ✅ Auto-Approved | AJ32: =IF(AI32="","",IF(AF32>AC32,"URGENT: Expenses exceed total income. Immediate review needed.",IF(AH32>0.4,"Expenses exceed 40% of income. Management approval required.","Within budget. No approval needed."))) -> Within budget. No approval needed. | AO32: =IF(AI32="","",IF(AI32="✅ Auto-Approved","✅ Approved (Auto - Within Budget)",IF(AN32="","⏳ Awaiting Approval",IF(AN32="Approved","✅ Approved by "&AL32&" on "&TEXT(AM32,"mm/dd/yyyy"),IF(AN32="Rejected","❌ Rejected by "&AL32&" - Review Expenses",IF(AN32="Pending Review","🔍 Under Review by "&AL32,IF(AN32="Escalated","⬆️ Escalated - Senior Management Review",""))))))) -> ✅ Approved (Auto - Within Budget) | AR32: Not Paid
A33: =A32+1 -> 32 | B33: ODOP-RPL | C33: 01042026-30 | D33: Normal | E33: Handicraft | G33: Bamboo Work Artisan | H33: Uttar Pradesh Institute of Design and Research | I33: Amethi | J33: Uttar Pradesh | K33: 46118 | L33: 46118 | M33: 25 | N33: 23 | O33: =IF(AND(M33<>"",N33<>""),M33-N33,"") -> 2 | P33: 0 | Q33: =IF(AND(N33<>"",P33<>""),N33-P33,"") -> 23 | R33: 23 | S33: =IF(AND(N33<>"",R33<>""),N33-R33,"") -> 0 | T33: 46120 | U33: Uploaded | V33: =IFERROR(R33/N33,"") -> 1 | W33: =IFERROR(S33/N33,"") -> 0 | X33: Amit Gangwar | Y33: AR73171 | Z33: Pradeep Kumar Kulshreshtha | AA33: TR587524 | AB33: =IFERROR(VLOOKUP(B33,'Scheme Master'!$B$4:$C$79,2,FALSE),"") -> 540 | AC33: =IF(AND(AB33<>"",N33<>""),AB33*N33,"") -> 12420 | AF33: =IF(OR(AD33<>"",AE33<>""),AD33+AE33,"") | AG33: =IF(AND(AC33<>"",AF33<>""),AC33-AF33,"") | AH33: =IF(AND(AC33<>"",AC33>0,AF33<>""),AF33/AC33,"") | AI33: =IF(AH33="","",IF(AF33>AC33,"🔴 Critical - Over Budget",IF(AH33>0.4,"⚠️ Approval Required","✅ Auto-Approved"))) | AJ33: =IF(AI33="","",IF(AF33>AC33,"URGENT: Expenses exceed total income. Immediate review needed.",IF(AH33>0.4,"Expenses exceed 40% of income. Management approval required.","Within budget. No approval needed."))) | AO33: =IF(AI33="","",IF(AI33="✅ Auto-Approved","✅ Approved (Auto - Within Budget)",IF(AN33="","⏳ Awaiting Approval",IF(AN33="Approved","✅ Approved by "&AL33&" on "&TEXT(AM33,"mm/dd/yyyy"),IF(AN33="Rejected","❌ Rejected by "&AL33&" - Review Expenses",IF(AN33="Pending Review","🔍 Under Review by "&AL33,IF(AN33="Escalated","⬆️ Escalated - Senior Management Review",""))))))) | AR33: Not Paid
A34: =A33+1 -> 33 | B34: ODOP-RPL | C34: 01042026-33 | D34: Normal | E34: Handicraft | G34: Traditional Hand Embroiderer | H34: Uttar Pradesh Institute of Design and Research | I34: Lucknow | J34: UttarPradesh | K34: 46118 | L34: 46118 | M34: 25 | N34: 24 | O34: =IF(AND(M34<>"",N34<>""),M34-N34,"") -> 1 | P34: 0 | Q34: =IF(AND(N34<>"",P34<>""),N34-P34,"") -> 24 | R34: 24 | S34: =IF(AND(N34<>"",R34<>""),N34-R34,"") -> 0 | T34: 46120 | U34: Uploaded | V34: =IFERROR(R34/N34,"") -> 1 | W34: =IFERROR(S34/N34,"") -> 0 | X34: Mohd Navi | Y34: AR2351 | Z34: Ritu Singh | AA34: TR353756 | AB34: =IFERROR(VLOOKUP(B34,'Scheme Master'!$B$4:$C$79,2,FALSE),"") -> 540 | AC34: =IF(AND(AB34<>"",N34<>""),AB34*N34,"") -> 12960 | AD34: 2000 | AF34: =IF(OR(AD34<>"",AE34<>""),AD34+AE34,"") -> 2000 | AG34: =IF(AND(AC34<>"",AF34<>""),AC34-AF34,"") -> 10960 | AH34: =IF(AND(AC34<>"",AC34>0,AF34<>""),AF34/AC34,"") -> 0.15432099 | AI34: =IF(AH34="","",IF(AF34>AC34,"🔴 Critical - Over Budget",IF(AH34>0.4,"⚠️ Approval Required","✅ Auto-Approved"))) -> ✅ Auto-Approved | AJ34: =IF(AI34="","",IF(AF34>AC34,"URGENT: Expenses exceed total income. Immediate review needed.",IF(AH34>0.4,"Expenses exceed 40% of income. Management approval required.","Within budget. No approval needed."))) -> Within budget. No approval needed. | AO34: =IF(AI34="","",IF(AI34="✅ Auto-Approved","✅ Approved (Auto - Within Budget)",IF(AN34="","⏳ Awaiting Approval",IF(AN34="Approved","✅ Approved by "&AL34&" on "&TEXT(AM34,"mm/dd/yyyy"),IF(AN34="Rejected","❌ Rejected by "&AL34&" - Review Expenses",IF(AN34="Pending Review","🔍 Under Review by "&AL34,IF(AN34="Escalated","⬆️ Escalated - Senior Management Review",""))))))) -> ✅ Approved (Auto - Within Budget) | AR34: Not Paid
A35: =A34+1 -> 34 | B35: ODOP-RPL | C35: 01042026-34 | D35: Normal | E35: Handicraft | G35: Traditional Hand Embroiderer | H35: Uttar Pradesh Institute of Design and Research | I35: Lucknow | J35: UttarPradesh | K35: 46118 | L35: 46118 | M35: 25 | N35: 22 | O35: =IF(AND(M35<>"",N35<>""),M35-N35,"") -> 3 | P35: 0 | Q35: =IF(AND(N35<>"",P35<>""),N35-P35,"") -> 22 | R35: 22 | S35: =IF(AND(N35<>"",R35<>""),N35-R35,"") -> 0 | T35: 46120 | U35: Uploaded | V35: =IFERROR(R35/N35,"") -> 1 | W35: =IFERROR(S35/N35,"") -> 0 | X35: Mohd Navi | Y35: AR2351 | Z35: Ritu Singh | AA35: TR353756 | AB35: =IFERROR(VLOOKUP(B35,'Scheme Master'!$B$4:$C$79,2,FALSE),"") -> 540 | AC35: =IF(AND(AB35<>"",N35<>""),AB35*N35,"") -> 11880 | AD35: 2000 | AF35: =IF(OR(AD35<>"",AE35<>""),AD35+AE35,"") -> 2000 | AG35: =IF(AND(AC35<>"",AF35<>""),AC35-AF35,"") -> 9880 | AH35: =IF(AND(AC35<>"",AC35>0,AF35<>""),AF35/AC35,"") -> 0.16835017 | AI35: =IF(AH35="","",IF(AF35>AC35,"🔴 Critical - Over Budget",IF(AH35>0.4,"⚠️ Approval Required","✅ Auto-Approved"))) -> ✅ Auto-Approved | AJ35: =IF(AI35="","",IF(AF35>AC35,"URGENT: Expenses exceed total income. Immediate review needed.",IF(AH35>0.4,"Expenses exceed 40% of income. Management approval required.","Within budget. No approval needed."))) -> Within budget. No approval needed. | AO35: =IF(AI35="","",IF(AI35="✅ Auto-Approved","✅ Approved (Auto - Within Budget)",IF(AN35="","⏳ Awaiting Approval",IF(AN35="Approved","✅ Approved by "&AL35&" on "&TEXT(AM35,"mm/dd/yyyy"),IF(AN35="Rejected","❌ Rejected by "&AL35&" - Review Expenses",IF(AN35="Pending Review","🔍 Under Review by "&AL35,IF(AN35="Escalated","⬆️ Escalated - Senior Management Review",""))))))) -> ✅ Approved (Auto - Within Budget) | AR35: Not Paid
A36: =A35+1 -> 35 | B36: PM Vishwakarma | C36: 3757304 | D36: Day 0 | E36: Handicraft | G36: Basic sculptor and stone artist (Moortikar)( HCS/N1506 ) | H36: National Federation of Farmers' Procurement, Processing & Retailing Cooperatives of India Ltd., (NACOF) | I36: KURNOOL | J36: ANDHRA PRADESH | K36: 46118 | L36: 46118 | M36: 39 | N36: 26 | O36: =IF(AND(M36<>"",N36<>""),M36-N36,"") -> 13 | P36: 23 | Q36: =IF(AND(N36<>"",P36<>""),N36-P36,"") -> 3 | R36: 26 | S36: =IF(AND(N36<>"",R36<>""),N36-R36,"") -> 0 | T36: 46118 | U36: Uploaded | V36: =IFERROR(R36/N36,"") -> 1 | W36: =IFERROR(S36/N36,"") -> 0 | X36: Shaik Sabeena | Y36: AR138412 Sabeena@321 | Z36: Shaik Sabeena | AA36: TR562299 | AB36: =IFERROR(VLOOKUP(B36,'Scheme Master'!$B$4:$C$79,2,FALSE),"") -> 360 | AC36: =IF(AND(AB36<>"",N36<>""),AB36*N36,"") -> 9360 | AD36: 2000 | AF36: =IF(OR(AD36<>"",AE36<>""),AD36+AE36,"") -> 2000 | AG36: =IF(AND(AC36<>"",AF36<>""),AC36-AF36,"") -> 7360 | AH36: =IF(AND(AC36<>"",AC36>0,AF36<>""),AF36/AC36,"") -> 0.21367521 | AI36: =IF(AH36="","",IF(AF36>AC36,"🔴 Critical - Over Budget",IF(AH36>0.4,"⚠️ Approval Required","✅ Auto-Approved"))) -> ✅ Auto-Approved | AJ36: =IF(AI36="","",IF(AF36>AC36,"URGENT: Expenses exceed total income. Immediate review needed.",IF(AH36>0.4,"Expenses exceed 40% of income. Management approval required.","Within budget. No approval needed."))) -> Within budget. No approval needed. | AO36: =IF(AI36="","",IF(AI36="✅ Auto-Approved","✅ Approved (Auto - Within Budget)",IF(AN36="","⏳ Awaiting Approval",IF(AN36="Approved","✅ Approved by "&AL36&" on "&TEXT(AM36,"mm/dd/yyyy"),IF(AN36="Rejected","❌ Rejected by "&AL36&" - Review Expenses",IF(AN36="Pending Review","🔍 Under Review by "&AL36,IF(AN36="Escalated","⬆️ Escalated - Senior Management Review",""))))))) -> ✅ Approved (Auto - Within Budget) | AR36: Not Paid
A37: =A36+1 -> 36 | B37: PM Vishwakarma | C37: 3744204 | D37: Day 6 | E37: Construction | G37: Brick Mason -Basic( CON/N0160 ) | H37: National Federation of Farmers' Procurement, Processing & Retailing Cooperatives of India Ltd., (NACOF) | I37: SRI POTTI SRIRAMULU NELLORE | J37: ANDHRA PRADESH | K37: Postpone | L37: Postpone | M37: 37 | O37: =IF(AND(M37<>"",N37<>""),M37-N37,"") | Q37: =IF(AND(N37<>"",P37<>""),N37-P37,"") | S37: =IF(AND(N37<>"",R37<>""),N37-R37,"") | V37: =IFERROR(R37/N37,"") | W37: =IFERROR(S37/N37,"") | X37: Cherukuru Tirupalu | Y37: AR95412 | AB37: =IFERROR(VLOOKUP(B37,'Scheme Master'!$B$4:$C$79,2,FALSE),"") -> 360 | AC37: =IF(AND(AB37<>"",N37<>""),AB37*N37,"") | AF37: =IF(OR(AD37<>"",AE37<>""),AD37+AE37,"") | AG37: =IF(AND(AC37<>"",AF37<>""),AC37-AF37,"") | AH37: =IF(AND(AC37<>"",AC37>0,AF37<>""),AF37/AC37,"") | AI37: =IF(AH37="","",IF(AF37>AC37,"🔴 Critical - Over Budget",IF(AH37>0.4,"⚠️ Approval Required","✅ Auto-Approved"))) | AJ37: =IF(AI37="","",IF(AF37>AC37,"URGENT: Expenses exceed total income. Immediate review needed.",IF(AH37>0.4,"Expenses exceed 40% of income. Management approval required.","Within budget. No approval needed."))) | AO37: =IF(AI37="","",IF(AI37="✅ Auto-Approved","✅ Approved (Auto - Within Budget)",IF(AN37="","⏳ Awaiting Approval",IF(AN37="Approved","✅ Approved by "&AL37&" on "&TEXT(AM37,"mm/dd/yyyy"),IF(AN37="Rejected","❌ Rejected by "&AL37&" - Review Expenses",IF(AN37="Pending Review","🔍 Under Review by "&AL37,IF(AN37="Escalated","⬆️ Escalated - Senior Management Review","")))))))
A38: =A37+1 -> 37 | B38: PM Vishwakarma | C38: 3739384 | D38: Day 0 | E38: Construction | G38: Brick Mason -Basic( CON/N0160 ) | H38: ORION EDUTECH PRIVATE LIMITED | I38: DARRANG | J38: ASSAM | K38: Postpone | L38: Postpone | M38: 41 | O38: =IF(AND(M38<>"",N38<>""),M38-N38,"") | Q38: =IF(AND(N38<>"",P38<>""),N38-P38,"") | S38: =IF(AND(N38<>"",R38<>""),N38-R38,"") | V38: =IFERROR(R38/N38,"") | W38: =IFERROR(S38/N38,"") | X38: Lalbabu Ahmed | Y38: AR103539 | AB38: =IFERROR(VLOOKUP(B38,'Scheme Master'!$B$4:$C$79,2,FALSE),"") -> 360 | AC38: =IF(AND(AB38<>"",N38<>""),AB38*N38,"") | AF38: =IF(OR(AD38<>"",AE38<>""),AD38+AE38,"") | AG38: =IF(AND(AC38<>"",AF38<>""),AC38-AF38,"") | AH38: =IF(AND(AC38<>"",AC38>0,AF38<>""),AF38/AC38,"") | AI38: =IF(AH38="","",IF(AF38>AC38,"🔴 Critical - Over Budget",IF(AH38>0.4,"⚠️ Approval Required","✅ Auto-Approved"))) | AJ38: =IF(AI38="","",IF(AF38>AC38,"URGENT: Expenses exceed total income. Immediate review needed.",IF(AH38>0.4,"Expenses exceed 40% of income. Management approval required.","Within budget. No approval needed."))) | AO38: =IF(AI38="","",IF(AI38="✅ Auto-Approved","✅ Approved (Auto - Within Budget)",IF(AN38="","⏳ Awaiting Approval",IF(AN38="Approved","✅ Approved by "&AL38&" on "&TEXT(AM38,"mm/dd/yyyy"),IF(AN38="Rejected","❌ Rejected by "&AL38&" - Review Expenses",IF(AN38="Pending Review","🔍 Under Review by "&AL38,IF(AN38="Escalated","⬆️ Escalated - Senior Management Review","")))))))
A39: =A38+1 -> 38 | B39: PM Vishwakarma | C39: 3758294 | D39: Day 0 | E39: Handicraft | G39: Traditional Soft Toy Maker( HCS/N7355 ) | H39: Government ITI, Moradabad | I39: MORADABAD | J39: UTTAR PRADESH | K39: Not Conducted | L39: Batch Cancelled | M39: 5 | O39: =IF(AND(M39<>"",N39<>""),M39-N39,"") | Q39: =IF(AND(N39<>"",P39<>""),N39-P39,"") | S39: =IF(AND(N39<>"",R39<>""),N39-R39,"") | V39: =IFERROR(R39/N39,"") | W39: =IFERROR(S39/N39,"") | AB39: =IFERROR(VLOOKUP(B39,'Scheme Master'!$B$4:$C$79,2,FALSE),"") -> 360 | AC39: =IF(AND(AB39<>"",N39<>""),AB39*N39,"") | AF39: =IF(OR(AD39<>"",AE39<>""),AD39+AE39,"") | AG39: =IF(AND(AC39<>"",AF39<>""),AC39-AF39,"") | AH39: =IF(AND(AC39<>"",AC39>0,AF39<>""),AF39/AC39,"") | AI39: =IF(AH39="","",IF(AF39>AC39,"🔴 Critical - Over Budget",IF(AH39>0.4,"⚠️ Approval Required","✅ Auto-Approved"))) | AJ39: =IF(AI39="","",IF(AF39>AC39,"URGENT: Expenses exceed total income. Immediate review needed.",IF(AH39>0.4,"Expenses exceed 40% of income. Management approval required.","Within budget. No approval needed."))) | AO39: =IF(AI39="","",IF(AI39="✅ Auto-Approved","✅ Approved (Auto - Within Budget)",IF(AN39="","⏳ Awaiting Approval",IF(AN39="Approved","✅ Approved by "&AL39&" on "&TEXT(AM39,"mm/dd/yyyy"),IF(AN39="Rejected","❌ Rejected by "&AL39&" - Review Expenses",IF(AN39="Pending Review","🔍 Under Review by "&AL39,IF(AN39="Escalated","⬆️ Escalated - Senior Management Review","")))))))
A40: =A39+1 -> 39 | B40: MinistryRPL | C40: 3733913 | D40: Normal | E40: Green Jobs | G40: Desludging Assistant | H40: SAHIBA ALI | I40: DHANBAD | J40: JHARKHAND | K40: 46119 | L40: 46119 | M40: 35 | N40: 24 | O40: =IF(AND(M40<>"",N40<>""),M40-N40,"") -> 11 | P40: 24 | Q40: =IF(AND(N40<>"",P40<>""),N40-P40,"") -> 0 | R40: 24 | S40: =IF(AND(N40<>"",R40<>""),N40-R40,"") -> 0 | T40: 46120 | U40: Uploaded | V40: =IFERROR(R40/N40,"") -> 1 | W40: =IFERROR(S40/N40,"") -> 0 | X40: DEEPAK KUMAR BHAGAT | Y40: AR72856 | Z40: Md Faizan Ansari | AA40: TR627892 | AB40: =IFERROR(VLOOKUP(B40,'Scheme Master'!$B$4:$C$79,2,FALSE),"") -> 200 | AC40: =IF(AND(AB40<>"",N40<>""),AB40*N40,"") -> 4800 | AF40: =IF(OR(AD40<>"",AE40<>""),AD40+AE40,"") | AG40: =IF(AND(AC40<>"",AF40<>""),AC40-AF40,"") | AH40: =IF(AND(AC40<>"",AC40>0,AF40<>""),AF40/AC40,"") | AI40: =IF(AH40="","",IF(AF40>AC40,"🔴 Critical - Over Budget",IF(AH40>0.4,"⚠️ Approval Required","✅ Auto-Approved"))) | AJ40: =IF(AI40="","",IF(AF40>AC40,"URGENT: Expenses exceed total income. Immediate review needed.",IF(AH40>0.4,"Expenses exceed 40% of income. Management approval required.","Within budget. No approval needed."))) | AO40: =IF(AI40="","",IF(AI40="✅ Auto-Approved","✅ Approved (Auto - Within Budget)",IF(AN40="","⏳ Awaiting Approval",IF(AN40="Approved","✅ Approved by "&AL40&" on "&TEXT(AM40,"mm/dd/yyyy"),IF(AN40="Rejected","❌ Rejected by "&AL40&" - Review Expenses",IF(AN40="Pending Review","🔍 Under Review by "&AL40,IF(AN40="Escalated","⬆️ Escalated - Senior Management Review",""))))))) | AR40: Not Paid
A41: =A40+1 -> 40 | B41: Suryamitra Skill Development Programme | C41: 3598642 | D41: Normal | E41: Green Jobs | G41: Solar PV Installer (Suryamitra) | H41: SARVA SHIKSHA VIKAS SAMITI | I41: BHOPAL | J41: MADHYA PRADESH | K41: 46119 | L41: 46119 | M41: 30 | N41: 30 | O41: =IF(AND(M41<>"",N41<>""),M41-N41,"") -> 0 | P41: 21 | Q41: =IF(AND(N41<>"",P41<>""),N41-P41,"") -> 9 | R41: 30 | S41: =IF(AND(N41<>"",R41<>""),N41-R41,"") -> 0 | T41: 46121 | U41: Uploaded | V41: =IFERROR(R41/N41,"") -> 1 | W41: =IFERROR(S41/N41,"") -> 0 | X41: Mohd Navi | Y41: AR2351 | Z41: Ayush Batham | AA41: TR443962 | AB41: =IFERROR(VLOOKUP(B41,'Scheme Master'!$B$4:$C$79,2,FALSE),"") -> 400 | AC41: =IF(AND(AB41<>"",N41<>""),AB41*N41,"") -> 12000 | AD41: 2000 | AE41: 2000 | AF41: =IF(OR(AD41<>"",AE41<>""),AD41+AE41,"") -> 4000 | AG41: =IF(AND(AC41<>"",AF41<>""),AC41-AF41,"") -> 8000 | AH41: =IF(AND(AC41<>"",AC41>0,AF41<>""),AF41/AC41,"") -> 0.33333333 | AI41: =IF(AH41="","",IF(AF41>AC41,"🔴 Critical - Over Budget",IF(AH41>0.4,"⚠️ Approval Required","✅ Auto-Approved"))) -> ✅ Auto-Approved | AJ41: =IF(AI41="","",IF(AF41>AC41,"URGENT: Expenses exceed total income. Immediate review needed.",IF(AH41>0.4,"Expenses exceed 40% of income. Management approval required.","Within budget. No approval needed."))) -> Within budget. No approval needed. | AO41: =IF(AI41="","",IF(AI41="✅ Auto-Approved","✅ Approved (Auto - Within Budget)",IF(AN41="","⏳ Awaiting Approval",IF(AN41="Approved","✅ Approved by "&AL41&" on "&TEXT(AM41,"mm/dd/yyyy"),IF(AN41="Rejected","❌ Rejected by "&AL41&" - Review Expenses",IF(AN41="Pending Review","🔍 Under Review by "&AL41,IF(AN41="Escalated","⬆️ Escalated - Senior Management Review",""))))))) -> ✅ Approved (Auto - Within Budget) | AR41: Not Paid
A42: =A41+1 -> 41 | B42: ODOP-RPL | C42: 01042026-31 | D42: Normal | E42: Handicraft | G42: Bamboo Work Artisan | H42: Uttar Pradesh Institute of Design and Research | I42: Amethi | J42: UttarPradesh | K42: 46119 | L42: 46119 | M42: 25 | N42: 25 | O42: =IF(AND(M42<>"",N42<>""),M42-N42,"") -> 0 | P42: 0 | Q42: =IF(AND(N42<>"",P42<>""),N42-P42,"") -> 25 | R42: 25 | S42: =IF(AND(N42<>"",R42<>""),N42-R42,"") -> 0 | T42: 46120 | U42: Uploaded | V42: =IFERROR(R42/N42,"") -> 1 | W42: =IFERROR(S42/N42,"") -> 0 | X42: Amit Gangwar | Y42: AR73171 | Z42: Pradeep Kumar Kulshreshtha | AA42: TR587524 | AB42: =IFERROR(VLOOKUP(B42,'Scheme Master'!$B$4:$C$79,2,FALSE),"") -> 540 | AC42: =IF(AND(AB42<>"",N42<>""),AB42*N42,"") -> 13500 | AF42: =IF(OR(AD42<>"",AE42<>""),AD42+AE42,"") | AG42: =IF(AND(AC42<>"",AF42<>""),AC42-AF42,"") | AH42: =IF(AND(AC42<>"",AC42>0,AF42<>""),AF42/AC42,"") | AI42: =IF(AH42="","",IF(AF42>AC42,"🔴 Critical - Over Budget",IF(AH42>0.4,"⚠️ Approval Required","✅ Auto-Approved"))) | AJ42: =IF(AI42="","",IF(AF42>AC42,"URGENT: Expenses exceed total income. Immediate review needed.",IF(AH42>0.4,"Expenses exceed 40% of income. Management approval required.","Within budget. No approval needed."))) | AO42: =IF(AI42="","",IF(AI42="✅ Auto-Approved","✅ Approved (Auto - Within Budget)",IF(AN42="","⏳ Awaiting Approval",IF(AN42="Approved","✅ Approved by "&AL42&" on "&TEXT(AM42,"mm/dd/yyyy"),IF(AN42="Rejected","❌ Rejected by "&AL42&" - Review Expenses",IF(AN42="Pending Review","🔍 Under Review by "&AL42,IF(AN42="Escalated","⬆️ Escalated - Senior Management Review",""))))))) | AR42: Not Paid
A43: =A42+1 -> 42 | B43: ODOP-RPL | C43: 01042026-32 | D43: Normal | E43: Handicraft | G43: Bamboo Work Artisan | H43: Uttar Pradesh Institute of Design and Research | I43: Amethi | J43: UttarPradesh | K43: 46119 | L43: 46119 | M43: 25 | N43: 22 | O43: =IF(AND(M43<>"",N43<>""),M43-N43,"") -> 3 | P43: 0 | Q43: =IF(AND(N43<>"",P43<>""),N43-P43,"") -> 22 | R43: 22 | S43: =IF(AND(N43<>"",R43<>""),N43-R43,"") -> 0 | T43: 46120 | U43: Uploaded | V43: =IFERROR(R43/N43,"") -> 1 | W43: =IFERROR(S43/N43,"") -> 0 | X43: Amit Gangwar | Y43: AR73171 | Z43: Pradeep Kumar Kulshreshtha | AA43: TR587524 | AB43: =IFERROR(VLOOKUP(B43,'Scheme Master'!$B$4:$C$79,2,FALSE),"") -> 540 | AC43: =IF(AND(AB43<>"",N43<>""),AB43*N43,"") -> 11880 | AE43: 1230 | AF43: =IF(OR(AD43<>"",AE43<>""),AD43+AE43,"") -> 1230 | AG43: =IF(AND(AC43<>"",AF43<>""),AC43-AF43,"") -> 10650 | AH43: =IF(AND(AC43<>"",AC43>0,AF43<>""),AF43/AC43,"") -> 0.10353535 | AI43: =IF(AH43="","",IF(AF43>AC43,"🔴 Critical - Over Budget",IF(AH43>0.4,"⚠️ Approval Required","✅ Auto-Approved"))) -> ✅ Auto-Approved | AJ43: =IF(AI43="","",IF(AF43>AC43,"URGENT: Expenses exceed total income. Immediate review needed.",IF(AH43>0.4,"Expenses exceed 40% of income. Management approval required.","Within budget. No approval needed."))) -> Within budget. No approval needed. | AO43: =IF(AI43="","",IF(AI43="✅ Auto-Approved","✅ Approved (Auto - Within Budget)",IF(AN43="","⏳ Awaiting Approval",IF(AN43="Approved","✅ Approved by "&AL43&" on "&TEXT(AM43,"mm/dd/yyyy"),IF(AN43="Rejected","❌ Rejected by "&AL43&" - Review Expenses",IF(AN43="Pending Review","🔍 Under Review by "&AL43,IF(AN43="Escalated","⬆️ Escalated - Senior Management Review",""))))))) -> ✅ Approved (Auto - Within Budget) | AR43: Not Paid
A44: =A43+1 -> 43 | B44: NAPS | C44: NAPS_07-04-2026 | D44: Normal | E44: Gems and Jewellery | G44: Jewellery Polisher and Cleaner (Version 4.0) | H44: ROYAL CHAINS PRIVATE LIMITED | I44: Delhi | J44: New Delhi | K44: Not Conducted | L44: Not Conducted | M44: 1 | O44: =IF(AND(M44<>"",N44<>""),M44-N44,"") | Q44: =IF(AND(N44<>"",P44<>""),N44-P44,"") | S44: =IF(AND(N44<>"",R44<>""),N44-R44,"") | V44: =IFERROR(R44/N44,"") | W44: =IFERROR(S44/N44,"") | AB44: =IFERROR(VLOOKUP(B44,'Scheme Master'!$B$4:$C$79,2,FALSE),"") -> 70 | AC44: =IF(AND(AB44<>"",N44<>""),AB44*N44,"") | AF44: =IF(OR(AD44<>"",AE44<>""),AD44+AE44,"") | AG44: =IF(AND(AC44<>"",AF44<>""),AC44-AF44,"") | AH44: =IF(AND(AC44<>"",AC44>0,AF44<>""),AF44/AC44,"") | AI44: =IF(AH44="","",IF(AF44>AC44,"🔴 Critical - Over Budget",IF(AH44>0.4,"⚠️ Approval Required","✅ Auto-Approved"))) | AJ44: =IF(AI44="","",IF(AF44>AC44,"URGENT: Expenses exceed total income. Immediate review needed.",IF(AH44>0.4,"Expenses exceed 40% of income. Management approval required.","Within budget. No approval needed."))) | AO44: =IF(AI44="","",IF(AI44="✅ Auto-Approved","✅ Approved (Auto - Within Budget)",IF(AN44="","⏳ Awaiting Approval",IF(AN44="Approved","✅ Approved by "&AL44&" on "&TEXT(AM44,"mm/dd/yyyy"),IF(AN44="Rejected","❌ Rejected by "&AL44&" - Review Expenses",IF(AN44="Pending Review","🔍 Under Review by "&AL44,IF(AN44="Escalated","⬆️ Escalated - Senior Management Review","")))))))
A45: =A44+1 -> 44 | B45: PMAY-G-STT | C45: 3646796 | D45: Normal | E45: Construction | G45: Rural Mason V4.0 | H45: Bhavsar Foundation | I45: Jalna | J45: Maharashtra | K45: 46119 | L45: 46119 | M45: 20 | N45: 18 | O45: =IF(AND(M45<>"",N45<>""),M45-N45,"") -> 2 | P45: 18 | Q45: =IF(AND(N45<>"",P45<>""),N45-P45,"") -> 0 | R45: 16 | S45: =IF(AND(N45<>"",R45<>""),N45-R45,"") -> 2 | T45: 46122 | U45: Uploaded | V45: =IFERROR(R45/N45,"") -> 0.88888889 | W45: =IFERROR(S45/N45,"") -> 0.11111111 | X45: Krishnapal | Y45: AR77228 | Z45: Sudama Saket | AA45: TR343497 | AB45: =IFERROR(VLOOKUP(B45,'Scheme Master'!$B$4:$C$79,2,FALSE),"") -> 720 | AC45: =IF(AND(AB45<>"",N45<>""),AB45*N45,"") -> 12960 | AF45: =IF(OR(AD45<>"",AE45<>""),AD45+AE45,"") | AG45: =IF(AND(AC45<>"",AF45<>""),AC45-AF45,"") | AH45: =IF(AND(AC45<>"",AC45>0,AF45<>""),AF45/AC45,"") | AI45: =IF(AH45="","",IF(AF45>AC45,"🔴 Critical - Over Budget",IF(AH45>0.4,"⚠️ Approval Required","✅ Auto-Approved"))) | AJ45: =IF(AI45="","",IF(AF45>AC45,"URGENT: Expenses exceed total income. Immediate review needed.",IF(AH45>0.4,"Expenses exceed 40% of income. Management approval required.","Within budget. No approval needed."))) | AO45: =IF(AI45="","",IF(AI45="✅ Auto-Approved","✅ Approved (Auto - Within Budget)",IF(AN45="","⏳ Awaiting Approval",IF(AN45="Approved","✅ Approved by "&AL45&" on "&TEXT(AM45,"mm/dd/yyyy"),IF(AN45="Rejected","❌ Rejected by "&AL45&" - Review Expenses",IF(AN45="Pending Review","🔍 Under Review by "&AL45,IF(AN45="Escalated","⬆️ Escalated - Senior Management Review",""))))))) | AR45: Not Paid
A46: =A45+1 -> 45 | B46: PM Vishwakarma | C46: 3757429 | D46: Day 0 | E46: Handicraft | G46: Potter (Kumhar) including traditional ceramics and terracotta product maker( HCS/N9213 ) | H46: Government ITI, World Bank Mahila, Varanasi | I46: VARANASI | J46: UTTAR PRADESH | K46: 46119 | L46: 46119 | M46: 8 | N46: 5 | O46: =IF(AND(M46<>"",N46<>""),M46-N46,"") -> 3 | P46: 5 | Q46: =IF(AND(N46<>"",P46<>""),N46-P46,"") -> 0 | R46: 5 | S46: =IF(AND(N46<>"",R46<>""),N46-R46,"") -> 0 | T46: 46119 | U46: Uploaded | V46: =IFERROR(R46/N46,"") -> 1 | W46: =IFERROR(S46/N46,"") -> 0 | X46: Ramsagar | Y46: AR137565 | Z46: Ramsagar | AA46: TR560839 | AB46: =IFERROR(VLOOKUP(B46,'Scheme Master'!$B$4:$C$79,2,FALSE),"") -> 360 | AC46: =IF(AND(AB46<>"",N46<>""),AB46*N46,"") -> 1800 | AF46: =IF(OR(AD46<>"",AE46<>""),AD46+AE46,"") | AG46: =IF(AND(AC46<>"",AF46<>""),AC46-AF46,"") | AH46: =IF(AND(AC46<>"",AC46>0,AF46<>""),AF46/AC46,"") | AI46: =IF(AH46="","",IF(AF46>AC46,"🔴 Critical - Over Budget",IF(AH46>0.4,"⚠️ Approval Required","✅ Auto-Approved"))) | AJ46: =IF(AI46="","",IF(AF46>AC46,"URGENT: Expenses exceed total income. Immediate review needed.",IF(AH46>0.4,"Expenses exceed 40% of income. Management approval required.","Within budget. No approval needed."))) | AO46: =IF(AI46="","",IF(AI46="✅ Auto-Approved","✅ Approved (Auto - Within Budget)",IF(AN46="","⏳ Awaiting Approval",IF(AN46="Approved","✅ Approved by "&AL46&" on "&TEXT(AM46,"mm/dd/yyyy"),IF(AN46="Rejected","❌ Rejected by "&AL46&" - Review Expenses",IF(AN46="Pending Review","🔍 Under Review by "&AL46,IF(AN46="Escalated","⬆️ Escalated - Senior Management Review",""))))))) | AR46: Not Paid
A47: =A46+1 -> 46 | B47: TOT | C47: TOT_MESC_07-04-2026 | D47: Normal | E47: Media & Entertainment | G47: 3D Printing Operator | H47: Dhanvantri Private Iti | K47: 46119 | L47: 46119 | M47: 3 | N47: 3 | O47: =IF(AND(M47<>"",N47<>""),M47-N47,"") -> 0 | P47: 3 | Q47: =IF(AND(N47<>"",P47<>""),N47-P47,"") -> 0 | R47: 3 | S47: =IF(AND(N47<>"",R47<>""),N47-R47,"") -> 0 | T47: 46119 | U47: Uploaded | V47: =IFERROR(R47/N47,"") -> 1 | W47: =IFERROR(S47/N47,"") -> 0 | X47: Mohd Nadeem | Y47: AR29759 | AB47: =IFERROR(VLOOKUP(B47,'Scheme Master'!$B$4:$C$79,2,FALSE),"") -> 400 | AC47: =IF(AND(AB47<>"",N47<>""),AB47*N47,"") -> 1200 | AF47: =IF(OR(AD47<>"",AE47<>""),AD47+AE47,"") | AG47: =IF(AND(AC47<>"",AF47<>""),AC47-AF47,"") | AH47: =IF(AND(AC47<>"",AC47>0,AF47<>""),AF47/AC47,"") | AI47: =IF(AH47="","",IF(AF47>AC47,"🔴 Critical - Over Budget",IF(AH47>0.4,"⚠️ Approval Required","✅ Auto-Approved"))) | AJ47: =IF(AI47="","",IF(AF47>AC47,"URGENT: Expenses exceed total income. Immediate review needed.",IF(AH47>0.4,"Expenses exceed 40% of income. Management approval required.","Within budget. No approval needed."))) | AO47: =IF(AI47="","",IF(AI47="✅ Auto-Approved","✅ Approved (Auto - Within Budget)",IF(AN47="","⏳ Awaiting Approval",IF(AN47="Approved","✅ Approved by "&AL47&" on "&TEXT(AM47,"mm/dd/yyyy"),IF(AN47="Rejected","❌ Rejected by "&AL47&" - Review Expenses",IF(AN47="Pending Review","🔍 Under Review by "&AL47,IF(AN47="Escalated","⬆️ Escalated - Senior Management Review",""))))))) | AR47: Not Paid
A48: =A47+1 -> 47 | B48: PMKVY 4.0 | C48: 3729854 | D48: Normal | E48: Green Jobs | G48: Desludging Assistant | H48: NATIONAL SAFAI KARAMCHARIS FINANCE AND DEVELOPMENT CORPORATION | I48: PURBI CHAMPARAN | J48: BIHAR | K48: 46120 | L48: 46120 | M48: 24 | N48: 19 | O48: =IF(AND(M48<>"",N48<>""),M48-N48,"") -> 5 | P48: 19 | Q48: =IF(AND(N48<>"",P48<>""),N48-P48,"") -> 0 | R48: 19 | S48: =IF(AND(N48<>"",R48<>""),N48-R48,"") -> 0 | T48: 46121 | U48: Uploaded | V48: =IFERROR(R48/N48,"") -> 1 | W48: =IFERROR(S48/N48,"") -> 0 | X48: DEEPAK KUMAR BHAGAT | Y48: AR72856 | Z48: Md Faizan Ansari | AA48: TR627892 | AB48: =IFERROR(VLOOKUP(B48,'Scheme Master'!$B$4:$C$79,2,FALSE),"") -> 480 | AC48: =IF(AND(AB48<>"",N48<>""),AB48*N48,"") -> 9120 | AD48: 2000 | AE48: 1000 | AF48: =IF(OR(AD48<>"",AE48<>""),AD48+AE48,"") -> 3000 | AG48: =IF(AND(AC48<>"",AF48<>""),AC48-AF48,"") -> 6120 | AH48: =IF(AND(AC48<>"",AC48>0,AF48<>""),AF48/AC48,"") -> 0.32894737 | AI48: =IF(AH48="","",IF(AF48>AC48,"🔴 Critical - Over Budget",IF(AH48>0.4,"⚠️ Approval Required","✅ Auto-Approved"))) -> ✅ Auto-Approved | AJ48: =IF(AI48="","",IF(AF48>AC48,"URGENT: Expenses exceed total income. Immediate review needed.",IF(AH48>0.4,"Expenses exceed 40% of income. Management approval required.","Within budget. No approval needed."))) -> Within budget. No approval needed. | AO48: =IF(AI48="","",IF(AI48="✅ Auto-Approved","✅ Approved (Auto - Within Budget)",IF(AN48="","⏳ Awaiting Approval",IF(AN48="Approved","✅ Approved by "&AL48&" on "&TEXT(AM48,"mm/dd/yyyy"),IF(AN48="Rejected","❌ Rejected by "&AL48&" - Review Expenses",IF(AN48="Pending Review","🔍 Under Review by "&AL48,IF(AN48="Escalated","⬆️ Escalated - Senior Management Review",""))))))) -> ✅ Approved (Auto - Within Budget) | AR48: Not Paid
A49: =A48+1 -> 48 | B49: SSC Affiliated: Skill Council for Green Jobs | C49: Non-PMKVY_01 | D49: Normal | E49: Green Jobs | G49: Solar PV Installer (Suryamitra) v4 | H49: Go Renewable Technologies | I49: Surendranagar | J49: Gujarat | K49: 46120 | L49: 46120 | M49: 31 | N49: 21 | O49: =IF(AND(M49<>"",N49<>""),M49-N49,"") -> 10 | P49: 0 | Q49: =IF(AND(N49<>"",P49<>""),N49-P49,"") -> 21 | R49: 21 | S49: =IF(AND(N49<>"",R49<>""),N49-R49,"") -> 0 | T49: Result Sheet Only 09-04-2026 | U49: Uploaded | V49: =IFERROR(R49/N49,"") -> 1 | W49: =IFERROR(S49/N49,"") -> 0 | X49: Gautam Parmar | Y49: AR65813 | Z49: Nevilkumar Gajendrabhai Patel | AA49: TR183325 | AB49: =IFERROR(VLOOKUP(B49,'Scheme Master'!$B$4:$C$79,2,FALSE),"") -> 400 | AC49: =IF(AND(AB49<>"",N49<>""),AB49*N49,"") -> 8400 | AF49: =IF(OR(AD49<>"",AE49<>""),AD49+AE49,"") | AG49: =IF(AND(AC49<>"",AF49<>""),AC49-AF49,"") | AH49: =IF(AND(AC49<>"",AC49>0,AF49<>""),AF49/AC49,"") | AI49: =IF(AH49="","",IF(AF49>AC49,"🔴 Critical - Over Budget",IF(AH49>0.4,"⚠️ Approval Required","✅ Auto-Approved"))) | AO49: =IF(AI49="","",IF(AI49="✅ Auto-Approved","✅ Approved (Auto - Within Budget)",IF(AN49="","⏳ Awaiting Approval",IF(AN49="Approved","✅ Approved by "&AL49&" on "&TEXT(AM49,"mm/dd/yyyy"),IF(AN49="Rejected","❌ Rejected by "&AL49&" - Review Expenses",IF(AN49="Pending Review","🔍 Under Review by "&AL49,IF(AN49="Escalated","⬆️ Escalated - Senior Management Review",""))))))) | AR49: Not Paid
A50: =A49+1 -> 49 | B50: BSDMA-RPL | C50: 3726957 | D50: Normal | E50: Construction | G50: Masonry of Earthquake-Resistant Building | H50: NIFA Infocom Service Pvt Ltd. | I50: Gaya | J50: Bihar | K50: 46120 | L50: 46121 | M50: 27 | N50: 27 | O50: =IF(AND(M50<>"",N50<>""),M50-N50,"") -> 0 | P50: 27 | Q50: =IF(AND(N50<>"",P50<>""),N50-P50,"") -> 0 | R50: 26 | S50: =IF(AND(N50<>"",R50<>""),N50-R50,"") -> 1 | T50: 46124 | U50: Uploaded | V50: =IFERROR(R50/N50,"") -> 0.96296296 | W50: =IFERROR(S50/N50,"") -> 0.037037037 | X50: Mohd Naseem Mallik | Y50: AR145441 | Z50: Dharmendra Kumar Sharma | AA50: TR545478 | AB50: =IFERROR(VLOOKUP(B50,'Scheme Master'!$B$4:$C$79,2,FALSE),"") -> 540 | AC50: =IF(AND(AB50<>"",N50<>""),AB50*N50,"") -> 14580 | AF50: =IF(OR(AD50<>"",AE50<>""),AD50+AE50,"") | AG50: =IF(AND(AC50<>"",AF50<>""),AC50-AF50,"") | AH50: =IF(AND(AC50<>"",AC50>0,AF50<>""),AF50/AC50,"") | AI50: =IF(AH50="","",IF(AF50>AC50,"🔴 Critical - Over Budget",IF(AH50>0.4,"⚠️ Approval Required","✅ Auto-Approved"))) | AO50: =IF(AI50="","",IF(AI50="✅ Auto-Approved","✅ Approved (Auto - Within Budget)",IF(AN50="","⏳ Awaiting Approval",IF(AN50="Approved","✅ Approved by "&AL50&" on "&TEXT(AM50,"mm/dd/yyyy"),IF(AN50="Rejected","❌ Rejected by "&AL50&" - Review Expenses",IF(AN50="Pending Review","🔍 Under Review by "&AL50,IF(AN50="Escalated","⬆️ Escalated - Senior Management Review",""))))))) | AR50: Not Paid
A51: =A50+1 -> 50 | B51: PM Vishwakarma | C51: 3757269 | D51: Day 0 | E51: Gems and Jewellery | G51: Goldsmith (Sunar)( G&J/N0612 ) | H51: Govt ITI Kahalgaon (Bhagalpur) | I51: BHAGALPUR | J51: BIHAR | K51: 46120 | L51: 46120 | M51: 26 | N51: 25 | O51: =IF(AND(M51<>"",N51<>""),M51-N51,"") -> 1 | P51: 25 | Q51: =IF(AND(N51<>"",P51<>""),N51-P51,"") -> 0 | R51: 25 | S51: =IF(AND(N51<>"",R51<>""),N51-R51,"") -> 0 | T51: 46120 | U51: Uploaded | V51: =IFERROR(R51/N51,"") -> 1 | W51: =IFERROR(S51/N51,"") -> 0 | X51: SOURAV KUMAR | Y51: AR119030/Sourav@2025 | Z51: SOURAV KUMAR | AA51: TR582022 | AB51: =IFERROR(VLOOKUP(B51,'Scheme Master'!$B$4:$C$79,2,FALSE),"") -> 360 | AC51: =IF(AND(AB51<>"",N51<>""),AB51*N51,"") -> 9000 | AD51: 2000 | AF51: =IF(OR(AD51<>"",AE51<>""),AD51+AE51,"") -> 2000 | AG51: =IF(AND(AC51<>"",AF51<>""),AC51-AF51,"") -> 7000 | AH51: =IF(AND(AC51<>"",AC51>0,AF51<>""),AF51/AC51,"") -> 0.22222222 | AI51: =IF(AH51="","",IF(AF51>AC51,"🔴 Critical - Over Budget",IF(AH51>0.4,"⚠️ Approval Required","✅ Auto-Approved"))) -> ✅ Auto-Approved | AJ51: =IF(AI51="","",IF(AF51>AC51,"URGENT: Expenses exceed total income. Immediate review needed.",IF(AH51>0.4,"Expenses exceed 40% of income. Management approval required.","Within budget. No approval needed."))) -> Within budget. No approval needed. | AO51: =IF(AI51="","",IF(AI51="✅ Auto-Approved","✅ Approved (Auto - Within Budget)",IF(AN51="","⏳ Awaiting Approval",IF(AN51="Approved","✅ Approved by "&AL51&" on "&TEXT(AM51,"mm/dd/yyyy"),IF(AN51="Rejected","❌ Rejected by "&AL51&" - Review Expenses",IF(AN51="Pending Review","🔍 Under Review by "&AL51,IF(AN51="Escalated","⬆️ Escalated - Senior Management Review",""))))))) -> ✅ Approved (Auto - Within Budget) | AR51: Not Paid
A52: =A51+1 -> 51 | B52: PM Vishwakarma | C52: 3758604 | D52: Day 0 | E52: Gems and Jewellery | G52: Goldsmith (Sunar)( G&J/N0612 ) | H52: GOVT ITI, GARHWA | I52: GARHWA | J52: JHARKHAND | K52: 46120 | L52: 46120 | M52: 15 | N52: 8 | O52: =IF(AND(M52<>"",N52<>""),M52-N52,"") -> 7 | P52: 8 | Q52: =IF(AND(N52<>"",P52<>""),N52-P52,"") -> 0 | R52: 8 | S52: =IF(AND(N52<>"",R52<>""),N52-R52,"") -> 0 | T52: 46120 | U52: Uploaded | V52: =IFERROR(R52/N52,"") -> 1 | W52: =IFERROR(S52/N52,"") -> 0 | X52: BIKRANT SAGAR MINZ | Y52: AR179820 | Z52: BIKRANT SAGAR MINZ | AA52: TR660935 | AB52: =IFERROR(VLOOKUP(B52,'Scheme Master'!$B$4:$C$79,2,FALSE),"") -> 360 | AC52: =IF(AND(AB52<>"",N52<>""),AB52*N52,"") -> 2880 | AD52: 700 | AF52: =IF(OR(AD52<>"",AE52<>""),AD52+AE52,"") -> 700 | AG52: =IF(AND(AC52<>"",AF52<>""),AC52-AF52,"") -> 2180 | AH52: =IF(AND(AC52<>"",AC52>0,AF52<>""),AF52/AC52,"") -> 0.24305556 | AI52: =IF(AH52="","",IF(AF52>AC52,"🔴 Critical - Over Budget",IF(AH52>0.4,"⚠️ Approval Required","✅ Auto-Approved"))) -> ✅ Auto-Approved | AJ52: =IF(AI52="","",IF(AF52>AC52,"URGENT: Expenses exceed total income. Immediate review needed.",IF(AH52>0.4,"Expenses exceed 40% of income. Management approval required.","Within budget. No approval needed."))) -> Within budget. No approval needed. | AO52: =IF(AI52="","",IF(AI52="✅ Auto-Approved","✅ Approved (Auto - Within Budget)",IF(AN52="","⏳ Awaiting Approval",IF(AN52="Approved","✅ Approved by "&AL52&" on "&TEXT(AM52,"mm/dd/yyyy"),IF(AN52="Rejected","❌ Rejected by "&AL52&" - Review Expenses",IF(AN52="Pending Review","🔍 Under Review by "&AL52,IF(AN52="Escalated","⬆️ Escalated - Senior Management Review",""))))))) -> ✅ Approved (Auto - Within Budget) | AR52: Not Paid
A53: =A52+1 -> 52 | B53: PM Vishwakarma | C53: 3759508 | D53: Day 0 | E53: Gems and Jewellery | G53: Goldsmith (Sunar)( G&J/N0612 ) | H53: Government ITI, Mehdawal, Sant Kabir Nagar | I53: SANT KABIR NAGAR | J53: UTTAR PRADESH | K53: 46120 | L53: 46120 | M53: 5 | N53: 5 | O53: =IF(AND(M53<>"",N53<>""),M53-N53,"") -> 0 | P53: 4 | Q53: =IF(AND(N53<>"",P53<>""),N53-P53,"") -> 1 | R53: 5 | S53: =IF(AND(N53<>"",R53<>""),N53-R53,"") -> 0 | T53: 46120 | U53: Uploaded | V53: =IFERROR(R53/N53,"") -> 1 | W53: =IFERROR(S53/N53,"") -> 0 | X53: satyam | Y53: AR158476 | Z53: satyam | AA53: TR609159 | AB53: =IFERROR(VLOOKUP(B53,'Scheme Master'!$B$4:$C$79,2,FALSE),"") -> 360 | AC53: =IF(AND(AB53<>"",N53<>""),AB53*N53,"") -> 1800 | AD53: 500 | AF53: =IF(OR(AD53<>"",AE53<>""),AD53+AE53,"") -> 500 | AG53: =IF(AND(AC53<>"",AF53<>""),AC53-AF53,"") -> 1300 | AH53: =IF(AND(AC53<>"",AC53>0,AF53<>""),AF53/AC53,"") -> 0.27777778 | AI53: =IF(AH53="","",IF(AF53>AC53,"🔴 Critical - Over Budget",IF(AH53>0.4,"⚠️ Approval Required","✅ Auto-Approved"))) -> ✅ Auto-Approved | AJ53: =IF(AI53="","",IF(AF53>AC53,"URGENT: Expenses exceed total income. Immediate review needed.",IF(AH53>0.4,"Expenses exceed 40% of income. Management approval required.","Within budget. No approval needed."))) -> Within budget. No approval needed. | AO53: =IF(AI53="","",IF(AI53="✅ Auto-Approved","✅ Approved (Auto - Within Budget)",IF(AN53="","⏳ Awaiting Approval",IF(AN53="Approved","✅ Approved by "&AL53&" on "&TEXT(AM53,"mm/dd/yyyy"),IF(AN53="Rejected","❌ Rejected by "&AL53&" - Review Expenses",IF(AN53="Pending Review","🔍 Under Review by "&AL53,IF(AN53="Escalated","⬆️ Escalated - Senior Management Review",""))))))) -> ✅ Approved (Auto - Within Budget) | AR53: Not Paid
A54: =A53+1 -> 53 | B54: PMKVY 4.0 | C54: 3747386 | D54: Normal | E54: Green Jobs | G54: Desludging Assistant | H54: NATIONAL SAFAI KARAMCHARIS FINANCE AND DEVELOPMENT CORPORATION | I54: SRINAGAR | J54: JAMMU AND KASHMIR | K54: 46121 | L54: 46121 | M54: 21 | N54: 14 | O54: =IF(AND(M54<>"",N54<>""),M54-N54,"") -> 7 | P54: 14 | Q54: =IF(AND(N54<>"",P54<>""),N54-P54,"") -> 0 | R54: 14 | S54: =IF(AND(N54<>"",R54<>""),N54-R54,"") -> 0 | T54: 46121 | U54: Uploaded | V54: =IFERROR(R54/N54,"") -> 1 | W54: =IFERROR(S54/N54,"") -> 0 | X54: Wajid Bashir | Y54: AR84804 | Z54: Danishwar Fayaz | AA54: TR294080 | AB54: =IFERROR(VLOOKUP(B54,'Scheme Master'!$B$4:$C$79,2,FALSE),"") -> 480 | AC54: =IF(AND(AB54<>"",N54<>""),AB54*N54,"") -> 6720 | AE54: 3000 | AF54: =IF(OR(AD54<>"",AE54<>""),AD54+AE54,"") -> 3000 | AG54: =IF(AND(AC54<>"",AF54<>""),AC54-AF54,"") -> 3720 | AH54: =IF(AND(AC54<>"",AC54>0,AF54<>""),AF54/AC54,"") -> 0.44642857 | AI54: =IF(AH54="","",IF(AF54>AC54,"🔴 Critical - Over Budget",IF(AH54>0.4,"⚠️ Approval Required","✅ Auto-Approved"))) -> ⚠️ Approval Required | AJ54: Mail Sent | AO54: =IF(AI54="","",IF(AI54="✅ Auto-Approved","✅ Approved (Auto - Within Budget)",IF(AN54="","⏳ Awaiting Approval",IF(AN54="Approved","✅ Approved by "&AL54&" on "&TEXT(AM54,"mm/dd/yyyy"),IF(AN54="Rejected","❌ Rejected by "&AL54&" - Review Expenses",IF(AN54="Pending Review","🔍 Under Review by "&AL54,IF(AN54="Escalated","⬆️ Escalated - Senior Management Review",""))))))) -> ⏳ Awaiting Approval
A55: =A54+1 -> 54 | B55: PMAY-G-STT | C55: 3582796 | D55: Normal | E55: Construction | G55: Rural Mason V4.0 | H55: SHIVA SHAKTHI MAHILA RURAL AND URBAN DEVELOPMENT ASSOCIATION | I55: Belagavi | J55: Karnataka | K55: 46121 | L55: 46122 | M55: 30 | N55: 21 | O55: 9 | P55: 30 | Q55: 0 | R55: 21 | S55: =IF(AND(N55<>"",R55<>""),N55-R55,"") -> 0 | T55: Result sheet Done i need confirmation | U55: Not Uploaded | V55: =IFERROR(R55/N55,"") -> 1 | W55: =IFERROR(S55/N55,"") -> 0 | X55: DEEPU RAJ | Y55: AR177654 | Z55: Ladamsaha Umarasaha Makandar | AA55: TR536125 | AB55: =IFERROR(VLOOKUP(B55,'Scheme Master'!$B$4:$C$79,2,FALSE),"") -> 720 | AC55: =IF(AND(AB55<>"",N55<>""),AB55*N55,"") -> 15120 | AF55: =IF(OR(AD55<>"",AE55<>""),AD55+AE55,"") | AG55: =IF(AND(AC55<>"",AF55<>""),AC55-AF55,"") | AH55: =IF(AND(AC55<>"",AC55>0,AF55<>""),AF55/AC55,"") | AI55: =IF(AH55="","",IF(AF55>AC55,"🔴 Critical - Over Budget",IF(AH55>0.4,"⚠️ Approval Required","✅ Auto-Approved"))) | AO55: =IF(AI55="","",IF(AI55="✅ Auto-Approved","✅ Approved (Auto - Within Budget)",IF(AN55="","⏳ Awaiting Approval",IF(AN55="Approved","✅ Approved by "&AL55&" on "&TEXT(AM55,"mm/dd/yyyy"),IF(AN55="Rejected","❌ Rejected by "&AL55&" - Review Expenses",IF(AN55="Pending Review","🔍 Under Review by "&AL55,IF(AN55="Escalated","⬆️ Escalated - Senior Management Review","")))))))
A56: =A55+1 -> 55 | B56: PM Vishwakarma | C56: 3760756 | D56: Day 0 | E56: Gems and Jewellery | G56: Goldsmith | H56: Government ITI, Moradabad | I56: MORADABAD | J56: UTTAR PRADESH | K56: 46121 | L56: 46121 | M56: 2 | N56: 2 | O56: =IF(AND(M56<>"",N56<>""),M56-N56,"") -> 0 | P56: 1 | Q56: =IF(AND(N56<>"",P56<>""),N56-P56,"") -> 1 | R56: 2 | S56: =IF(AND(N56<>"",R56<>""),N56-R56,"") -> 0 | T56: 46121 | U56: Uploaded | V56: =IFERROR(R56/N56,"") -> 1 | W56: =IFERROR(S56/N56,"") -> 0 | X56: Anmol Pandey | Y56: AR87617 | AB56: =IFERROR(VLOOKUP(B56,'Scheme Master'!$B$4:$C$79,2,FALSE),"") -> 360 | AC56: =IF(AND(AB56<>"",N56<>""),AB56*N56,"") -> 720 | AF56: =IF(OR(AD56<>"",AE56<>""),AD56+AE56,"") | AG56: =IF(AND(AC56<>"",AF56<>""),AC56-AF56,"") | AH56: =IF(AND(AC56<>"",AC56>0,AF56<>""),AF56/AC56,"") | AI56: =IF(AH56="","",IF(AF56>AC56,"🔴 Critical - Over Budget",IF(AH56>0.4,"⚠️ Approval Required","✅ Auto-Approved")))
A57: =A56+1 -> 56 | B57: TOA | C57: TOA_MESC_09-04-2026 | D57: Normal | E57: Media & Entertainment | G57: Account Executive | K57: 46121 | L57: 46121 | M57: 2 | N57: 2 | O57: =IF(AND(M57<>"",N57<>""),M57-N57,"") -> 0 | P57: 2 | Q57: =IF(AND(N57<>"",P57<>""),N57-P57,"") -> 0 | R57: 2 | S57: =IF(AND(N57<>"",R57<>""),N57-R57,"") -> 0 | T57: 46121 | U57: Uploaded | V57: =IFERROR(R57/N57,"") -> 1 | W57: =IFERROR(S57/N57,"") -> 0 | AB57: =IFERROR(VLOOKUP(B57,'Scheme Master'!$B$4:$C$79,2,FALSE),"") -> 400 | AC57: =IF(AND(AB57<>"",N57<>""),AB57*N57,"") -> 800 | AF57: =IF(OR(AD57<>"",AE57<>""),AD57+AE57,"") | AG57: =IF(AND(AC57<>"",AF57<>""),AC57-AF57,"") | AH57: =IF(AND(AC57<>"",AC57>0,AF57<>""),AF57/AC57,"") | AI57: =IF(AH57="","",IF(AF57>AC57,"🔴 Critical - Over Budget",IF(AH57>0.4,"⚠️ Approval Required","✅ Auto-Approved"))) | AO57: =IF(AI57="","",IF(AI57="✅ Auto-Approved","✅ Approved (Auto - Within Budget)",IF(AN57="","⏳ Awaiting Approval",IF(AN57="Approved","✅ Approved by "&AL57&" on "&TEXT(AM57,"mm/dd/yyyy"),IF(AN57="Rejected","❌ Rejected by "&AL57&" - Review Expenses",IF(AN57="Pending Review","🔍 Under Review by "&AL57,IF(AN57="Escalated","⬆️ Escalated - Senior Management Review","")))))))
A58: =A57+1 -> 57 | B58: TOA | C58: TOA_MESC_09-04-2026 | D58: Normal | E58: Media & Entertainment | G58: Assistant Costume Designer | K58: 46121 | L58: 46121 | M58: 1 | N58: 1 | O58: =IF(AND(M58<>"",N58<>""),M58-N58,"") -> 0 | P58: 1 | Q58: =IF(AND(N58<>"",P58<>""),N58-P58,"") -> 0 | R58: 1 | S58: =IF(AND(N58<>"",R58<>""),N58-R58,"") -> 0 | T58: 46121 | U58: Uploaded | V58: =IFERROR(R58/N58,"") -> 1 | W58: =IFERROR(S58/N58,"") -> 0 | AB58: =IFERROR(VLOOKUP(B58,'Scheme Master'!$B$4:$C$79,2,FALSE),"") -> 400 | AC58: =IF(AND(AB58<>"",N58<>""),AB58*N58,"") -> 400 | AF58: =IF(OR(AD58<>"",AE58<>""),AD58+AE58,"") | AG58: =IF(AND(AC58<>"",AF58<>""),AC58-AF58,"") | AH58: =IF(AND(AC58<>"",AC58>0,AF58<>""),AF58/AC58,"") | AI58: =IF(AH58="","",IF(AF58>AC58,"🔴 Critical - Over Budget",IF(AH58>0.4,"⚠️ Approval Required","✅ Auto-Approved"))) | AO58: =IF(AI58="","",IF(AI58="✅ Auto-Approved","✅ Approved (Auto - Within Budget)",IF(AN58="","⏳ Awaiting Approval",IF(AN58="Approved","✅ Approved by "&AL58&" on "&TEXT(AM58,"mm/dd/yyyy"),IF(AN58="Rejected","❌ Rejected by "&AL58&" - Review Expenses",IF(AN58="Pending Review","🔍 Under Review by "&AL58,IF(AN58="Escalated","⬆️ Escalated - Senior Management Review","")))))))
A59: =A58+1 -> 58 | B59: NAPS | C59: NAPS_09-04-2026 | D59: Normal | E59: Gems and Jewellery | G59: Planner | K59: 46121 | L59: 46121 | M59: 4 | N59: 4 | O59: =IF(AND(M59<>"",N59<>""),M59-N59,"") -> 0 | P59: 4 | Q59: =IF(AND(N59<>"",P59<>""),N59-P59,"") -> 0 | R59: 4 | S59: =IF(AND(N59<>"",R59<>""),N59-R59,"") -> 0 | T59: 46121 | U59: Uploaded | V59: =IFERROR(R59/N59,"") -> 1 | W59: =IFERROR(S59/N59,"") -> 0 | AB59: =IFERROR(VLOOKUP(B59,'Scheme Master'!$B$4:$C$79,2,FALSE),"") -> 70 | AC59: =IF(AND(AB59<>"",N59<>""),AB59*N59,"") -> 280 | AF59: =IF(OR(AD59<>"",AE59<>""),AD59+AE59,"") | AG59: =IF(AND(AC59<>"",AF59<>""),AC59-AF59,"") | AH59: =IF(AND(AC59<>"",AC59>0,AF59<>""),AF59/AC59,"") | AI59: =IF(AH59="","",IF(AF59>AC59,"🔴 Critical - Over Budget",IF(AH59>0.4,"⚠️ Approval Required","✅ Auto-Approved"))) | AJ59: =IF(AI59="","",IF(AF59>AC59,"URGENT: Expenses exceed total income. Immediate review needed.",IF(AH59>0.4,"Expenses exceed 40% of income. Management approval required.","Within budget. No approval needed."))) | AO59: =IF(AI59="","",IF(AI59="✅ Auto-Approved","✅ Approved (Auto - Within Budget)",IF(AN59="","⏳ Awaiting Approval",IF(AN59="Approved","✅ Approved by "&AL59&" on "&TEXT(AM59,"mm/dd/yyyy"),IF(AN59="Rejected","❌ Rejected by "&AL59&" - Review Expenses",IF(AN59="Pending Review","🔍 Under Review by "&AL59,IF(AN59="Escalated","⬆️ Escalated - Senior Management Review","")))))))
A60: =A59+1 -> 59 | B60: PM Vishwakarma | C60: 3757257 | D60: Day 6 | E60: gems and Jewellery | G60: Goldsmith (Sunar)( G&J/N0612 ) | H60: GOVT WITI SAHARSA | I60: SAHARSA | J60: BIHAR | K60: 46122 | L60: 46122 | M60: 19 | N60: 19 | O60: =IF(AND(M60<>"",N60<>""),M60-N60,"") -> 0 | P60: 9 | Q60: =IF(AND(N60<>"",P60<>""),N60-P60,"") -> 10 | R60: 19 | S60: =IF(AND(N60<>"",R60<>""),N60-R60,"") -> 0 | T60: 46122 | U60: Uploaded | V60: =IFERROR(R60/N60,"") -> 1 | W60: =IFERROR(S60/N60,"") -> 0 | X60: Swarnim Prabhat | Y60: AR161938 | Z60: Ashwinee Kumar | AA60: TR616427 | AB60: =IFERROR(VLOOKUP(B60,'Scheme Master'!$B$4:$C$79,2,FALSE),"") -> 360 | AC60: =IF(AND(AB60<>"",N60<>""),AB60*N60,"") -> 6840 | AF60: =IF(OR(AD60<>"",AE60<>""),AD60+AE60,"") | AG60: =IF(AND(AC60<>"",AF60<>""),AC60-AF60,"") | AH60: =IF(AND(AC60<>"",AC60>0,AF60<>""),AF60/AC60,"") | AI60: =IF(AH60="","",IF(AF60>AC60,"🔴 Critical - Over Budget",IF(AH60>0.4,"⚠️ Approval Required","✅ Auto-Approved"))) | AO60: =IF(AI60="","",IF(AI60="✅ Auto-Approved","✅ Approved (Auto - Within Budget)",IF(AN60="","⏳ Awaiting Approval",IF(AN60="Approved","✅ Approved by "&AL60&" on "&TEXT(AM60,"mm/dd/yyyy"),IF(AN60="Rejected","❌ Rejected by "&AL60&" - Review Expenses",IF(AN60="Pending Review","🔍 Under Review by "&AL60,IF(AN60="Escalated","⬆️ Escalated - Senior Management Review","")))))))
A61: =A60+1 -> 60 | B61: PM Vishwakarma | C61: 3757435 | D61: Day 6 | E61: gems and Jewellery | G61: Goldsmith (Sunar)( G&J/N0612 ) | H61: LEARNET SKILLS LIMITED | I61: JHUNJHUNU | J61: RAJASTHAN | K61: 46122 | L61: 46122 | M61: 35 | N61: 26 | O61: =IF(AND(M61<>"",N61<>""),M61-N61,"") -> 9 | P61: 25 | Q61: =IF(AND(N61<>"",P61<>""),N61-P61,"") -> 1 | R61: 26 | S61: =IF(AND(N61<>"",R61<>""),N61-R61,"") -> 0 | T61: 46122 | U61: Uploaded | V61: =IFERROR(R61/N61,"") -> 1 | W61: =IFERROR(S61/N61,"") -> 0 | X61: Yogesh Jangir | Y61: AR123754 | Z61: Aditya Ojha | AA61: TR533903 | AB61: =IFERROR(VLOOKUP(B61,'Scheme Master'!$B$4:$C$79,2,FALSE),"") -> 360 | AC61: =IF(AND(AB61<>"",N61<>""),AB61*N61,"") -> 9360 | AF61: =IF(OR(AD61<>"",AE61<>""),AD61+AE61,"") | AG61: =IF(AND(AC61<>"",AF61<>""),AC61-AF61,"") | AH61: =IF(AND(AC61<>"",AC61>0,AF61<>""),AF61/AC61,"") | AI61: =IF(AH61="","",IF(AF61>AC61,"🔴 Critical - Over Budget",IF(AH61>0.4,"⚠️ Approval Required","✅ Auto-Approved"))) | AO61: =IF(AI61="","",IF(AI61="✅ Auto-Approved","✅ Approved (Auto - Within Budget)",IF(AN61="","⏳ Awaiting Approval",IF(AN61="Approved","✅ Approved by "&AL61&" on "&TEXT(AM61,"mm/dd/yyyy"),IF(AN61="Rejected","❌ Rejected by "&AL61&" - Review Expenses",IF(AN61="Pending Review","🔍 Under Review by "&AL61,IF(AN61="Escalated","⬆️ Escalated - Senior Management Review","")))))))
A62: =A61+1 -> 61 | B62: PM Vishwakarma | C62: 3761243 | D62: Day 0 | E62: gems and Jewellery | G62: Goldsmith (Sunar)( G&J/N0612 ) | H62: NAJIBABAD GOVERNMENT ITI | I62: BIJNOR | J62: UTTAR PRADESH | K62: 46122 | L62: 46122 | M62: 7 | N62: 6 | O62: =IF(AND(M62<>"",N62<>""),M62-N62,"") -> 1 | P62: 4 | Q62: 2 | R62: 6 | S62: =IF(AND(N62<>"",R62<>""),N62-R62,"") -> 0 | T62: 46122 | U62: Uploaded | V62: =IFERROR(R62/N62,"") -> 1 | W62: =IFERROR(S62/N62,"") -> 0 | X62: shewtank mishra | Y62: AR100182 | AB62: =IFERROR(VLOOKUP(B62,'Scheme Master'!$B$4:$C$79,2,FALSE),"") -> 360 | AC62: =IF(AND(AB62<>"",N62<>""),AB62*N62,"") -> 2160 | AF62: =IF(OR(AD62<>"",AE62<>""),AD62+AE62,"") | AG62: =IF(AND(AC62<>"",AF62<>""),AC62-AF62,"") | AH62: =IF(AND(AC62<>"",AC62>0,AF62<>""),AF62/AC62,"") | AI62: =IF(AH62="","",IF(AF62>AC62,"🔴 Critical - Over Budget",IF(AH62>0.4,"⚠️ Approval Required","✅ Auto-Approved"))) | AO62: =IF(AI62="","",IF(AI62="✅ Auto-Approved","✅ Approved (Auto - Within Budget)",IF(AN62="","⏳ Awaiting Approval",IF(AN62="Approved","✅ Approved by "&AL62&" on "&TEXT(AM62,"mm/dd/yyyy"),IF(AN62="Rejected","❌ Rejected by "&AL62&" - Review Expenses",IF(AN62="Pending Review","🔍 Under Review by "&AL62,IF(AN62="Escalated","⬆️ Escalated - Senior Management Review","")))))))
A63: =A62+1 -> 62 | B63: SSC Affiliated: Skill Council for Green Jobs | C63: 3598633 | D63: Normal | E63: Green Jobs | G63: Solar PV Installer (Suryamitra) | H63: Idaksha Training Academy Private Limited | I63: Bhopal | J63: MADHYA PRADESH | K63: 46122 | L63: 46122 | M63: 29 | N63: 29 | O63: =IF(AND(M63<>"",N63<>""),M63-N63,"") -> 0 | P63: 25 | Q63: =IF(AND(N63<>"",P63<>""),N63-P63,"") -> 4 | R63: 28 | S63: =IF(AND(N63<>"",R63<>""),N63-R63,"") -> 1 | T63: 46124 | U63: Uploaded | V63: =IFERROR(R63/N63,"") -> 0.96551724 | W63: =IFERROR(S63/N63,"") -> 0.034482759 | X63: Mohd Navi | Y63: AR2351 | Z63: Neha sapkale | AA63: TR433972 | AB63: =IFERROR(VLOOKUP(B63,'Scheme Master'!$B$4:$C$79,2,FALSE),"") -> 400 | AC63: =IF(AND(AB63<>"",N63<>""),AB63*N63,"") -> 11600 | AF63: =IF(OR(AD63<>"",AE63<>""),AD63+AE63,"") | AG63: =IF(AND(AC63<>"",AF63<>""),AC63-AF63,"") | AH63: =IF(AND(AC63<>"",AC63>0,AF63<>""),AF63/AC63,"") | AI63: =IF(AH63="","",IF(AF63>AC63,"🔴 Critical - Over Budget",IF(AH63>0.4,"⚠️ Approval Required","✅ Auto-Approved"))) | AO63: =IF(AI63="","",IF(AI63="✅ Auto-Approved","✅ Approved (Auto - Within Budget)",IF(AN63="","⏳ Awaiting Approval",IF(AN63="Approved","✅ Approved by "&AL63&" on "&TEXT(AM63,"mm/dd/yyyy"),IF(AN63="Rejected","❌ Rejected by "&AL63&" - Review Expenses",IF(AN63="Pending Review","🔍 Under Review by "&AL63,IF(AN63="Escalated","⬆️ Escalated - Senior Management Review","")))))))
A64: =A63+1 -> 63 | B64: BSDMA-RPL | C64: 3733185 | D64: Normal | E64: Construction | G64: Masonry of Earthquake-Resistant Building | H64: Prabhodita Services India Private Limited | I64: Katihar | J64: Bihar | K64: 46123 | L64: 46124 | M64: 30 | N64: 28 | O64: =IF(AND(M64<>"",N64<>""),M64-N64,"") -> 2 | P64: 28 | Q64: =IF(AND(N64<>"",P64<>""),N64-P64,"") -> 0 | R64: 26 | S64: =IF(AND(N64<>"",R64<>""),N64-R64,"") -> 2 | T64: 46128 | U64: Uploaded | V64: =IFERROR(R64/N64,"") -> 0.92857143 | W64: =IFERROR(S64/N64,"") -> 0.071428571 | X64: Mohd Waseem | Y64: AR148405 | AB64: =IFERROR(VLOOKUP(B64,'Scheme Master'!$B$4:$C$79,2,FALSE),"") -> 540 | AC64: =IF(AND(AB64<>"",N64<>""),AB64*N64,"") -> 15120 | AF64: =IF(OR(AD64<>"",AE64<>""),AD64+AE64,"") | AG64: =IF(AND(AC64<>"",AF64<>""),AC64-AF64,"") | AH64: =IF(AND(AC64<>"",AC64>0,AF64<>""),AF64/AC64,"") | AI64: =IF(AH64="","",IF(AF64>AC64,"🔴 Critical - Over Budget",IF(AH64>0.4,"⚠️ Approval Required","✅ Auto-Approved"))) | AO64: =IF(AI64="","",IF(AI64="✅ Auto-Approved","✅ Approved (Auto - Within Budget)",IF(AN64="","⏳ Awaiting Approval",IF(AN64="Approved","✅ Approved by "&AL64&" on "&TEXT(AM64,"mm/dd/yyyy"),IF(AN64="Rejected","❌ Rejected by "&AL64&" - Review Expenses",IF(AN64="Pending Review","🔍 Under Review by "&AL64,IF(AN64="Escalated","⬆️ Escalated - Senior Management Review","")))))))
A65: =A64+1 -> 64 | B65: SSC Affiliated: Skill Council for Green Jobs | C65: 3730142 | D65: Re Assessment | E65: Green Jobs | G65: Solar PV Installer (Suryamitra) 4.0 | H65: Gaurav Singh | I65: KHAMMAM | J65: TELANGANA | K65: 46122 | L65: 46122 | M65: 2 | N65: 1 | O65: =IF(AND(M65<>"",N65<>""),M65-N65,"") -> 1 | P65: 1 | Q65: =IF(AND(N65<>"",P65<>""),N65-P65,"") -> 0 | R65: 1 | S65: =IF(AND(N65<>"",R65<>""),N65-R65,"") -> 0 | T65: 46122 | U65: Uploaded | V65: =IFERROR(R65/N65,"") -> 1 | W65: =IFERROR(S65/N65,"") -> 0 | X65: Vikash Kumar | Y65: AR116014 | Z65: Bathuru Praveenkumar | AA65: TR609878 | AB65: =IFERROR(VLOOKUP(B65,'Scheme Master'!$B$4:$C$79,2,FALSE),"") -> 400 | AC65: =IF(AND(AB65<>"",N65<>""),AB65*N65,"") -> 400 | AF65: =IF(OR(AD65<>"",AE65<>""),AD65+AE65,"") | AG65: =IF(AND(AC65<>"",AF65<>""),AC65-AF65,"") | AH65: =IF(AND(AC65<>"",AC65>0,AF65<>""),AF65/AC65,"") | AI65: =IF(AH65="","",IF(AF65>AC65,"🔴 Critical - Over Budget",IF(AH65>0.4,"⚠️ Approval Required","✅ Auto-Approved"))) | AO65: =IF(AI65="","",IF(AI65="✅ Auto-Approved","✅ Approved (Auto - Within Budget)",IF(AN65="","⏳ Awaiting Approval",IF(AN65="Approved","✅ Approved by "&AL65&" on "&TEXT(AM65,"mm/dd/yyyy"),IF(AN65="Rejected","❌ Rejected by "&AL65&" - Review Expenses",IF(AN65="Pending Review","🔍 Under Review by "&AL65,IF(AN65="Escalated","⬆️ Escalated - Senior Management Review","")))))))
A66: =A65+1 -> 65 | B66: SSC Affiliated: Skill Council for Green Jobs | C66: 3730139 | D66: Re Assessment | E66: Green Jobs | G66: Solar PV Installer (Suryamitra) 4.0 | H66: Gaurav Singh | I66: KHAMMAM | J66: TELANGANA | K66: 46122 | L66: 46122 | M66: 8 | N66: 4 | O66: =IF(AND(M66<>"",N66<>""),M66-N66,"") -> 4 | P66: 4 | Q66: =IF(AND(N66<>"",P66<>""),N66-P66,"") -> 0 | R66: 4 | S66: =IF(AND(N66<>"",R66<>""),N66-R66,"") -> 0 | T66: 46122 | U66: Uploaded | V66: =IFERROR(R66/N66,"") -> 1 | W66: =IFERROR(S66/N66,"") -> 0 | X66: Wajid Bashir | Y66: AR84804 | Z66: Bathuru Praveenkumar | AA66: TR609878 | AB66: =IFERROR(VLOOKUP(B66,'Scheme Master'!$B$4:$C$79,2,FALSE),"") -> 400 | AC66: =IF(AND(AB66<>"",N66<>""),AB66*N66,"") -> 1600 | AF66: =IF(OR(AD66<>"",AE66<>""),AD66+AE66,"") | AG66: =IF(AND(AC66<>"",AF66<>""),AC66-AF66,"") | AH66: =IF(AND(AC66<>"",AC66>0,AF66<>""),AF66/AC66,"") | AI66: =IF(AH66="","",IF(AF66>AC66,"🔴 Critical - Over Budget",IF(AH66>0.4,"⚠️ Approval Required","✅ Auto-Approved")))
A67: =A66+1 -> 66 | B67: SSC Affiliated: Skill Council for Green Jobs | C67: 3736098 | D67: Re Assessment | E67: Green Jobs | G67: Solar PV Installer (Suryamitra) 4.0 | H67: Gaurav Singh | I67: KHAMMAM | J67: TELANGANA | K67: 46122 | L67: 46122 | M67: 12 | N67: 10 | O67: =IF(AND(M67<>"",N67<>""),M67-N67,"") -> 2 | P67: 10 | Q67: =IF(AND(N67<>"",P67<>""),N67-P67,"") -> 0 | R67: 10 | S67: =IF(AND(N67<>"",R67<>""),N67-R67,"") -> 0 | T67: 46122 | U67: Uploaded | V67: =IFERROR(R67/N67,"") -> 1 | W67: =IFERROR(S67/N67,"") -> 0 | X67: Kanagala Ramasurekanand | Y67: AR102979 | Z67: Bathuru Praveenkumar | AA67: TR609878 | AB67: =IFERROR(VLOOKUP(B67,'Scheme Master'!$B$4:$C$79,2,FALSE),"") -> 400 | AC67: =IF(AND(AB67<>"",N67<>""),AB67*N67,"") -> 4000 | AD67: 2000 | AE67: 1000 | AF67: =IF(OR(AD67<>"",AE67<>""),AD67+AE67,"") -> 3000 | AG67: =IF(AND(AC67<>"",AF67<>""),AC67-AF67,"") -> 1000 | AH67: =IF(AND(AC67<>"",AC67>0,AF67<>""),AF67/AC67,"") -> 0.75 | AI67: =IF(AH67="","",IF(AF67>AC67,"🔴 Critical - Over Budget",IF(AH67>0.4,"⚠️ Approval Required","✅ Auto-Approved"))) -> ⚠️ Approval Required | AJ67: Mail Sent | AK67: Nisha Saifi
A68: =A67+1 -> 67 | B68: PM Vishwakarma | C68: 3759939 | D68: Day 0 | E68: Handicraft | G68: Traditional Soft Toy Maker( HCS/N7355 ) | H68: ORION EDUTECH PRIVATE LIMITED | I68: WARDHA | J68: MAHARASHTRA | K68: 46122 | L68: 46122 | M68: 15 | N68: 14 | O68: =IF(AND(M68<>"",N68<>""),M68-N68,"") -> 1 | P68: 1 | Q68: =IF(AND(N68<>"",P68<>""),N68-P68,"") -> 13 | R68: 14 | S68: =IF(AND(N68<>"",R68<>""),N68-R68,"") -> 0 | T68: 46122 | U68: Uploaded | V68: =IFERROR(R68/N68,"") -> 1 | W68: =IFERROR(S68/N68,"") -> 0 | X68: Neha Dineshrao Bangare | Y68: AR134445 | Z68: Neha Dineshrao Bangare | AA68: TR555172 | AB68: =IFERROR(VLOOKUP(B68,'Scheme Master'!$B$4:$C$79,2,FALSE),"") -> 360 | AC68: =IF(AND(AB68<>"",N68<>""),AB68*N68,"") -> 5040 | AF68: =IF(OR(AD68<>"",AE68<>""),AD68+AE68,"") | AG68: =IF(AND(AC68<>"",AF68<>""),AC68-AF68,"") | AH68: =IF(AND(AC68<>"",AC68>0,AF68<>""),AF68/AC68,"") | AI68: =IF(AH68="","",IF(AF68>AC68,"🔴 Critical - Over Budget",IF(AH68>0.4,"⚠️ Approval Required","✅ Auto-Approved"))) | AO68: =IF(AI68="","",IF(AI68="✅ Auto-Approved","✅ Approved (Auto - Within Budget)",IF(AN68="","⏳ Awaiting Approval",IF(AN68="Approved","✅ Approved by "&AL68&" on "&TEXT(AM68,"mm/dd/yyyy"),IF(AN68="Rejected","❌ Rejected by "&AL68&" - Review Expenses",IF(AN68="Pending Review","🔍 Under Review by "&AL68,IF(AN68="Escalated","⬆️ Escalated - Senior Management Review","")))))))
A69: =A68+1 -> 68 | B69: TOT | C69: TOT_MESC_10-04-2026 | D69: Normal | E69: Media & Entertainment | G69: 3D Printing Operator | K69: 46122 | L69: 46122 | M69: 2 | N69: 2 | O69: =IF(AND(M69<>"",N69<>""),M69-N69,"") -> 0 | P69: 0 | Q69: =IF(AND(N69<>"",P69<>""),N69-P69,"") -> 2 | R69: 0 | S69: =IF(AND(N69<>"",R69<>""),N69-R69,"") -> 2 | T69: 46122 | U69: Uploaded | V69: =IFERROR(R69/N69,"") -> 0 | W69: =IFERROR(S69/N69,"") -> 1 | AB69: =IFERROR(VLOOKUP(B69,'Scheme Master'!$B$4:$C$79,2,FALSE),"") -> 400 | AC69: =IF(AND(AB69<>"",N69<>""),AB69*N69,"") -> 800 | AF69: =IF(OR(AD69<>"",AE69<>""),AD69+AE69,"") | AG69: =IF(AND(AC69<>"",AF69<>""),AC69-AF69,"") | AH69: =IF(AND(AC69<>"",AC69>0,AF69<>""),AF69/AC69,"") | AI69: =IF(AH69="","",IF(AF69>AC69,"🔴 Critical - Over Budget",IF(AH69>0.4,"⚠️ Approval Required","✅ Auto-Approved"))) | AO69: =IF(AI69="","",IF(AI69="✅ Auto-Approved","✅ Approved (Auto - Within Budget)",IF(AN69="","⏳ Awaiting Approval",IF(AN69="Approved","✅ Approved by "&AL69&" on "&TEXT(AM69,"mm/dd/yyyy"),IF(AN69="Rejected","❌ Rejected by "&AL69&" - Review Expenses",IF(AN69="Pending Review","🔍 Under Review by "&AL69,IF(AN69="Escalated","⬆️ Escalated - Senior Management Review","")))))))
A70: =A69+1 -> 69 | B70: PM Vishwakarma | C70: 3760292 | D70: Day 6 | E70: gems and Jewellery | G70: Goldsmith (Sunar)( G&J/N0612 ) | H70: Govt ITI Kahalgaon (Bhagalpur) | I70: BHAGALPUR | J70: BIHAR | K70: 46126 | L70: 46126 | M70: 25 | N70: 24 | O70: =IF(AND(M70<>"",N70<>""),M70-N70,"") -> 1 | P70: 24 | Q70: =IF(AND(N70<>"",P70<>""),N70-P70,"") -> 0 | R70: 24 | S70: =IF(AND(N70<>"",R70<>""),N70-R70,"") -> 0 | T70: 46126 | U70: Uploaded | V70: =IFERROR(R70/N70,"") -> 1 | W70: =IFERROR(S70/N70,"") -> 0 | X70: Priyanshu Kumar Tiwari | Y70: AR164546 | Z70: Raushan Kumar | AA70: TR627945 | AB70: =IFERROR(VLOOKUP(B70,'Scheme Master'!$B$4:$C$79,2,FALSE),"") -> 360 | AC70: =IF(AND(AB70<>"",N70<>""),AB70*N70,"") -> 8640 | AD70: 2000 | AE70: 1000 | AF70: =IF(OR(AD70<>"",AE70<>""),AD70+AE70,"") -> 3000 | AG70: =IF(AND(AC70<>"",AF70<>""),AC70-AF70,"") -> 5640 | AH70: =IF(AND(AC70<>"",AC70>0,AF70<>""),AF70/AC70,"") -> 0.34722222 | AI70: =IF(AH70="","",IF(AF70>AC70,"🔴 Critical - Over Budget",IF(AH70>0.4,"⚠️ Approval Required","✅ Auto-Approved"))) -> ✅ Auto-Approved | AK70: Nisha Saifi | AN70: Approved | AO70: =IF(AI70="","",IF(AI70="✅ Auto-Approved","✅ Approved (Auto - Within Budget)",IF(AN70="","⏳ Awaiting Approval",IF(AN70="Approved","✅ Approved by "&AL70&" on "&TEXT(AM70,"mm/dd/yyyy"),IF(AN70="Rejected","❌ Rejected by "&AL70&" - Review Expenses",IF(AN70="Pending Review","🔍 Under Review by "&AL70,IF(AN70="Escalated","⬆️ Escalated - Senior Management Review",""))))))) -> ✅ Approved (Auto - Within Budget)
A71: =A70+1 -> 70 | B71: PMAY-G-STT | C71: 3662886 | D71: Day 1 | E71: Construction | G71: Rural Mason V4.0 | H71: SHIVA SHAKTHI MAHILA RURAL AND URBAN DEVELOPMENT ASSOCIATION | I71: Hassan | J71: Karnataka | K71: 46123 | L71: Batch not Confirm | M71: 30 | O71: =IF(AND(M71<>"",N71<>""),M71-N71,"") | Q71: =IF(AND(N71<>"",P71<>""),N71-P71,"") | S71: =IF(AND(N71<>"",R71<>""),N71-R71,"") | V71: =IFERROR(R71/N71,"") | W71: =IFERROR(S71/N71,"") | X71: Deepu Raj | Y71: AR177654 | AB71: =IFERROR(VLOOKUP(B71,'Scheme Master'!$B$4:$C$79,2,FALSE),"") -> 720 | AC71: =IF(AND(AB71<>"",N71<>""),AB71*N71,"") | AF71: =IF(OR(AD71<>"",AE71<>""),AD71+AE71,"") | AG71: =IF(AND(AC71<>"",AF71<>""),AC71-AF71,"") | AH71: =IF(AND(AC71<>"",AC71>0,AF71<>""),AF71/AC71,"") | AI71: =IF(AH71="","",IF(AF71>AC71,"🔴 Critical - Over Budget",IF(AH71>0.4,"⚠️ Approval Required","✅ Auto-Approved"))) | AO71: =IF(AI71="","",IF(AI71="✅ Auto-Approved","✅ Approved (Auto - Within Budget)",IF(AN71="","⏳ Awaiting Approval",IF(AN71="Approved","✅ Approved by "&AL71&" on "&TEXT(AM71,"mm/dd/yyyy"),IF(AN71="Rejected","❌ Rejected by "&AL71&" - Review Expenses",IF(AN71="Pending Review","🔍 Under Review by "&AL71,IF(AN71="Escalated","⬆️ Escalated - Senior Management Review","")))))))
A72: =A71+1 -> 71 | B72: PMAY-G-STT | C72: 3652313 | D72: Day 1 | E72: Construction | G72: Rural Mason V4.0 | H72: SHIVA SHAKTHI MAHILA RURAL AND URBAN DEVELOPMENT ASSOCIATION | I72: Belagavi | J72: Karnataka | K72: 46123 | L72: 46124 | M72: 30 | N72: 20 | O72: =IF(AND(M72<>"",N72<>""),M72-N72,"") -> 10 | P72: 20 | Q72: =IF(AND(N72<>"",P72<>""),N72-P72,"") -> 0 | R72: 20 | S72: =IF(AND(N72<>"",R72<>""),N72-R72,"") -> 0 | T72: 46128 | U72: Uploaded | V72: =IFERROR(R72/N72,"") -> 1 | W72: =IFERROR(S72/N72,"") -> 0 | X72: Deepu Raj | Y72: AR177654 | AB72: =IFERROR(VLOOKUP(B72,'Scheme Master'!$B$4:$C$79,2,FALSE),"") -> 720 | AC72: =IF(AND(AB72<>"",N72<>""),AB72*N72,"") -> 14400 | AF72: =IF(OR(AD72<>"",AE72<>""),AD72+AE72,"") | AG72: =IF(AND(AC72<>"",AF72<>""),AC72-AF72,"") | AH72: =IF(AND(AC72<>"",AC72>0,AF72<>""),AF72/AC72,"") | AI72: =IF(AH72="","",IF(AF72>AC72,"🔴 Critical - Over Budget",IF(AH72>0.4,"⚠️ Approval Required","✅ Auto-Approved"))) | AO72: =IF(AI72="","",IF(AI72="✅ Auto-Approved","✅ Approved (Auto - Within Budget)",IF(AN72="","⏳ Awaiting Approval",IF(AN72="Approved","✅ Approved by "&AL72&" on "&TEXT(AM72,"mm/dd/yyyy"),IF(AN72="Rejected","❌ Rejected by "&AL72&" - Review Expenses",IF(AN72="Pending Review","🔍 Under Review by "&AL72,IF(AN72="Escalated","⬆️ Escalated - Senior Management Review","")))))))
A73: =A72+1 -> 72 | B73: PMAY-G-STT | C73: 3713839 | D73: Day 1 | E73: Construction | G73: Rural Mason V4.0 | H73: Maya Jan Vikas Seva Sansthan | I73: BHANDARA | J73: Maharashtra | K73: 46123 | L73: 46124 | M73: 33 | N73: 29 | O73: =IF(AND(M73<>"",N73<>""),M73-N73,"") -> 4 | P73: 29 | Q73: =IF(AND(N73<>"",P73<>""),N73-P73,"") -> 0 | R73: 29 | S73: =IF(AND(N73<>"",R73<>""),N73-R73,"") -> 0 | T73: 46126 | U73: Uploaded | V73: =IFERROR(R73/N73,"") -> 1 | W73: =IFERROR(S73/N73,"") -> 0 | X73: Deepsingh Tanwar | Y73: AR16827 | AB73: =IFERROR(VLOOKUP(B73,'Scheme Master'!$B$4:$C$79,2,FALSE),"") -> 720 | AC73: =IF(AND(AB73<>"",N73<>""),AB73*N73,"") -> 20880 | AF73: =IF(OR(AD73<>"",AE73<>""),AD73+AE73,"") | AG73: =IF(AND(AC73<>"",AF73<>""),AC73-AF73,"") | AH73: =IF(AND(AC73<>"",AC73>0,AF73<>""),AF73/AC73,"") | AI73: =IF(AH73="","",IF(AF73>AC73,"🔴 Critical - Over Budget",IF(AH73>0.4,"⚠️ Approval Required","✅ Auto-Approved"))) | AO73: =IF(AI73="","",IF(AI73="✅ Auto-Approved","✅ Approved (Auto - Within Budget)",IF(AN73="","⏳ Awaiting Approval",IF(AN73="Approved","✅ Approved by "&AL73&" on "&TEXT(AM73,"mm/dd/yyyy"),IF(AN73="Rejected","❌ Rejected by "&AL73&" - Review Expenses",IF(AN73="Pending Review","🔍 Under Review by "&AL73,IF(AN73="Escalated","⬆️ Escalated - Senior Management Review","")))))))
A74: =A73+1 -> 73 | B74: PM Vishwakarma | C74: 3759841 | D74: Day 0 | E74: Handicraft | G74: Traditional Malakar( HCS/N9210 ) | H74: ALL INDIA SOCIETY FOR ELECTRONICS AND COMPUTER TECHNOLOGY | I74: MORENA | J74: MADHYA PRADESH | K74: 46123 | L74: 46123 | M74: 12 | N74: 6 | O74: =IF(AND(M74<>"",N74<>""),M74-N74,"") -> 6 | P74: 5 | Q74: =IF(AND(N74<>"",P74<>""),N74-P74,"") -> 1 | R74: 6 | S74: =IF(AND(N74<>"",R74<>""),N74-R74,"") -> 0 | T74: 46123 | U74: Uploaded | V74: =IFERROR(R74/N74,"") -> 1 | W74: =IFERROR(S74/N74,"") -> 0 | X74: Saurabh Mishra | Y74: AR158975 | Z74: Saurabh Mishra | AA74: TR481327 | AB74: =IFERROR(VLOOKUP(B74,'Scheme Master'!$B$4:$C$79,2,FALSE),"") -> 360 | AC74: =IF(AND(AB74<>"",N74<>""),AB74*N74,"") -> 2160 | AF74: =IF(OR(AD74<>"",AE74<>""),AD74+AE74,"") | AG74: =IF(AND(AC74<>"",AF74<>""),AC74-AF74,"") | AH74: =IF(AND(AC74<>"",AC74>0,AF74<>""),AF74/AC74,"") | AI74: =IF(AH74="","",IF(AF74>AC74,"🔴 Critical - Over Budget",IF(AH74>0.4,"⚠️ Approval Required","✅ Auto-Approved"))) | AO74: =IF(AI74="","",IF(AI74="✅ Auto-Approved","✅ Approved (Auto - Within Budget)",IF(AN74="","⏳ Awaiting Approval",IF(AN74="Approved","✅ Approved by "&AL74&" on "&TEXT(AM74,"mm/dd/yyyy"),IF(AN74="Rejected","❌ Rejected by "&AL74&" - Review Expenses",IF(AN74="Pending Review","🔍 Under Review by "&AL74,IF(AN74="Escalated","⬆️ Escalated - Senior Management Review","")))))))
A75: =A74+1 -> 74 | B75: PM Vishwakarma | C75: 3758535 | D75: Day 6 | E75: handicraft | G75: Traditional Soft Toy Maker( HCS/N7355 ) | H75: ORION EDUTECH PRIVATE LIMITED | I75: BULDHANA | J75: MAHARASHTRA | K75: 46125 | L75: 46125 | M75: 30 | N75: 17 | O75: =IF(AND(M75<>"",N75<>""),M75-N75,"") -> 13 | Q75: =IF(AND(N75<>"",P75<>""),N75-P75,"") | R75: 17 | S75: =IF(AND(N75<>"",R75<>""),N75-R75,"") -> 0 | T75: 46125 | U75: Uploaded | V75: =IFERROR(R75/N75,"") -> 1 | W75: =IFERROR(S75/N75,"") -> 0 | X75: Gaytri Ramesh Tadas | Y75: AR161115 | Z75: Kashmira Devi | AA75: TR669634 | AB75: =IFERROR(VLOOKUP(B75,'Scheme Master'!$B$4:$C$79,2,FALSE),"") -> 360 | AC75: =IF(AND(AB75<>"",N75<>""),AB75*N75,"") -> 6120 | AD75: 2000 | AE75: 300 | AF75: =IF(OR(AD75<>"",AE75<>""),AD75+AE75,"") -> 2300 | AG75: =IF(AND(AC75<>"",AF75<>""),AC75-AF75,"") -> 3820 | AH75: =IF(AND(AC75<>"",AC75>0,AF75<>""),AF75/AC75,"") -> 0.37581699 | AI75: =IF(AH75="","",IF(AF75>AC75,"🔴 Critical - Over Budget",IF(AH75>0.4,"⚠️ Approval Required","✅ Auto-Approved"))) -> ✅ Auto-Approved | AK75: Nisha Saifi | AO75: =IF(AI75="","",IF(AI75="✅ Auto-Approved","✅ Approved (Auto - Within Budget)",IF(AN75="","⏳ Awaiting Approval",IF(AN75="Approved","✅ Approved by "&AL75&" on "&TEXT(AM75,"mm/dd/yyyy"),IF(AN75="Rejected","❌ Rejected by "&AL75&" - Review Expenses",IF(AN75="Pending Review","🔍 Under Review by "&AL75,IF(AN75="Escalated","⬆️ Escalated - Senior Management Review",""))))))) -> ✅ Approved (Auto - Within Budget)
A76: =A75+1 -> 75 | B76: PM Vishwakarma | C76: 3759814 | D76: Day 6 | E76: handicraft | G76: Traditional Soft Toy Maker( HCS/N7355 ) | H76: LEARNET SKILLS LIMITED | I76: MUZAFFARPUR | J76: BIHAR | K76: 46125 | L76: 46125 | M76: 30 | N76: 0 | O76: =IF(AND(M76<>"",N76<>""),M76-N76,"") -> 30 | P76: 0 | Q76: =IF(AND(N76<>"",P76<>""),N76-P76,"") -> 0 | R76: 0 | S76: =IF(AND(N76<>"",R76<>""),N76-R76,"") -> 0 | T76: 46125 | U76: Uploaded | V76: =IFERROR(R76/N76,"") | W76: =IFERROR(S76/N76,"") | X76: Deepmala Kumari | Y76: AR113805 | Z76: Shiwani Kumari | AA76: TR583330 | AB76: =IFERROR(VLOOKUP(B76,'Scheme Master'!$B$4:$C$79,2,FALSE),"") -> 360 | AC76: =IF(AND(AB76<>"",N76<>""),AB76*N76,"") -> 0 | AD76: 2000 | AE76: 700 | AF76: =IF(OR(AD76<>"",AE76<>""),AD76+AE76,"") -> 2700 | AG76: =IF(AND(AC76<>"",AF76<>""),AC76-AF76,"") -> -2700 | AH76: =IF(AND(AC76<>"",AC76>0,AF76<>""),AF76/AC76,"") | AI76: =IF(AH76="","",IF(AF76>AC76,"🔴 Critical - Over Budget",IF(AH76>0.4,"⚠️ Approval Required","✅ Auto-Approved"))) | AK76: Naeem | AO76: =IF(AI76="","",IF(AI76="✅ Auto-Approved","✅ Approved (Auto - Within Budget)",IF(AN76="","⏳ Awaiting Approval",IF(AN76="Approved","✅ Approved by "&AL76&" on "&TEXT(AM76,"mm/dd/yyyy"),IF(AN76="Rejected","❌ Rejected by "&AL76&" - Review Expenses",IF(AN76="Pending Review","🔍 Under Review by "&AL76,IF(AN76="Escalated","⬆️ Escalated - Senior Management Review","")))))))
A77: =A76+1 -> 76 | B77: PM Vishwakarma | C77: 3761365 | D77: Day 0 | E77: gems and Jewellery | G77: Goldsmith (Sunar)( G&J/N0612 ) | H77: LEARNET SKILLS LIMITED | I77: JHUNJHUNU | J77: RAJASTHAN | K77: 46123 | L77: 46123 | M77: 45 | N77: 28 | O77: =IF(AND(M77<>"",N77<>""),M77-N77,"") -> 17 | P77: 25 | Q77: =IF(AND(N77<>"",P77<>""),N77-P77,"") -> 3 | R77: 28 | S77: =IF(AND(N77<>"",R77<>""),N77-R77,"") -> 0 | T77: 46123 | U77: Uploaded | V77: =IFERROR(R77/N77,"") -> 1 | W77: =IFERROR(S77/N77,"") -> 0 | X77: Sukhveer Singh Maan | Y77: AR163611 | Z77: Sukhveer Singh Maan | AA77: TR620280 | AB77: =IFERROR(VLOOKUP(B77,'Scheme Master'!$B$4:$C$79,2,FALSE),"") -> 360 | AC77: =IF(AND(AB77<>"",N77<>""),AB77*N77,"") -> 10080 | AF77: =IF(OR(AD77<>"",AE77<>""),AD77+AE77,"") | AG77: =IF(AND(AC77<>"",AF77<>""),AC77-AF77,"") | AH77: =IF(AND(AC77<>"",AC77>0,AF77<>""),AF77/AC77,"") | AI77: =IF(AH77="","",IF(AF77>AC77,"🔴 Critical - Over Budget",IF(AH77>0.4,"⚠️ Approval Required","✅ Auto-Approved"))) | AO77: =IF(AI77="","",IF(AI77="✅ Auto-Approved","✅ Approved (Auto - Within Budget)",IF(AN77="","⏳ Awaiting Approval",IF(AN77="Approved","✅ Approved by "&AL77&" on "&TEXT(AM77,"mm/dd/yyyy"),IF(AN77="Rejected","❌ Rejected by "&AL77&" - Review Expenses",IF(AN77="Pending Review","🔍 Under Review by "&AL77,IF(AN77="Escalated","⬆️ Escalated - Senior Management Review","")))))))
A78: =A77+1 -> 77 | B78: PM Vishwakarma | C78: 3744204 | D78: Day 6 | E78: Construction | G78: Brick Mason -Basic( CON/N0160 ) | H78: National Federation of Farmers' Procurement, Processing & Retailing Cooperatives of India Ltd., (NACOF) | I78: SRI POTTI SRIRAMULU NELLORE | J78: ANDHRA PRADESH | K78: 46123 | L78: 46123 | M78: 37 | N78: 12 | O78: =IF(AND(M78<>"",N78<>""),M78-N78,"") -> 25 | P78: 11 | Q78: =IF(AND(N78<>"",P78<>""),N78-P78,"") -> 1 | R78: 12 | S78: =IF(AND(N78<>"",R78<>""),N78-R78,"") -> 0 | T78: 46123 | U78: Uploaded | V78: =IFERROR(R78/N78,"") -> 1 | W78: =IFERROR(S78/N78,"") -> 0 | X78: Cherukuru Tirupalu | Y78: AR95412 / Pmvk@2024 | Z78: Rondla Akhil | AA78: TR438024 | AB78: =IFERROR(VLOOKUP(B78,'Scheme Master'!$B$4:$C$79,2,FALSE),"") -> 360 | AC78: =IF(AND(AB78<>"",N78<>""),AB78*N78,"") -> 4320 | AF78: =IF(OR(AD78<>"",AE78<>""),AD78+AE78,"") | AG78: =IF(AND(AC78<>"",AF78<>""),AC78-AF78,"") | AH78: =IF(AND(AC78<>"",AC78>0,AF78<>""),AF78/AC78,"") | AI78: =IF(AH78="","",IF(AF78>AC78,"🔴 Critical - Over Budget",IF(AH78>0.4,"⚠️ Approval Required","✅ Auto-Approved"))) | AO78: =IF(AI78="","",IF(AI78="✅ Auto-Approved","✅ Approved (Auto - Within Budget)",IF(AN78="","⏳ Awaiting Approval",IF(AN78="Approved","✅ Approved by "&AL78&" on "&TEXT(AM78,"mm/dd/yyyy"),IF(AN78="Rejected","❌ Rejected by "&AL78&" - Review Expenses",IF(AN78="Pending Review","🔍 Under Review by "&AL78,IF(AN78="Escalated","⬆️ Escalated - Senior Management Review","")))))))
A79: =A78+1 -> 78 | B79: Suryamitra Skill Development Programme | C79: 3636818 | D79: Normal | E79: Green Jobs | G79: Solar PV Installer (Suryamitra) 4.0 | H79: iDaksha Training Academy Pvt. Ltd | I79: Jabalpur | J79: MADHYA PRADESH | K79: 46126 | L79: 46126 | M79: 30 | N79: 28 | O79: =IF(AND(M79<>"",N79<>""),M79-N79,"") -> 2 | P79: 28 | Q79: =IF(AND(N79<>"",P79<>""),N79-P79,"") -> 0 | R79: 28 | S79: =IF(AND(N79<>"",R79<>""),N79-R79,"") -> 0 | T79: 46128 | U79: Uploaded | V79: =IFERROR(R79/N79,"") -> 1 | W79: =IFERROR(S79/N79,"") -> 0 | X79: Mohd Nadeem | Y79: AR29759 | Z79: Satyam Mishra | AA79: TR590110 | AB79: =IFERROR(VLOOKUP(B79,'Scheme Master'!$B$4:$C$79,2,FALSE),"") -> 400 | AC79: =IF(AND(AB79<>"",N79<>""),AB79*N79,"") -> 11200 | AF79: =IF(OR(AD79<>"",AE79<>""),AD79+AE79,"") | AG79: =IF(AND(AC79<>"",AF79<>""),AC79-AF79,"") | AH79: =IF(AND(AC79<>"",AC79>0,AF79<>""),AF79/AC79,"") | AI79: =IF(AH79="","",IF(AF79>AC79,"🔴 Critical - Over Budget",IF(AH79>0.4,"⚠️ Approval Required","✅ Auto-Approved"))) | AO79: =IF(AI79="","",IF(AI79="✅ Auto-Approved","✅ Approved (Auto - Within Budget)",IF(AN79="","⏳ Awaiting Approval",IF(AN79="Approved","✅ Approved by "&AL79&" on "&TEXT(AM79,"mm/dd/yyyy"),IF(AN79="Rejected","❌ Rejected by "&AL79&" - Review Expenses",IF(AN79="Pending Review","🔍 Under Review by "&AL79,IF(AN79="Escalated","⬆️ Escalated - Senior Management Review","")))))))
A80: =A79+1 -> 79 | B80: MinistryRPL | C80: 3734745 | D80: Normal | E80: Green Jobs | G80: Swacchta Saarthi( SGJ/MCr-0015 ) | H80: ankur garg | I80: SONITPUR | J80: ASSAM | K80: 46124 | L80: 46124 | M80: 47 | N80: 31 | O80: =IF(AND(M80<>"",N80<>""),M80-N80,"") -> 16 | P80: 15 | Q80: =IF(AND(N80<>"",P80<>""),N80-P80,"") -> 16 | R80: 31 | S80: =IF(AND(N80<>"",R80<>""),N80-R80,"") -> 0 | T80: 46125 | U80: Uploaded | V80: =IFERROR(R80/N80,"") -> 1 | W80: =IFERROR(S80/N80,"") -> 0 | X80: Mossarraf Hussain | Y80: AR80057 | Z80: Aditya Das | AA80: TR640230 | AB80: =IFERROR(VLOOKUP(B80,'Scheme Master'!$B$4:$C$79,2,FALSE),"") -> 200 | AC80: =IF(AND(AB80<>"",N80<>""),AB80*N80,"") -> 6200 | AF80: =IF(OR(AD80<>"",AE80<>""),AD80+AE80,"") | AG80: =IF(AND(AC80<>"",AF80<>""),AC80-AF80,"") | AH80: =IF(AND(AC80<>"",AC80>0,AF80<>""),AF80/AC80,"") | AI80: =IF(AH80="","",IF(AF80>AC80,"🔴 Critical - Over Budget",IF(AH80>0.4,"⚠️ Approval Required","✅ Auto-Approved"))) | AO80: =IF(AI80="","",IF(AI80="✅ Auto-Approved","✅ Approved (Auto - Within Budget)",IF(AN80="","⏳ Awaiting Approval",IF(AN80="Approved","✅ Approved by "&AL80&" on "&TEXT(AM80,"mm/dd/yyyy"),IF(AN80="Rejected","❌ Rejected by "&AL80&" - Review Expenses",IF(AN80="Pending Review","🔍 Under Review by "&AL80,IF(AN80="Escalated","⬆️ Escalated - Senior Management Review","")))))))
A81: =A80+1 -> 80 | B81: PM Vishwakarma | C81: 3759186 | D81: Day 6 | E81: handicraft | G81: Potter (Kumhar) including traditional ceramics and terracotta product maker( HCS/N9213 ) | H81: National Federation of Farmers' Procurement, Processing & Retailing Cooperatives of India Ltd., (NACOF) | I81: KURNOOL | J81: ANDHRA PRADESH | K81: 46125 | L81: 46125 | M81: 15 | N81: 7 | O81: =IF(AND(M81<>"",N81<>""),M81-N81,"") -> 8 | Q81: =IF(AND(N81<>"",P81<>""),N81-P81,"") | R81: 7 | S81: =IF(AND(N81<>"",R81<>""),N81-R81,"") -> 0 | T81: 46125 | U81: Uploaded | V81: =IFERROR(R81/N81,"") -> 1 | W81: =IFERROR(S81/N81,"") -> 0 | X81: Nagaveni C | Y81: AR145809 | Z81: Dasari venkata Kalyan Bharadwaj | AA81: TR561972 | AB81: =IFERROR(VLOOKUP(B81,'Scheme Master'!$B$4:$C$79,2,FALSE),"") -> 360 | AC81: =IF(AND(AB81<>"",N81<>""),AB81*N81,"") -> 2520 | AF81: =IF(OR(AD81<>"",AE81<>""),AD81+AE81,"") | AG81: =IF(AND(AC81<>"",AF81<>""),AC81-AF81,"") | AH81: =IF(AND(AC81<>"",AC81>0,AF81<>""),AF81/AC81,"") | AI81: =IF(AH81="","",IF(AF81>AC81,"🔴 Critical - Over Budget",IF(AH81>0.4,"⚠️ Approval Required","✅ Auto-Approved"))) | AO81: =IF(AI81="","",IF(AI81="✅ Auto-Approved","✅ Approved (Auto - Within Budget)",IF(AN81="","⏳ Awaiting Approval",IF(AN81="Approved","✅ Approved by "&AL81&" on "&TEXT(AM81,"mm/dd/yyyy"),IF(AN81="Rejected","❌ Rejected by "&AL81&" - Review Expenses",IF(AN81="Pending Review","🔍 Under Review by "&AL81,IF(AN81="Escalated","⬆️ Escalated - Senior Management Review","")))))))
A82: =A81+1 -> 81 | B82: PM Vishwakarma | C82: 3761739 | D82: Day 0 | E82: gems and Jewellery | G82: Goldsmith (Sunar)( G&J/N0612 ) | H82: LEARNET SKILLS LIMITED | I82: JHUNJHUNU | J82: RAJASTHAN | K82: 46125 | L82: 46125 | M82: 39 | N82: 20 | O82: =IF(AND(M82<>"",N82<>""),M82-N82,"") -> 19 | P82: 16 | Q82: =IF(AND(N82<>"",P82<>""),N82-P82,"") -> 4 | R82: 20 | S82: =IF(AND(N82<>"",R82<>""),N82-R82,"") -> 0 | T82: 46125 | U82: Uploaded | V82: =IFERROR(R82/N82,"") -> 1 | W82: =IFERROR(S82/N82,"") -> 0 | X82: Sukhveer Singh Maan | Y82: AR163611 | AB82: =IFERROR(VLOOKUP(B82,'Scheme Master'!$B$4:$C$79,2,FALSE),"") -> 360 | AC82: =IF(AND(AB82<>"",N82<>""),AB82*N82,"") -> 7200 | AF82: =IF(OR(AD82<>"",AE82<>""),AD82+AE82,"") | AG82: =IF(AND(AC82<>"",AF82<>""),AC82-AF82,"") | AH82: =IF(AND(AC82<>"",AC82>0,AF82<>""),AF82/AC82,"") | AI82: =IF(AH82="","",IF(AF82>AC82,"🔴 Critical - Over Budget",IF(AH82>0.4,"⚠️ Approval Required","✅ Auto-Approved"))) | AO82: =IF(AI82="","",IF(AI82="✅ Auto-Approved","✅ Approved (Auto - Within Budget)",IF(AN82="","⏳ Awaiting Approval",IF(AN82="Approved","✅ Approved by "&AL82&" on "&TEXT(AM82,"mm/dd/yyyy"),IF(AN82="Rejected","❌ Rejected by "&AL82&" - Review Expenses",IF(AN82="Pending Review","🔍 Under Review by "&AL82,IF(AN82="Escalated","⬆️ Escalated - Senior Management Review","")))))))
A83: =A82+1 -> 82 | B83: PM Vishwakarma | C83: 3739384 | D83: Day 0 | E83: Construction | G83: Brick Mason -Basic( CON/N0160 ) | H83: ORION EDUTECH PRIVATE LIMITED | I83: DARRANG | J83: ASSAM | K83: 46131 | L83: 46131 | M83: 41 | O83: =IF(AND(M83<>"",N83<>""),M83-N83,"") | Q83: =IF(AND(N83<>"",P83<>""),N83-P83,"") | S83: =IF(AND(N83<>"",R83<>""),N83-R83,"") | V83: =IFERROR(R83/N83,"") | W83: =IFERROR(S83/N83,"") | X83: Lalbabu Ahmed | Y83: AR103539/Lal@1234 | AB83: =IFERROR(VLOOKUP(B83,'Scheme Master'!$B$4:$C$79,2,FALSE),"") -> 360 | AC83: =IF(AND(AB83<>"",N83<>""),AB83*N83,"") | AF83: =IF(OR(AD83<>"",AE83<>""),AD83+AE83,"") | AG83: =IF(AND(AC83<>"",AF83<>""),AC83-AF83,"") | AH83: =IF(AND(AC83<>"",AC83>0,AF83<>""),AF83/AC83,"") | AI83: =IF(AH83="","",IF(AF83>AC83,"🔴 Critical - Over Budget",IF(AH83>0.4,"⚠️ Approval Required","✅ Auto-Approved"))) | AO83: =IF(AI83="","",IF(AI83="✅ Auto-Approved","✅ Approved (Auto - Within Budget)",IF(AN83="","⏳ Awaiting Approval",IF(AN83="Approved","✅ Approved by "&AL83&" on "&TEXT(AM83,"mm/dd/yyyy"),IF(AN83="Rejected","❌ Rejected by "&AL83&" - Review Expenses",IF(AN83="Pending Review","🔍 Under Review by "&AL83,IF(AN83="Escalated","⬆️ Escalated - Senior Management Review","")))))))
A84: =A83+1 -> 83 | B84: PM Vishwakarma | C84: 3756903 | D84: Day 6 | E84: Construction | G84: Brick Mason -Basic( CON/N0160 ) | H84: GOVERNMENT POLYTECHNIC FOR WOMEN SRINAGAR | I84: SRINAGAR | J84: JAMMU AND KASHMIR | K84: 46124 | L84: 46124 | M84: 43 | N84: 24 | O84: =IF(AND(M84<>"",N84<>""),M84-N84,"") -> 19 | P84: 24 | Q84: =IF(AND(N84<>"",P84<>""),N84-P84,"") -> 0 | R84: 24 | S84: =IF(AND(N84<>"",R84<>""),N84-R84,"") -> 0 | T84: 46124 | U84: Uploaded | V84: =IFERROR(R84/N84,"") -> 1 | W84: =IFERROR(S84/N84,"") -> 0 | X84: MUDASSAR AHMED | Y84: AR80508/Openzargar@49 | Z84: Aadil saidullah bhat | AA84: TR395267 | AB84: =IFERROR(VLOOKUP(B84,'Scheme Master'!$B$4:$C$79,2,FALSE),"") -> 360 | AC84: =IF(AND(AB84<>"",N84<>""),AB84*N84,"") -> 8640 | AF84: =IF(OR(AD84<>"",AE84<>""),AD84+AE84,"") | AG84: =IF(AND(AC84<>"",AF84<>""),AC84-AF84,"") | AH84: =IF(AND(AC84<>"",AC84>0,AF84<>""),AF84/AC84,"") | AI84: =IF(AH84="","",IF(AF84>AC84,"🔴 Critical - Over Budget",IF(AH84>0.4,"⚠️ Approval Required","✅ Auto-Approved"))) | AO84: =IF(AI84="","",IF(AI84="✅ Auto-Approved","✅ Approved (Auto - Within Budget)",IF(AN84="","⏳ Awaiting Approval",IF(AN84="Approved","✅ Approved by "&AL84&" on "&TEXT(AM84,"mm/dd/yyyy"),IF(AN84="Rejected","❌ Rejected by "&AL84&" - Review Expenses",IF(AN84="Pending Review","🔍 Under Review by "&AL84,IF(AN84="Escalated","⬆️ Escalated - Senior Management Review","")))))))
A85: =A84+1 -> 84 | B85: PM Vishwakarma | C85: 3760992 | D85: Day 0 | E85: handicraft | G85: Potter (Kumhar) including traditional ceramics and terracotta product maker( HCS/N9213 ) | H85: APITCO LIMITED | I85: AMBEDKAR NAGAR | J85: UTTAR PRADESH | K85: 46124 | L85: 46124 | M85: 24 | N85: 18 | O85: =IF(AND(M85<>"",N85<>""),M85-N85,"") -> 6 | P85: 16 | Q85: =IF(AND(N85<>"",P85<>""),N85-P85,"") -> 2 | R85: 18 | S85: =IF(AND(N85<>"",R85<>""),N85-R85,"") -> 0 | T85: 46124 | U85: Uploaded | V85: =IFERROR(R85/N85,"") -> 1 | W85: =IFERROR(S85/N85,"") -> 0 | X85: SAHDEV PRAJAPATI | Y85: AR104406 / Aisect@123 | Z85: sahdav prajapati | AA85: TR475299 | AB85: =IFERROR(VLOOKUP(B85,'Scheme Master'!$B$4:$C$79,2,FALSE),"") -> 360 | AC85: =IF(AND(AB85<>"",N85<>""),AB85*N85,"") -> 6480 | AF85: =IF(OR(AD85<>"",AE85<>""),AD85+AE85,"") | AG85: =IF(AND(AC85<>"",AF85<>""),AC85-AF85,"") | AH85: =IF(AND(AC85<>"",AC85>0,AF85<>""),AF85/AC85,"") | AI85: =IF(AH85="","",IF(AF85>AC85,"🔴 Critical - Over Budget",IF(AH85>0.4,"⚠️ Approval Required","✅ Auto-Approved"))) | AO85: =IF(AI85="","",IF(AI85="✅ Auto-Approved","✅ Approved (Auto - Within Budget)",IF(AN85="","⏳ Awaiting Approval",IF(AN85="Approved","✅ Approved by "&AL85&" on "&TEXT(AM85,"mm/dd/yyyy"),IF(AN85="Rejected","❌ Rejected by "&AL85&" - Review Expenses",IF(AN85="Pending Review","🔍 Under Review by "&AL85,IF(AN85="Escalated","⬆️ Escalated - Senior Management Review","")))))))
A86: =A85+1 -> 85 | B86: PM Vishwakarma | C86: 3760899 | D86: Day 0 | E86: handicraft | G86: Traditional Soft Toy Maker( HCS/N7355 ) | H86: APITCO LIMITED | I86: AMBEDKAR NAGAR | J86: UTTAR PRADESH | K86: 46124 | L86: 46124 | M86: 15 | N86: 14 | O86: =IF(AND(M86<>"",N86<>""),M86-N86,"") -> 1 | P86: 5 | Q86: =IF(AND(N86<>"",P86<>""),N86-P86,"") -> 9 | R86: 14 | S86: =IF(AND(N86<>"",R86<>""),N86-R86,"") -> 0 | T86: 46124 | U86: Uploaded | V86: =IFERROR(R86/N86,"") -> 1 | W86: =IFERROR(S86/N86,"") -> 0 | X86: Aftab Husain | Y86: AR101205 / Rms@7860 | Z86: Rena Verma | AA86: TR314334 | AB86: =IFERROR(VLOOKUP(B86,'Scheme Master'!$B$4:$C$79,2,FALSE),"") -> 360 | AC86: =IF(AND(AB86<>"",N86<>""),AB86*N86,"") -> 5040 | AF86: =IF(OR(AD86<>"",AE86<>""),AD86+AE86,"") | AG86: =IF(AND(AC86<>"",AF86<>""),AC86-AF86,"") | AH86: =IF(AND(AC86<>"",AC86>0,AF86<>""),AF86/AC86,"") | AI86: =IF(AH86="","",IF(AF86>AC86,"🔴 Critical - Over Budget",IF(AH86>0.4,"⚠️ Approval Required","✅ Auto-Approved"))) | AO86: =IF(AI86="","",IF(AI86="✅ Auto-Approved","✅ Approved (Auto - Within Budget)",IF(AN86="","⏳ Awaiting Approval",IF(AN86="Approved","✅ Approved by "&AL86&" on "&TEXT(AM86,"mm/dd/yyyy"),IF(AN86="Rejected","❌ Rejected by "&AL86&" - Review Expenses",IF(AN86="Pending Review","🔍 Under Review by "&AL86,IF(AN86="Escalated","⬆️ Escalated - Senior Management Review","")))))))
A87: =A86+1 -> 86 | B87: 3rd Party | C87: Switchon_Batch _01 | D87: Normal | E87: Green Jobs | G87: Solar Program | H87: SwitchON | K87: 46125 | L87: 46125 | M87: 29 | N87: 28 | O87: =IF(AND(M87<>"",N87<>""),M87-N87,"") -> 1 | P87: 28 | Q87: =IF(AND(N87<>"",P87<>""),N87-P87,"") -> 0 | R87: 28 | S87: =IF(AND(N87<>"",R87<>""),N87-R87,"") -> 0 | T87: 46128 | U87: Uploaded | V87: =IFERROR(R87/N87,"") -> 1 | W87: =IFERROR(S87/N87,"") -> 0 | AB87: =IFERROR(VLOOKUP(B87,'Scheme Master'!$B$4:$C$79,2,FALSE),"") -> 480 | AC87: =IF(AND(AB87<>"",N87<>""),AB87*N87,"") -> 13440 | AF87: =IF(OR(AD87<>"",AE87<>""),AD87+AE87,"") | AG87: =IF(AND(AC87<>"",AF87<>""),AC87-AF87,"") | AH87: =IF(AND(AC87<>"",AC87>0,AF87<>""),AF87/AC87,"") | AI87: =IF(AH87="","",IF(AF87>AC87,"🔴 Critical - Over Budget",IF(AH87>0.4,"⚠️ Approval Required","✅ Auto-Approved"))) | AO87: =IF(AI87="","",IF(AI87="✅ Auto-Approved","✅ Approved (Auto - Within Budget)",IF(AN87="","⏳ Awaiting Approval",IF(AN87="Approved","✅ Approved by "&AL87&" on "&TEXT(AM87,"mm/dd/yyyy"),IF(AN87="Rejected","❌ Rejected by "&AL87&" - Review Expenses",IF(AN87="Pending Review","🔍 Under Review by "&AL87,IF(AN87="Escalated","⬆️ Escalated - Senior Management Review","")))))))
A88: =A87+1 -> 87 | B88: PM Vishwakarma | C88: 3761649 | D88: Day 0 | E88: gems and Jewellery | G88: Goldsmith (Sunar)( G&J/N0612 ) | H88: EMPOWER PRAGATI VOCATIONAL AND STAFFING PRIVATE LIMITED | I88: BHARATPUR | J88: RAJASTHAN | K88: 46125 | L88: 46125 | M88: 37 | N88: 27 | O88: =IF(AND(M88<>"",N88<>""),M88-N88,"") -> 10 | Q88: =IF(AND(N88<>"",P88<>""),N88-P88,"") | R88: 27 | S88: =IF(AND(N88<>"",R88<>""),N88-R88,"") -> 0 | T88: 46125 | U88: Uploaded | V88: =IFERROR(R88/N88,"") -> 1 | W88: =IFERROR(S88/N88,"") -> 0 | X88: Anisha Soni | Y88: AR180647 / Soni@123 | AB88: =IFERROR(VLOOKUP(B88,'Scheme Master'!$B$4:$C$79,2,FALSE),"") -> 360 | AC88: =IF(AND(AB88<>"",N88<>""),AB88*N88,"") -> 9720 | AF88: =IF(OR(AD88<>"",AE88<>""),AD88+AE88,"") | AG88: =IF(AND(AC88<>"",AF88<>""),AC88-AF88,"") | AH88: =IF(AND(AC88<>"",AC88>0,AF88<>""),AF88/AC88,"") | AI88: =IF(AH88="","",IF(AF88>AC88,"🔴 Critical - Over Budget",IF(AH88>0.4,"⚠️ Approval Required","✅ Auto-Approved"))) | AO88: =IF(AI88="","",IF(AI88="✅ Auto-Approved","✅ Approved (Auto - Within Budget)",IF(AN88="","⏳ Awaiting Approval",IF(AN88="Approved","✅ Approved by "&AL88&" on "&TEXT(AM88,"mm/dd/yyyy"),IF(AN88="Rejected","❌ Rejected by "&AL88&" - Review Expenses",IF(AN88="Pending Review","🔍 Under Review by "&AL88,IF(AN88="Escalated","⬆️ Escalated - Senior Management Review","")))))))
A89: =A88+1 -> 88 | B89: PMAY-G-STT | C89: 3573816 | D89: Normal | E89: Construction | G89: Rural Mason V4.0 CON/Q3603-SI001 | H89: Merapath Education Limited | I89: Nashik | J89: Maharashtra | K89: 46126 | L89: 46127 | M89: 30 | O89: =IF(AND(M89<>"",N89<>""),M89-N89,"") | Q89: =IF(AND(N89<>"",P89<>""),N89-P89,"") | S89: =IF(AND(N89<>"",R89<>""),N89-R89,"") | V89: =IFERROR(R89/N89,"") | W89: =IFERROR(S89/N89,"") | X89: Deepsingh Tanwar | Y89: AR16827 | AB89: =IFERROR(VLOOKUP(B89,'Scheme Master'!$B$4:$C$79,2,FALSE),"") -> 720 | AC89: =IF(AND(AB89<>"",N89<>""),AB89*N89,"") | AF89: =IF(OR(AD89<>"",AE89<>""),AD89+AE89,"") | AG89: =IF(AND(AC89<>"",AF89<>""),AC89-AF89,"") | AH89: =IF(AND(AC89<>"",AC89>0,AF89<>""),AF89/AC89,"") | AI89: =IF(AH89="","",IF(AF89>AC89,"🔴 Critical - Over Budget",IF(AH89>0.4,"⚠️ Approval Required","✅ Auto-Approved"))) | AO89: =IF(AI89="","",IF(AI89="✅ Auto-Approved","✅ Approved (Auto - Within Budget)",IF(AN89="","⏳ Awaiting Approval",IF(AN89="Approved","✅ Approved by "&AL89&" on "&TEXT(AM89,"mm/dd/yyyy"),IF(AN89="Rejected","❌ Rejected by "&AL89&" - Review Expenses",IF(AN89="Pending Review","🔍 Under Review by "&AL89,IF(AN89="Escalated","⬆️ Escalated - Senior Management Review","")))))))
A90: =A89+1 -> 89 | B90: PM Vishwakarma | C90: 3759213 | D90: Day 6 | E90: gems and Jewellery | G90: Goldsmith (Sunar)( G&J/N0612 ) | H90: LEARNET SKILLS LIMITED | I90: JHUNJHUNU | J90: RAJASTHAN | K90: 46126 | L90: 46126 | M90: 33 | N90: 24 | O90: =IF(AND(M90<>"",N90<>""),M90-N90,"") -> 9 | P90: 21 | Q90: =IF(AND(N90<>"",P90<>""),N90-P90,"") -> 3 | R90: 24 | S90: =IF(AND(N90<>"",R90<>""),N90-R90,"") -> 0 | T90: 46126 | U90: Uploaded | V90: =IFERROR(R90/N90,"") -> 1 | W90: =IFERROR(S90/N90,"") -> 0 | X90: Yogesh Jangir | Y90: AR123754 | Z90: Sukhveer Singh Maan | AA90: TR620280 | AB90: =IFERROR(VLOOKUP(B90,'Scheme Master'!$B$4:$C$79,2,FALSE),"") -> 360 | AC90: =IF(AND(AB90<>"",N90<>""),AB90*N90,"") -> 8640 | AF90: =IF(OR(AD90<>"",AE90<>""),AD90+AE90,"") | AG90: =IF(AND(AC90<>"",AF90<>""),AC90-AF90,"") | AH90: =IF(AND(AC90<>"",AC90>0,AF90<>""),AF90/AC90,"") | AI90: =IF(AH90="","",IF(AF90>AC90,"🔴 Critical - Over Budget",IF(AH90>0.4,"⚠️ Approval Required","✅ Auto-Approved"))) | AO90: =IF(AI90="","",IF(AI90="✅ Auto-Approved","✅ Approved (Auto - Within Budget)",IF(AN90="","⏳ Awaiting Approval",IF(AN90="Approved","✅ Approved by "&AL90&" on "&TEXT(AM90,"mm/dd/yyyy"),IF(AN90="Rejected","❌ Rejected by "&AL90&" - Review Expenses",IF(AN90="Pending Review","🔍 Under Review by "&AL90,IF(AN90="Escalated","⬆️ Escalated - Senior Management Review","")))))))
A91: =A90+1 -> 90 | B91: PM Vishwakarma | C91: 3761653 | D91: Day 0 | E91: handicraft | G91: Traditional Soft Toy Maker( HCS/N7355 ) | H91: MEDHAVI FOUNDATION | I91: CACHAR | J91: ASSAM | K91: 46126 | L91: 46126 | M91: 30 | N91: 20 | O91: =IF(AND(M91<>"",N91<>""),M91-N91,"") -> 10 | P91: 1 | Q91: =IF(AND(N91<>"",P91<>""),N91-P91,"") -> 19 | R91: 20 | S91: =IF(AND(N91<>"",R91<>""),N91-R91,"") -> 0 | T91: 46126 | U91: Uploaded | V91: =IFERROR(R91/N91,"") -> 1 | W91: =IFERROR(S91/N91,"") -> 0 | X91: Kalyani Deb | Y91: AR77139 | AB91: =IFERROR(VLOOKUP(B91,'Scheme Master'!$B$4:$C$79,2,FALSE),"") -> 360 | AC91: =IF(AND(AB91<>"",N91<>""),AB91*N91,"") -> 7200 | AF91: =IF(OR(AD91<>"",AE91<>""),AD91+AE91,"") | AG91: =IF(AND(AC91<>"",AF91<>""),AC91-AF91,"") | AH91: =IF(AND(AC91<>"",AC91>0,AF91<>""),AF91/AC91,"") | AI91: =IF(AH91="","",IF(AF91>AC91,"🔴 Critical - Over Budget",IF(AH91>0.4,"⚠️ Approval Required","✅ Auto-Approved"))) | AO91: =IF(AI91="","",IF(AI91="✅ Auto-Approved","✅ Approved (Auto - Within Budget)",IF(AN91="","⏳ Awaiting Approval",IF(AN91="Approved","✅ Approved by "&AL91&" on "&TEXT(AM91,"mm/dd/yyyy"),IF(AN91="Rejected","❌ Rejected by "&AL91&" - Review Expenses",IF(AN91="Pending Review","🔍 Under Review by "&AL91,IF(AN91="Escalated","⬆️ Escalated - Senior Management Review","")))))))
A92: =A91+1 -> 91 | B92: PM Vishwakarma | C92: 3760024 | D92: Day 6 | E92: Construction | G92: Brick Mason -Basic( CON/N0160 ) | H92: CENTRAL FOOTWEAR TRAINING INSTITUTE | I92: JANJGIR-CHAMPA | J92: CHHATTISGARH | K92: 46127 | L92: 46127 | M92: 41 | N92: 24 | O92: =IF(AND(M92<>"",N92<>""),M92-N92,"") -> 17 | Q92: =IF(AND(N92<>"",P92<>""),N92-P92,"") | S92: =IF(AND(N92<>"",R92<>""),N92-R92,"") | V92: =IFERROR(R92/N92,"") -> 0 | W92: 0 | X92: Takesh Kumar | Y92: AR130863 | AB92: =IFERROR(VLOOKUP(B92,'Scheme Master'!$B$4:$C$79,2,FALSE),"") -> 360 | AC92: =IF(AND(AB92<>"",N92<>""),AB92*N92,"") -> 8640 | AD92: 3000 | AF92: =IF(OR(AD92<>"",AE92<>""),AD92+AE92,"") -> 3000 | AG92: =IF(AND(AC92<>"",AF92<>""),AC92-AF92,"") -> 5640 | AH92: =IF(AND(AC92<>"",AC92>0,AF92<>""),AF92/AC92,"") -> 0.34722222 | AI92: =IF(AH92="","",IF(AF92>AC92,"🔴 Critical - Over Budget",IF(AH92>0.4,"⚠️ Approval Required","✅ Auto-Approved"))) -> ✅ Auto-Approved | AO92: =IF(AI92="","",IF(AI92="✅ Auto-Approved","✅ Approved (Auto - Within Budget)",IF(AN92="","⏳ Awaiting Approval",IF(AN92="Approved","✅ Approved by "&AL92&" on "&TEXT(AM92,"mm/dd/yyyy"),IF(AN92="Rejected","❌ Rejected by "&AL92&" - Review Expenses",IF(AN92="Pending Review","🔍 Under Review by "&AL92,IF(AN92="Escalated","⬆️ Escalated - Senior Management Review",""))))))) -> ✅ Approved (Auto - Within Budget)
A93: =A92+1 -> 92 | B93: PMAY-G-RPL | C93: 3723643 | D93: Normal | E93: Construction | G93: Rural Mason V4.0 | H93: Padmaranjeeta Education Trust | I93: Darrang | J93: ASSAM | K93: 46127 | L93: 46128 | M93: 30 | O93: =IF(AND(M93<>"",N93<>""),M93-N93,"") | Q93: =IF(AND(N93<>"",P93<>""),N93-P93,"") | S93: =IF(AND(N93<>"",R93<>""),N93-R93,"") | V93: =IFERROR(R93/N93,"") | W93: =IFERROR(S93/N93,"") | X93: Krishnapal Singh | Y93: AR77228 | AB93: =IFERROR(VLOOKUP(B93,'Scheme Master'!$B$4:$C$79,2,FALSE),"") -> 540 | AC93: =IF(AND(AB93<>"",N93<>""),AB93*N93,"") | AF93: =IF(OR(AD93<>"",AE93<>""),AD93+AE93,"") | AG93: =IF(AND(AC93<>"",AF93<>""),AC93-AF93,"") | AH93: =IF(AND(AC93<>"",AC93>0,AF93<>""),AF93/AC93,"") | AI93: =IF(AH93="","",IF(AF93>AC93,"🔴 Critical - Over Budget",IF(AH93>0.4,"⚠️ Approval Required","✅ Auto-Approved"))) | AO93: =IF(AI93="","",IF(AI93="✅ Auto-Approved","✅ Approved (Auto - Within Budget)",IF(AN93="","⏳ Awaiting Approval",IF(AN93="Approved","✅ Approved by "&AL93&" on "&TEXT(AM93,"mm/dd/yyyy"),IF(AN93="Rejected","❌ Rejected by "&AL93&" - Review Expenses",IF(AN93="Pending Review","🔍 Under Review by "&AL93,IF(AN93="Escalated","⬆️ Escalated - Senior Management Review","")))))))
A94: =A93+1 -> 93 | B94: NAPS | C94: NAPS_15-04-2026 | D94: Normal | E94: gems and Jewellery | G94: Planner | H94: Dimexon Diamonds Limited | K94: 46127 | L94: 46127 | M94: 5 | O94: =IF(AND(M94<>"",N94<>""),M94-N94,"") | Q94: =IF(AND(N94<>"",P94<>""),N94-P94,"") | S94: =IF(AND(N94<>"",R94<>""),N94-R94,"") | V94: =IFERROR(R94/N94,"") | W94: =IFERROR(S94/N94,"") | AB94: =IFERROR(VLOOKUP(B94,'Scheme Master'!$B$4:$C$79,2,FALSE),"") -> 70 | AC94: =IF(AND(AB94<>"",N94<>""),AB94*N94,"") | AF94: =IF(OR(AD94<>"",AE94<>""),AD94+AE94,"") | AG94: =IF(AND(AC94<>"",AF94<>""),AC94-AF94,"") | AH94: =IF(AND(AC94<>"",AC94>0,AF94<>""),AF94/AC94,"") | AI94: =IF(AH94="","",IF(AF94>AC94,"🔴 Critical - Over Budget",IF(AH94>0.4,"⚠️ Approval Required","✅ Auto-Approved"))) | AO94: =IF(AI94="","",IF(AI94="✅ Auto-Approved","✅ Approved (Auto - Within Budget)",IF(AN94="","⏳ Awaiting Approval",IF(AN94="Approved","✅ Approved by "&AL94&" on "&TEXT(AM94,"mm/dd/yyyy"),IF(AN94="Rejected","❌ Rejected by "&AL94&" - Review Expenses",IF(AN94="Pending Review","🔍 Under Review by "&AL94,IF(AN94="Escalated","⬆️ Escalated - Senior Management Review","")))))))
A95: =A94+1 -> 94 | B95: PM Vishwakarma | C95: 3762478 | D95: Day 0 | E95: handicraft | G95: Basic sculptor and stone artist (Moortikar)( HCS/N1506 ) | H95: AFC INDIA LIMITED | I95: PALNADU | J95: ANDHRA PRADESH | K95: 46129 | L95: 46129 | M95: 15 | O95: =IF(AND(M95<>"",N95<>""),M95-N95,"") | Q95: =IF(AND(N95<>"",P95<>""),N95-P95,"") | S95: =IF(AND(N95<>"",R95<>""),N95-R95,"") | V95: =IFERROR(R95/N95,"") | W95: =IFERROR(S95/N95,"") | X95: Ergadindla Tharun | Y95: AR112532/Shritech@1234 | Z95: Ergadindla Tharun | AA95: TR492315 | AB95: =IFERROR(VLOOKUP(B95,'Scheme Master'!$B$4:$C$79,2,FALSE),"") -> 360 | AC95: =IF(AND(AB95<>"",N95<>""),AB95*N95,"") | AF95: =IF(OR(AD95<>"",AE95<>""),AD95+AE95,"") | AG95: =IF(AND(AC95<>"",AF95<>""),AC95-AF95,"") | AH95: =IF(AND(AC95<>"",AC95>0,AF95<>""),AF95/AC95,"") | AI95: =IF(AH95="","",IF(AF95>AC95,"🔴 Critical - Over Budget",IF(AH95>0.4,"⚠️ Approval Required","✅ Auto-Approved"))) | AO95: =IF(AI95="","",IF(AI95="✅ Auto-Approved","✅ Approved (Auto - Within Budget)",IF(AN95="","⏳ Awaiting Approval",IF(AN95="Approved","✅ Approved by "&AL95&" on "&TEXT(AM95,"mm/dd/yyyy"),IF(AN95="Rejected","❌ Rejected by "&AL95&" - Review Expenses",IF(AN95="Pending Review","🔍 Under Review by "&AL95,IF(AN95="Escalated","⬆️ Escalated - Senior Management Review","")))))))
A96: =A95+1 -> 95 | B96: PM Vishwakarma | C96: 3760887 | D96: Day 6 | E96: gems and Jewellery | G96: Goldsmith (Sunar)( G&J/N0612 ) | H96: GOVT ITI, GARHWA | I96: GARHWA | J96: JHARKHAND | K96: 46127 | L96: 46127 | M96: 11 | N96: 8 | O96: =IF(AND(M96<>"",N96<>""),M96-N96,"") -> 3 | P96: 8 | Q96: =IF(AND(N96<>"",P96<>""),N96-P96,"") -> 0 | R96: 8 | S96: =IF(AND(N96<>"",R96<>""),N96-R96,"") -> 0 | T96: 46127 | U96: Uploaded | V96: =IFERROR(R96/N96,"") -> 1 | W96: =IFERROR(S96/N96,"") -> 0 | X96: Dilshad Ansari | Y96: AR180986 | Z96: Bikrant Sagar Minz | AA96: TR660935 | AB96: =IFERROR(VLOOKUP(B96,'Scheme Master'!$B$4:$C$79,2,FALSE),"") -> 360 | AC96: =IF(AND(AB96<>"",N96<>""),AB96*N96,"") -> 2880 | AD96: 2000 | AE96: 600 | AF96: =IF(OR(AD96<>"",AE96<>""),AD96+AE96,"") -> 2600 | AG96: =IF(AND(AC96<>"",AF96<>""),AC96-AF96,"") -> 280 | AH96: =IF(AND(AC96<>"",AC96>0,AF96<>""),AF96/AC96,"") -> 0.90277778 | AI96: =IF(AH96="","",IF(AF96>AC96,"🔴 Critical - Over Budget",IF(AH96>0.4,"⚠️ Approval Required","✅ Auto-Approved"))) -> ⚠️ Approval Required | AJ96: Mail Sent | AK96: Nisha Saifi | AO96: =IF(AI96="","",IF(AI96="✅ Auto-Approved","✅ Approved (Auto - Within Budget)",IF(AN96="","⏳ Awaiting Approval",IF(AN96="Approved","✅ Approved by "&AL96&" on "&TEXT(AM96,"mm/dd/yyyy"),IF(AN96="Rejected","❌ Rejected by "&AL96&" - Review Expenses",IF(AN96="Pending Review","🔍 Under Review by "&AL96,IF(AN96="Escalated","⬆️ Escalated - Senior Management Review",""))))))) -> ⏳ Awaiting Approval
A97: =A96+1 -> 96 | B97: PM Vishwakarma | C97: 3760057 | D97: Day 6 | E97: gems and Jewellery | G97: Goldsmith (Sunar)( G&J/N0612 ) | H97: Government Industrial Training Institute, Kannauj 209732 | I97: KANNAUJ | J97: UTTAR PRADESH | K97: 46128 | L97: 46128 | M97: 11 | N97: 5 | O97: =IF(AND(M97<>"",N97<>""),M97-N97,"") -> 6 | P97: 5 | Q97: =IF(AND(N97<>"",P97<>""),N97-P97,"") -> 0 | R97: 5 | S97: =IF(AND(N97<>"",R97<>""),N97-R97,"") -> 0 | T97: 46128 | U97: Uploaded | V97: =IFERROR(R97/N97,"") -> 1 | W97: =IFERROR(S97/N97,"") -> 0 | X97: Ankit Mishra | Y97: AR67665 / Ankit@321 | Z97: Deepa singh | AA97: TR533198 | AB97: =IFERROR(VLOOKUP(B97,'Scheme Master'!$B$4:$C$79,2,FALSE),"") -> 360 | AD97: 2000 | AE97: 600 | AF97: =IF(OR(AD97<>"",AE97<>""),AD97+AE97,"") -> 2600 | AG97: =IF(AND(AC97<>"",AF97<>""),AC97-AF97,"") | AH97: =IF(AND(AC97<>"",AC97>0,AF97<>""),AF97/AC97,"") | AI97: =IF(AH97="","",IF(AF97>AC97,"🔴 Critical - Over Budget",IF(AH97>0.4,"⚠️ Approval Required","✅ Auto-Approved"))) | AO97: =IF(AI97="","",IF(AI97="✅ Auto-Approved","✅ Approved (Auto - Within Budget)",IF(AN97="","⏳ Awaiting Approval",IF(AN97="Approved","✅ Approved by "&AL97&" on "&TEXT(AM97,"mm/dd/yyyy"),IF(AN97="Rejected","❌ Rejected by "&AL97&" - Review Expenses",IF(AN97="Pending Review","🔍 Under Review by "&AL97,IF(AN97="Escalated","⬆️ Escalated - Senior Management Review","")))))))
A98: =A97+1 -> 97 | B98: PM Vishwakarma | C98: 3763199 | D98: Day 0 | E98: gems and Jewellery | G98: Goldsmith (Sunar)( G&J/N0612 ) | H98: EMPOWER PRAGATI VOCATIONAL AND STAFFING PRIVATE LIMITED | I98: BHARATPUR | J98: RAJASTHAN | K98: 46127 | L98: 46127 | M98: 25 | N98: 15 | O98: =IF(AND(M98<>"",N98<>""),M98-N98,"") -> 10 | P98: 9 | Q98: =IF(AND(N98<>"",P98<>""),N98-P98,"") -> 6 | R98: 15 | S98: =IF(AND(N98<>"",R98<>""),N98-R98,"") -> 0 | T98: 46127 | U98: Uploaded | V98: =IFERROR(R98/N98,"") -> 1 | W98: =IFERROR(S98/N98,"") -> 0 | X98: Anisha Soni | Y98: AR180647 / Soni@123 | AB98: =IFERROR(VLOOKUP(B98,'Scheme Master'!$B$4:$C$79,2,FALSE),"") -> 360 | AC98: =IF(AND(AB98<>"",N98<>""),AB98*N98,"") -> 5400 | AF98: =IF(OR(AD98<>"",AE98<>""),AD98+AE98,"") | AG98: =IF(AND(AC98<>"",AF98<>""),AC98-AF98,"") | AH98: =IF(AND(AC98<>"",AC98>0,AF98<>""),AF98/AC98,"") | AI98: =IF(AH98="","",IF(AF98>AC98,"🔴 Critical - Over Budget",IF(AH98>0.4,"⚠️ Approval Required","✅ Auto-Approved"))) | AO98: =IF(AI98="","",IF(AI98="✅ Auto-Approved","✅ Approved (Auto - Within Budget)",IF(AN98="","⏳ Awaiting Approval",IF(AN98="Approved","✅ Approved by "&AL98&" on "&TEXT(AM98,"mm/dd/yyyy"),IF(AN98="Rejected","❌ Rejected by "&AL98&" - Review Expenses",IF(AN98="Pending Review","🔍 Under Review by "&AL98,IF(AN98="Escalated","⬆️ Escalated - Senior Management Review","")))))))
A99: =A98+1 -> 98 | B99: PM Vishwakarma | C99: 3762282 | D99: Day 0 | E99: Construction | G99: Brick Mason -Basic( CON/N0160 ) | H99: MOSAIC WORKSKILLS PRIVATE LIMITED | I99: GANDERBAL | J99: JAMMU AND KASHMIR | K99: 46128 | L99: 46128 | M99: 11 | N99: 5 | O99: =IF(AND(M99<>"",N99<>""),M99-N99,"") -> 6 | P99: 5 | Q99: =IF(AND(N99<>"",P99<>""),N99-P99,"") -> 0 | R99: 5 | S99: =IF(AND(N99<>"",R99<>""),N99-R99,"") -> 0 | T99: 46128 | U99: Uploaded | V99: =IFERROR(R99/N99,"") -> 1 | W99: =IFERROR(S99/N99,"") -> 0 | X99: Mubashir Manzoor | Y99: AR83388/Muba@1234 | AB99: =IFERROR(VLOOKUP(B99,'Scheme Master'!$B$4:$C$79,2,FALSE),"") -> 360 | AC99: =IF(AND(AB99<>"",N99<>""),AB99*N99,"") -> 1800 | AF99: =IF(OR(AD99<>"",AE99<>""),AD99+AE99,"") | AG99: =IF(AND(AC99<>"",AF99<>""),AC99-AF99,"") | AH99: =IF(AND(AC99<>"",AC99>0,AF99<>""),AF99/AC99,"") | AI99: =IF(AH99="","",IF(AF99>AC99,"🔴 Critical - Over Budget",IF(AH99>0.4,"⚠️ Approval Required","✅ Auto-Approved"))) | AO99: =IF(AI99="","",IF(AI99="✅ Auto-Approved","✅ Approved (Auto - Within Budget)",IF(AN99="","⏳ Awaiting Approval",IF(AN99="Approved","✅ Approved by "&AL99&" on "&TEXT(AM99,"mm/dd/yyyy"),IF(AN99="Rejected","❌ Rejected by "&AL99&" - Review Expenses",IF(AN99="Pending Review","🔍 Under Review by "&AL99,IF(AN99="Escalated","⬆️ Escalated - Senior Management Review","")))))))
A100: =A99+1 -> 99 | B100: PM Vishwakarma | C100: 3761960 | D100: Day 6 | E100: handicraft | G100: Traditional Soft Toy Maker( HCS/N7355 ) | H100: GOVT WOMEN INDUSTRIAL TRAINING INSTITUTE BHAGALPUR | I100: BHAGALPUR | J100: BIHAR | K100: 46129 | L100: 46129 | M100: 10 | O100: =IF(AND(M100<>"",N100<>""),M100-N100,"") | Q100: =IF(AND(N100<>"",P100<>""),N100-P100,"") | S100: =IF(AND(N100<>"",R100<>""),N100-R100,"") | V100: =IFERROR(R100/N100,"") | W100: =IFERROR(S100/N100,"") | X100: Shabnam Kumari | Y100: AR106886 / New@#123 | Z100: Hari Priya Kumari | AA100: TR633659 | AB100: =IFERROR(VLOOKUP(B100,'Scheme Master'!$B$4:$C$79,2,FALSE),"") -> 360 | AC100: =IF(AND(AB100<>"",N100<>""),AB100*N100,"") | AF100: =IF(OR(AD100<>"",AE100<>""),AD100+AE100,"") | AG100: =IF(AND(AC100<>"",AF100<>""),AC100-AF100,"") | AH100: =IF(AND(AC100<>"",AC100>0,AF100<>""),AF100/AC100,"") | AI100: =IF(AH100="","",IF(AF100>AC100,"🔴 Critical - Over Budget",IF(AH100>0.4,"⚠️ Approval Required","✅ Auto-Approved"))) | AO100: =IF(AI100="","",IF(AI100="✅ Auto-Approved","✅ Approved (Auto - Within Budget)",IF(AN100="","⏳ Awaiting Approval",IF(AN100="Approved","✅ Approved by "&AL100&" on "&TEXT(AM100,"mm/dd/yyyy"),IF(AN100="Rejected","❌ Rejected by "&AL100&" - Review Expenses",IF(AN100="Pending Review","🔍 Under Review by "&AL100,IF(AN100="Escalated","⬆️ Escalated - Senior Management Review","")))))))
...

Sheet Sheet2
A1: 46121 | B1: Multiple Mistakes found in one day.
A2: 46122 | B2: DBMS and Assessment Tracker status not matched

Sheet PMKVY 4.0 

Sheet Dashboard
A1: 📊 ASSESSMENT COST MANAGEMENT DASHBOARD | K1: CHART DATA (Scheme-wise)
K2: Scheme | L2: Batches | M2: Candidates | N2: Income | O2: Expenses | P2: Profit
A3: 📋 KEY PERFORMANCE INDICATORS | K3: =A13 -> PMKVY 4.0 | L3: =B13 -> 9 | M3: =D13 -> 161 | N3: =F13 -> 77280 | O3: =H13 -> 14000 | P3: =I13 -> 63280
K4: =A14 -> DDUGKY | L4: =B14 -> 2 | M4: =D14 -> 54 | N4: =F14 -> 38880 | O4: =H14 -> 0 | P4: =I14 -> 38880
A5: Total Assessments | B5: =COUNTA('Assessment Tracker'!A2:A115) -> 114 | D5: Total Candidates | F5: Pass % | H5: Total Income (₹) | K5: =A15 -> ODOP-RPL | L5: =B15 -> 8 | M5: =D15 -> 188 | N5: =F15 -> 101520 | O5: =H15 -> 7690 | P5: =I15 -> 93830
K6: =A16 -> #REF! | L6: =B16 -> 0 | M6: =D16 -> 0 | N6: =F16 -> 0 | O6: =H16 -> 0 | P6: =I16 -> 0
D7: =SUM('Assessment Tracker'!N2:N115) -> 1501 | F7: =IFERROR(SUM('Assessment Tracker'!R2:R115)/SUM('Assessment Tracker'!N2:N115),0) -> 0.97534977 | H7: =SUM('Assessment Tracker'!AC2:AC115) -> 670400 | K7: =A17 -> BSDMA-RPL | L7: =B17 -> 4 | M7: =D17 -> 103 | N7: =F17 -> 55620 | O7: =H17 -> 4000 | P7: =I17 -> 51620
A8: Total Passed | B8: =SUM('Assessment Tracker'!R2:R115) -> 1464 | D8: Total Failed | F8: Total Expenses (₹) | H8: Total Profit (₹) | K8: =A18 -> PMAY-G-STT | L8: =B18 -> 9 | M8: =D18 -> 103 | N8: =F18 -> 74160 | O8: =H18 -> 0 | P8: =I18 -> 74160
D9: =SUM('Assessment Tracker'!S2:S115) -> 13 | F9: =SUM('Assessment Tracker'!AF2:AF115) -> 73090 | H9: =H7-F9 -> 597310
K10: CHART DATA (Assessor-wise)
A11: 📈 SCHEME-WISE SUMMARY | K11: Assessor | L11: Batches | M11: Candidates | N11: Passed | O11: Pass % | P11: Assessor Fee
A12: Scheme | B12: Batches | D12: Candidates | F12: Income (₹) | H12: Expenses (₹) | I12: Profit (₹) | K12: =A22 -> Mohd Haseen | L12: =B22 -> 0 | M12: =D22 -> 0 | N12: =F22 -> 0 | O12: =H22 -> 0 | P12: =I22 -> 0
A13: ='Scheme Master'!B4 -> PMKVY 4.0 | B13: =COUNTIF('Assessment Tracker'!B2:B115,A13) -> 9 | D13: =SUMIF('Assessment Tracker'!B2:B115,A13,'Assessment Tracker'!N2:N115) -> 161 | F13: =SUMIF('Assessment Tracker'!B2:B115,A13,'Assessment Tracker'!AC2:AC115) -> 77280 | H13: =SUMIF('Assessment Tracker'!B2:B115,A13,'Assessment Tracker'!AF2:AF115) -> 14000 | I13: =F13-H13 -> 63280 | K13: =A23 -> Ram Assessor | L13: =B23 -> 0 | M13: =D23 -> 0 | N13: =F23 -> 0 | O13: =H23 -> 0 | P13: =I23 -> 0
A14: ='Scheme Master'!B5 -> DDUGKY | B14: =COUNTIF('Assessment Tracker'!B2:B115,A14) -> 2 | D14: =SUMIF('Assessment Tracker'!B2:B115,A14,'Assessment Tracker'!N2:N115) -> 54 | F14: =SUMIF('Assessment Tracker'!B2:B115,A14,'Assessment Tracker'!AC2:AC115) -> 38880 | H14: =SUMIF('Assessment Tracker'!B2:B115,A14,'Assessment Tracker'!AF2:AF115) -> 0 | I14: =F14-H14 -> 38880
A15: ='Scheme Master'!B6 -> ODOP-RPL | B15: =COUNTIF('Assessment Tracker'!B2:B115,A15) -> 8 | D15: =SUMIF('Assessment Tracker'!B2:B115,A15,'Assessment Tracker'!N2:N115) -> 188 | F15: =SUMIF('Assessment Tracker'!B2:B115,A15,'Assessment Tracker'!AC2:AC115) -> 101520 | H15: =SUMIF('Assessment Tracker'!B2:B115,A15,'Assessment Tracker'!AF2:AF115) -> 7690 | I15: =F15-H15 -> 93830 | K15: CHART DATA (Approval)
A16: =#REF! -> #REF! | B16: =COUNTIF('Assessment Tracker'!B2:B115,A16) -> 0 | D16: =SUMIF('Assessment Tracker'!B2:B115,A16,'Assessment Tracker'!N2:N115) -> 0 | F16: =SUMIF('Assessment Tracker'!B2:B115,A16,'Assessment Tracker'!AC2:AC115) -> 0 | H16: =SUMIF('Assessment Tracker'!B2:B115,A16,'Assessment Tracker'!AF2:AF115) -> 0 | I16: =F16-H16 -> 0
A17: ='Scheme Master'!B7 -> BSDMA-RPL | B17: =COUNTIF('Assessment Tracker'!B2:B115,A17) -> 4 | D17: =SUMIF('Assessment Tracker'!B2:B115,A17,'Assessment Tracker'!N2:N115) -> 103 | F17: =SUMIF('Assessment Tracker'!B2:B115,A17,'Assessment Tracker'!AC2:AC115) -> 55620 | H17: =SUMIF('Assessment Tracker'!B2:B115,A17,'Assessment Tracker'!AF2:AF115) -> 4000 | I17: =F17-H17 -> 51620 | K17: Status | L17: Count
A18: ='Scheme Master'!B8 -> PMAY-G-STT | B18: =COUNTIF('Assessment Tracker'!B2:B115,A18) -> 9 | D18: =SUMIF('Assessment Tracker'!B2:B115,A18,'Assessment Tracker'!N2:N115) -> 103 | F18: =SUMIF('Assessment Tracker'!B2:B115,A18,'Assessment Tracker'!AC2:AC115) -> 74160 | H18: =SUMIF('Assessment Tracker'!B2:B115,A18,'Assessment Tracker'!AF2:AF115) -> 0 | I18: =F18-H18 -> 74160 | K18: Auto-Approved | L18: =B27 -> 27
K19: Approval Required | L19: =B28 -> 4
A20: 👤 ASSESSOR-WISE SUMMARY | K20: Critical | L20: =B29 -> 0
A21: Assessor Name | B21: Batches | D21: Candidates | F21: Passed | H21: Pass % | I21: Assessor Fee (₹)
A22: Mohd Haseen | B22: =COUNTIF('Assessment Tracker'!X2:X115,"*Haseen*") -> 0 | D22: {=SUMPRODUCT((ISNUMBER(SEARCH("Haseen",'Assessment Tracker'!X2:X115)))*('Assessment Tracker'!N2:N115))} -> 0 | F22: {=SUMPRODUCT((ISNUMBER(SEARCH("Haseen",'Assessment Tracker'!X2:X115)))*('Assessment Tracker'!R2:R115))} -> 0 | H22: =IFERROR(F22/D22,0) -> 0 | I22: {=SUMPRODUCT((ISNUMBER(SEARCH("Haseen",'Assessment Tracker'!X2:X115)))*('Assessment Tracker'!AD2:AD115))} -> 0 | K22: CHART DATA (Pass/Fail)
A23: Ram Assessor | B23: =COUNTIF('Assessment Tracker'!X2:X115,A23) -> 0 | D23: =SUMIF('Assessment Tracker'!X2:X115,A23,'Assessment Tracker'!N2:N115) -> 0 | F23: =SUMIF('Assessment Tracker'!X2:X115,A23,'Assessment Tracker'!R2:R115) -> 0 | H23: =IFERROR(F23/D23,0) -> 0 | I23: =SUMIF('Assessment Tracker'!X2:X115,A23,'Assessment Tracker'!AD2:AD115) -> 0 | K23: Result | L23: Count
K24: Passed | L24: =B8 -> 1464
A25: ✅ APPROVAL STATUS | F25: 💰 EXPENSE % BY SCHEME | K25: Failed | L25: =SUM('Assessment Tracker'!S2:S115) -> 13
A26: Status | B26: Count | F26: Scheme | H26: Expense % | I26: Status
A27: ✅ Auto-Approved | B27: =COUNTIF('Assessment Tracker'!AI2:AI115,"*Auto*") -> 27 | F27: =A13 -> PMKVY 4.0 | H27: =IFERROR(H13/F13,0) -> 0.18115942 | I27: =IF(H27>0.5,"🔴 Over Budget",IF(H27>0.4,"⚠️ Warning","✅ Healthy")) -> ✅ Healthy
A28: ⚠️ Approval Required | B28: =COUNTIF('Assessment Tracker'!AI2:AI115,"*Approval Required*") -> 4 | F28: =A14 -> DDUGKY | H28: =IFERROR(H14/F14,0) -> 0 | I28: =IF(H28>0.5,"🔴 Over Budget",IF(H28>0.4,"⚠️ Warning","✅ Healthy")) -> ✅ Healthy
A29: 🔴 Critical - Over Budget | B29: =COUNTIF('Assessment Tracker'!AI2:AI115,"*Critical*") -> 0 | F29: =A15 -> ODOP-RPL | H29: =IFERROR(H15/F15,0) -> 0.075748621 | I29: =IF(H29>0.5,"🔴 Over Budget",IF(H29>0.4,"⚠️ Warning","✅ Healthy")) -> ✅ Healthy
F30: =A16 -> #REF! | H30: =IFERROR(H16/F16,0) -> 0 | I30: =IF(H30>0.5,"🔴 Over Budget",IF(H30>0.4,"⚠️ Warning","✅ Healthy")) -> ✅ Healthy
F31: =A17 -> BSDMA-RPL | H31: =IFERROR(H17/F17,0) -> 0.071916577 | I31: =IF(H31>0.5,"🔴 Over Budget",IF(H31>0.4,"⚠️ Warning","✅ Healthy")) -> ✅ Healthy
F32: =A18 -> PMAY-G-STT | H32: =IFERROR(H18/F18,0) -> 0 | I32: =IF(H32>0.5,"🔴 Over Budget",IF(H32>0.4,"⚠️ Warning","✅ Healthy")) -> ✅ Healthy
